Workbook

Sheet Main
B1: {=_xlfn.SEQUENCE(,COUNTA(B2:V2))} -> 1 | C1: 2 | D1: 3 | E1: 4 | F1: 5 | G1: 6 | H1: 7 | I1: 8 | J1: 9 | K1: 10 | L1: 11 | M1: 12 | N1: 13 | O1: 14 | P1: 15 | Q1: 16 | R1: 17 | S1: 18 | T1: 19 | U1: 20
B2: CLIENTE | C2: DI /DSI DDE/DSE/DU-E | D2: N/REF | E2: S/REF | F2: AFRMM | G2: CE MERCANTE | H2: Alerta | I2: Prazo Contrato | J2: Contrato | K2: Descrição da Mercadoria | L2: PRAZO SOLICITADO | M2: Data de Registro | N2: Data de Desembaraço | O2: Unidade de Desembaraço | P2: CNPJ/MF PROCESSO | Q2: Processo Nacional | R2: DOSSIE | S2: PRAZO APOLICE (cobrar quando data estiver vermelha) | T2: Histórico | U2: MODAL
A3: =B3&" - "&COUNTIF($B$3:B3,B3) -> MAMMOET - 1 | B3: MAMMOET | C3: 2213721580 | D3: I-22/0968-MBG | F3: SUSPENSA | G3: 72205154296309 | H3: =EDATE(I3,-1) -> 45563 | I3: =EDATE(LEFT(L3,10),-1) -> 45593 | J3: CONTRATO DE LOCAÇÃO S/NR | K3: DISTRIBUIDOR DE CARGA METALICO, Fabricante Mammoet Lifting and Transport SAS, Modelo: HEB300- S235, ANO DE FABRICACAO: 2020, USADO,NUMERO DE EQUIPAMENTO: 200812-001; 200812-002; 200812-003; 200812-004; 200812-005; 200812-006; 200812-009; 200812-010. | L3: 28/11/2024 (REEXPORTADO) | M3: 44761 | N3: 44769 | O3: IRF - PORTO DE SUAPE | P3: 11426377000123 | R3: 202200158843967 | T3: 29/11/2024 - Reexportado através dos processos E-24/0382-MBG e E-24/0384-MBG 30/09/2024 - Cobrado procedimento a ser adotado 27/06/2024 - Juntada efetuada 27/06/2024 - Docs recebidos 17/06/2024 - Nuerario enviado, ag retorno 13/06/2024 - Prorrogação por mais 5 meses 03/06/2024 - Cobrado novamente 30/04/2024 - Cobrado procedimento a ser adotado 27/12/2023 - Juntada efetuada. 01/12/2023 - Enviado Numerario e RPR, ag retorno 22/11/2023 - Solicitado prorrogação por mais 6 meses 30/10/2023 - Cobrado procedimento a ser adotado 27/06/2023 - Juntada efetuada pelo DOSSIE 21/06/2023 - Documentação recebida 01/06/2023 - Cobrado novamente 03/05/2023 - Cobrado procedimento a ser adotado 22/09/2022 - Processo incluido no controle | U3: MARÍTIMO | V3: ="'"&SUBSTITUTE(T3,CHAR(10),"' + CHAR(13) + CHAR(10) + "&CHAR(10)&"'")&"'" -> '29/11/2024 - Reexportado através dos processos E-24/0382-MBG e E-24/0384-MBG' + CHAR(13) + CHAR(10) + '30/09/2024 - Cobrado procedimento a ser adotado' + CHAR(13) + CHAR(10) + '27/06/2024 - Juntada efetuada' + CHAR(13) + CHAR(10) + '27/06/2024 - Docs recebidos' + CHAR(13) + CHAR(10) + '17/06/2024 - Nuerario enviado, ag retorno' + CHAR(13) + CHAR(10) + '13/06/2024 - Prorrogação por mais 5 meses' + CHAR(13) + CHAR(10) + '03/06/2024 - Cobrado novamente' + CHAR(13) + CHAR(10) + '30/04/2024 - Cobrado procedimento a ser adotado' + CHAR(13) + CHAR(10) + '27/12/2023 - Juntada efetuada.' + CHAR(13) + CHAR(10) + '01/12/2023 - Enviado Numerario e RPR, ag retorno' + CHAR(13) + CHAR(10) + '22/11/2023 - Solicitado prorrogação por mais 6 meses' + CHAR(13) + CHAR(10) + '30/10/2023 - Cobrado procedimento a ser adotado' + CHAR(13) + CHAR(10) + '27/06/2023 - Juntada efetuada pelo DOSSIE' + CHAR(13) + CHAR(10) + '21/06/2023 - Documentação recebida' + CHAR(13) + CHAR(10) + '01/06/2023 - Cobrado novamente' + CHAR(13) + CHAR(10) + '03/05/2023 - Cobrado procedimento a ser adotado' + CHAR(13) + CHAR(10) + '22/09/2022 - Processo incluido no controle' | W3: {="WHEN "&_xlfn.SEQUENCE(COUNTA(B3:B56))&" THEN"&CHAR(10)&V3:V56} -> WHEN 1 THEN '29/11/2024 - Reexportado através dos processos E-24/0382-MBG e E-24/0384-MBG' + CHAR(13) + CHAR(10) + '30/09/2024 - Cobrado procedimento a ser adotado' + CHAR(13) + CHAR(10) + '27/06/2024 - Juntada efetuada' + CHAR(13) + CHAR(10) + '27/06/2024 - Docs recebidos' + CHAR(13) + CHAR(10) + '17/06/2024 - Nuerario enviado, ag retorno' + CHAR(13) + CHAR(10) + '13/06/2024 - Prorrogação por mais 5 meses' + CHAR(13) + CHAR(10) + '03/06/2024 - Cobrado novamente' + CHAR(13) + CHAR(10) + '30/04/2024 - Cobrado procedimento a ser adotado' + CHAR(13) + CHAR(10) + '27/12/2023 - Juntada efetuada.' + CHAR(13) + CHAR(10) + '01/12/2023 - Enviado Numerario e RPR, ag retorno' + CHAR(13) + CHAR(10) + '22/11/2023 - Solicitado prorrogação por mais 6 meses' + CHAR(13) + CHAR(10) + '30/10/2023 - Cobrado procedimento a ser adotado' + CHAR(13) + CHAR(10) + '27/06/2023 - Juntada efetuada pelo DOSSIE' + CHAR(13) + CHAR(10) + '21/06/2023 - Documentação recebida' + CHAR(13) + CHAR(10) + '01/06/2023 - Cobrado novamente' + CHAR(13) + CHAR(10) + '03/05/2023 - Cobrado procedimento a ser adotado' + CHAR(13) + CHAR(10) + '22/09/2022 - Processo incluido no controle' | X3: {="WHEN "&_xlfn.SEQUENCE(COUNTA(B3:B56))&" THEN"&CHAR(10)&"'"&UPPER(TRIM(K3:K56))&"'"} -> WHEN 1 THEN 'DISTRIBUIDOR DE CARGA METALICO, FABRICANTE MAMMOET LIFTING AND TRANSPORT SAS, MODELO: HEB300- S235, ANO DE FABRICACAO: 2020, USADO,NUMERO DE EQUIPAMENTO: 200812-001; 200812-002; 200812-003; 200812-004; 200812-005; 200812-006; 200812-009; 200812-010.'
A4: =B4&" - "&COUNTIF($B$3:B4,B4) -> MAMMOET - 2 | B4: MAMMOET | C4: 2406902926 | D4: I-24/0271-MBG | E4: CABOS E CONTRAPESO | F4: SUSPENSA | G4: 72405061514983 | H4: =EDATE(I4,-1) -> 45568 | I4: =EDATE(LEFT(L4,10),-1) -> 45599 | J4: CONTRATODE COMODATO DE 12/03/2024 | K4: CABOS DE AÇO, GALVANIZADO PARA GUINDASTE | L4: 03/12/2024 (REEXPORTADO) | M4: 45384 | N4: 45386 | O4: INST.PORT.USO PUBL.-SUATA SERV.LOG. LTDA. | P4: 11426377000123 | R4: 202400232144540 | T4: 29/11/2024 - Reexportado através dos processos E-24/0418-MBG 27/11/2024 - Cobrado novamente 01/11/2024 - Cobrado procedimento a ser adotado 29/10/2024 - Juntada efetuada 28/10/2024 - Docs recebidos 22/10/2024 - Numerario enviado, ag retorno 21/10/2024 - Solciitado prorrogaçao por mais 1 mes 14/10/2024 - Cobrado novamente 09/09/2024 - Cobrado procedimento a ser adotado 03/07/2024 - Juntada efetuada 02/07/2024 - Docs recebidos 25/06/2024 - Solicitado prorrogação por mais 4 meses, numerario enviado, ag retorno 10/06/2024 - Cobrado procedimento a ser adotado 03/06/2024 - Juntada efetuada 29/05/2024 - Docs recebidos 27/05/2024 - Enviado Numerario e RPR, ag retorno 21/05/2024 - Solicitado prorrogação por mais 1 mes 07/05/2024 - Cobrado procedimento a ser adotado 30/04/2024 - Processo incluído no controle | U4: MARÍTIMO | V4: ="'"&SUBSTITUTE(T4,CHAR(10),"' + CHAR(13) + CHAR(10) + "&CHAR(10)&"'")&"'" -> '29/11/2024 - Reexportado através dos processos E-24/0418-MBG' + CHAR(13) + CHAR(10) + '27/11/2024 - Cobrado novamente' + CHAR(13) + CHAR(10) + '01/11/2024 - Cobrado procedimento a ser adotado' + CHAR(13) + CHAR(10) + '29/10/2024 - Juntada efetuada' + CHAR(13) + CHAR(10) + '28/10/2024 - Docs recebidos' + CHAR(13) + CHAR(10) + '22/10/2024 - Numerario enviado, ag retorno' + CHAR(13) + CHAR(10) + '21/10/2024 - Solciitado prorrogaçao por mais 1 mes' + CHAR(13) + CHAR(10) + '14/10/2024 - Cobrado novamente' + CHAR(13) + CHAR(10) + '09/09/2024 - Cobrado procedimento a ser adotado' + CHAR(13) + CHAR(10) + '03/07/2024 - Juntada efetuada' + CHAR(13) + CHAR(10) + '02/07/2024 - Docs recebidos' + CHAR(13) + CHAR(10) + '25/06/2024 - Solicitado prorrogação por mais 4 meses, numerario enviado, ag retorno' + CHAR(13) + CHAR(10) + '10/06/2024 - Cobrado procedimento a ser adotado' + CHAR(13) + CHAR(10) + '03/06/2024 - Juntada efetuada' + CHAR(13) + CHAR(10) + '29/05/2024 - Docs recebidos' + CHAR(13) + CHAR(10) + '27/05/2024 - Enviado Numerario e RPR, ag retorno' + CHAR(13) + CHAR(10) + '21/05/2024 - Solicitado prorrogação por mais 1 mes' + CHAR(13) + CHAR(10) + '07/05/2024 - Cobrado procedimento a ser adotado' + CHAR(13) + CHAR(10) + '30/04/2024 - Processo incluído no controle' | W4: WHEN 2 THEN '29/11/2024 - Reexportado através dos processos E-24/0418-MBG' + CHAR(13) + CHAR(10) + '27/11/2024 - Cobrado novamente' + CHAR(13) + CHAR(10) + '01/11/2024 - Cobrado procedimento a ser adotado' + CHAR(13) + CHAR(10) + '29/10/2024 - Juntada efetuada' + CHAR(13) + CHAR(10) + '28/10/2024 - Docs recebidos' + CHAR(13) + CHAR(10) + '22/10/2024 - Numerario enviado, ag retorno' + CHAR(13) + CHAR(10) + '21/10/2024 - Solciitado prorrogaçao por mais 1 mes' + CHAR(13) + CHAR(10) + '14/10/2024 - Cobrado novamente' + CHAR(13) + CHAR(10) + '09/09/2024 - Cobrado procedimento a ser adotado' + CHAR(13) + CHAR(10) + '03/07/2024 - Juntada efetuada' + CHAR(13) + CHAR(10) + '02/07/2024 - Docs recebidos' + CHAR(13) + CHAR(10) + '25/06/2024 - Solicitado prorrogação por mais 4 meses, numerario enviado, ag retorno' + CHAR(13) + CHAR(10) + '10/06/2024 - Cobrado procedimento a ser adotado' + CHAR(13) + CHAR(10) + '03/06/2024 - Juntada efetuada' + CHAR(13) + CHAR(10) + '29/05/2024 - Docs recebidos' + CHAR(13) + CHAR(10) + '27/05/2024 - Enviado Numerario e RPR, ag retorno' + CHAR(13) + CHAR(10) + '21/05/2024 - Solicitado prorrogação por mais 1 mes' + CHAR(13) + CHAR(10) + '07/05/2024 - Cobrado procedimento a ser adotado' + CHAR(13) + CHAR(10) + '30/04/2024 - Processo incluído no controle' | X4: WHEN 2 THEN 'CABOS DE AÇO, GALVANIZADO PARA GUINDASTE'
A5: =B5&" - "&COUNTIF($B$3:B5,B5) -> MAMMOET - 3 | B5: MAMMOET | C5: 2215388101 | D5: I-22/1149-MBG | F5: SUSPENSA | G5: 72205156943263 | H5: =EDATE(I5,-1) -> 45577 | I5: =EDATE(LEFT(L5,10),-1) -> 45608 | J5: CONTRATO DE LOCAÇÃO S/NR | K5: DISTRIBUIDOR DE CARGA METALICO 3xHEB 500 Lg, Fabricante Servicios de Elevacion y Transporte- Mammoet Chile y Cia Ltda, Modelo:15104519-ENGDWG-F001-0, ANO DE FABRICACAO: 2022, USADO, NÚMERO DE EQUIPAMENTO: NA. | L5: 12/12/2024 (REEXPORTADO) | M5: 44783 | N5: 44785 | O5: IRF - PORTO DE SUAPE | P5: 11426377000123 | R5: 202200161707530 | T5: 29/11/2024 - Reexportado através do processo E-24/0406-MBG 27/11/2024 - Cobrado novamente 01/11/2024 - Cobrado procedimento a ser adotado 29/10/2024 - Juntada efetuada 28/10/2024 - Docs recebidos 22/10/2024 - Numerario enviado, ag retorno 21/10/2024 - Solciitado prorrogaçao por mais 1 mes 14/10/2024 - Cobrado novamente 30/09/2024 - Cobrado procedimento a ser adotado 13/06/2024 - Juntada efetuada 11/06/2024 - Docs recebidos 10/06/2024 - Numerario enviado, ag retorno 04/06/2024 - Prorrogação por mais 5 meses 03/06/2024 - Cobrado novamente 15/04/2024 - Cobrado procedimento a ser adotado 12/01/2024 - Juntada efetuada 12/01/2024 - Docs recebidos 04/01/2024 - Numerario e RPR enviados, agr retorno 03/01/2024 - Solicitado prorrogação por mais 4 meses 28/12/2023 - Cobrado novamente 21/11/2023 - Cobrado procedimento a ser adotado 10/07/2023 - Juntada efetuada através do DOSSIE 28/06/2023 - Docs recebidos 20/06/2023 - Numerario e TR enviado, ag retorno 19/06/2023 - Informado que será prorrogado por 6 meses 18/05/2023 - Cobrado procedimento a ser adotado 22/09/2022 - Processo incluido no controle | U5: MARÍTIMO | V5: ="'"&SUBSTITUTE(T5,CHAR(10),"' + CHAR(13) + CHAR(10) + "&CHAR(10)&"'")&"'" -> '29/11/2024 - Reexportado através do processo E-24/0406-MBG' + CHAR(13) + CHAR(10) + '27/11/2024 - Cobrado novamente' + CHAR(13) + CHAR(10) + '01/11/2024 - Cobrado procedimento a ser adotado' + CHAR(13) + CHAR(10) + '29/10/2024 - Juntada efetuada' + CHAR(13) + CHAR(10) + '28/10/2024 - Docs recebidos' + CHAR(13) + CHAR(10) + '22/10/2024 - Numerario enviado, ag retorno' + CHAR(13) + CHAR(10) + '21/10/2024 - Solciitado prorrogaçao por mais 1 mes' + CHAR(13) + CHAR(10) + '14/10/2024 - Cobrado novamente' + CHAR(13) + CHAR(10) + '30/09/2024 - Cobrado procedimento a ser adotado' + CHAR(13) + CHAR(10) + '13/06/2024 - Juntada efetuada' + CHAR(13) + CHAR(10) + '11/06/2024 - Docs recebidos' + CHAR(13) + CHAR(10) + '10/06/2024 - Numerario enviado, ag retorno' + CHAR(13) + CHAR(10) + '04/06/2024 - Prorrogação por mais 5 meses' + CHAR(13) + CHAR(10) + '03/06/2024 - Cobrado novamente' + CHAR(13) + CHAR(10) + '15/04/2024 - Cobrado procedimento a ser adotado' + CHAR(13) + CHAR(10) + '12/01/2024 - Juntada efetuada' + CHAR(13) + CHAR(10) + '12/01/2024 - Docs recebidos' + CHAR(13) + CHAR(10) + '04/01/2024 - Numerario e RPR enviados, agr retorno' + CHAR(13) + CHAR(10) + '03/01/2024 - Solicitado prorrogação por mais 4 meses' + CHAR(13) + CHAR(10) + '28/12/2023 - Cobrado novamente' + CHAR(13) + CHAR(10) + '21/11/2023 - Cobrado procedimento a ser adotado' + CHAR(13) + CHAR(10) + '10/07/2023 - Juntada efetuada através do DOSSIE' + CHAR(13) + CHAR(10) + '28/06/2023 - Docs recebidos' + CHAR(13) + CHAR(10) + '20/06/2023 - Numerario e TR enviado, ag retorno' + CHAR(13) + CHAR(10) + '19/06/2023 - Informado que será prorrogado por 6 meses' + CHAR(13) + CHAR(10) + '18/05/2023 - Cobrado procedimento a ser adotado' + CHAR(13) + CHAR(10) + '22/09/2022 - Processo incluido no controle' | W5: WHEN 3 THEN '29/11/2024 - Reexportado através do processo E-24/0406-MBG' + CHAR(13) + CHAR(10) + '27/11/2024 - Cobrado novamente' + CHAR(13) + CHAR(10) + '01/11/2024 - Cobrado procedimento a ser adotado' + CHAR(13) + CHAR(10) + '29/10/2024 - Juntada efetuada' + CHAR(13) + CHAR(10) + '28/10/2024 - Docs recebidos' + CHAR(13) + CHAR(10) + '22/10/2024 - Numerario enviado, ag retorno' + CHAR(13) + CHAR(10) + '21/10/2024 - Solciitado prorrogaçao por mais 1 mes' + CHAR(13) + CHAR(10) + '14/10/2024 - Cobrado novamente' + CHAR(13) + CHAR(10) + '30/09/2024 - Cobrado procedimento a ser adotado' + CHAR(13) + CHAR(10) + '13/06/2024 - Juntada efetuada' + CHAR(13) + CHAR(10) + '11/06/2024 - Docs recebidos' + CHAR(13) + CHAR(10) + '10/06/2024 - Numerario enviado, ag retorno' + CHAR(13) + CHAR(10) + '04/06/2024 - Prorrogação por mais 5 meses' + CHAR(13) + CHAR(10) + '03/06/2024 - Cobrado novamente' + CHAR(13) + CHAR(10) + '15/04/2024 - Cobrado procedimento a ser adotado' + CHAR(13) + CHAR(10) + '12/01/2024 - Juntada efetuada' + CHAR(13) + CHAR(10) + '12/01/2024 - Docs recebidos' + CHAR(13) + CHAR(10) + '04/01/2024 - Numerario e RPR enviados, agr retorno' + CHAR(13) + CHAR(10) + '03/01/2024 - Solicitado prorrogação por mais 4 meses' + CHAR(13) + CHAR(10) + '28/12/2023 - Cobrado novamente' + CHAR(13) + CHAR(10) + '21/11/2023 - Cobrado procedimento a ser adotado' + CHAR(13) + CHAR(10) + '10/07/2023 - Juntada efetuada através do DOSSIE' + CHAR(13) + CHAR(10) + '28/06/2023 - Docs recebidos' + CHAR(13) + CHAR(10) + '20/06/2023 - Numerario e TR enviado, ag retorno' + CHAR(13) + CHAR(10) + '19/06/2023 - Informado que será prorrogado por 6 meses' + CHAR(13) + CHAR(10) + '18/05/2023 - Cobrado procedimento a ser adotado' + CHAR(13) + CHAR(10) + '22/09/2022 - Processo incluido no controle' | X5: WHEN 3 THEN 'DISTRIBUIDOR DE CARGA METALICO 3XHEB 500 LG, FABRICANTE SERVICIOS DE ELEVACION Y TRANSPORTE- MAMMOET CHILE Y CIA LTDA, MODELO:15104519-ENGDWG-F001-0, ANO DE FABRICACAO: 2022, USADO, NÚMERO DE EQUIPAMENTO: NA.'
A6: =B6&" - "&COUNTIF($B$3:B6,B6) -> MAMMOET - 4 | B6: MAMMOET | C6: 2211469948 | D6: I-22/0680-MBG | E6: CC3800-1 | F6: SUSPENSA | G6: 102205138266757 | H6: =EDATE(I6,-1) -> 45585 | I6: =EDATE(LEFT(L6,10),-1) -> 45616 | J6: S/NR. | K6: Guindaste autopropelido sobre esteiras, novo, marca Terex-Demag, modelo CC 38.650-1, número de série 36254, ano de fabricação 2022, número da frota 003380, computadorizado, acionado por motor diesel, capacidade de 650 toneladas, superlift, contrapesos, com todos acessórios para seu funcionamento, desmontado parcialmente para manuseio e transporte. | L6: 20/12/2024 (REEXPORTADO) | M6: 44729 | N6: 44741 | O6: PORTO DE SALVADOR - CODEBA | P6: 11426377000123 | R6: 202200155225677 | T6: 29/11/2024 - Reexportado através dos processos E-24/0419-MBG 25/11/2024 - Cobrado procedimento a ser adotado 19/11/2024 - Juntada efetuada 13/11/2024 - Docs recebidos 11/11/2024 - Numerario enviado, ag retorno 07/11/2024 - Solcicitado prorrogaçao por mais 1 mes 30/09/2024 - Cobrado procedimento a ser adotado 20/06/2024 - Juntada efetuada 14/06/2024 - Docs recebidos 04/06/2024 - Prorrogação por mais 5 meses, ag retorno 03/06/2024 - Cobrado novamente 30/04/2024 - Cobrado procedimento a ser adotado 19/12/2023 - Juntada efetuada 01/12/2023 - Enviado RPR, TR e Numerario, ag retorno 22/11/2023 - Solicitado renovação por mais 6 meses 26/10/2023 - Cobrado procedimento a ser adotado 28/07/2022 - Processo incluido no controle | U6: MARÍTIMO | V6: ="'"&SUBSTITUTE(T6,CHAR(10),"' + CHAR(13) + CHAR(10) + "&CHAR(10)&"'")&"'" -> '29/11/2024 - Reexportado através dos processos E-24/0419-MBG' + CHAR(13) + CHAR(10) + '25/11/2024 - Cobrado procedimento a ser adotado' + CHAR(13) + CHAR(10) + '19/11/2024 - Juntada efetuada' + CHAR(13) + CHAR(10) + '13/11/2024 - Docs recebidos' + CHAR(13) + CHAR(10) + '11/11/2024 - Numerario enviado, ag retorno' + CHAR(13) + CHAR(10) + '07/11/2024 - Solcicitado prorrogaçao por mais 1 mes' + CHAR(13) + CHAR(10) + '30/09/2024 - Cobrado procedimento a ser adotado' + CHAR(13) + CHAR(10) + '20/06/2024 - Juntada efetuada' + CHAR(13) + CHAR(10) + '14/06/2024 - Docs recebidos' + CHAR(13) + CHAR(10) + '04/06/2024 - Prorrogação por mais 5 meses, ag retorno' + CHAR(13) + CHAR(10) + '03/06/2024 - Cobrado novamente' + CHAR(13) + CHAR(10) + '30/04/2024 - Cobrado procedimento a ser adotado' + CHAR(13) + CHAR(10) + '19/12/2023 - Juntada efetuada' + CHAR(13) + CHAR(10) + '01/12/2023 - Enviado RPR, TR e Numerario, ag retorno' + CHAR(13) + CHAR(10) + '22/11/2023 - Solicitado renovação por mais 6 meses' + CHAR(13) + CHAR(10) + '26/10/2023 - Cobrado procedimento a ser adotado' + CHAR(13) + CHAR(10) + '28/07/2022 - Processo incluido no controle' | W6: WHEN 4 THEN '29/11/2024 - Reexportado através dos processos E-24/0419-MBG' + CHAR(13) + CHAR(10) + '25/11/2024 - Cobrado procedimento a ser adotado' + CHAR(13) + CHAR(10) + '19/11/2024 - Juntada efetuada' + CHAR(13) + CHAR(10) + '13/11/2024 - Docs recebidos' + CHAR(13) + CHAR(10) + '11/11/2024 - Numerario enviado, ag retorno' + CHAR(13) + CHAR(10) + '07/11/2024 - Solcicitado prorrogaçao por mais 1 mes' + CHAR(13) + CHAR(10) + '30/09/2024 - Cobrado procedimento a ser adotado' + CHAR(13) + CHAR(10) + '20/06/2024 - Juntada efetuada' + CHAR(13) + CHAR(10) + '14/06/2024 - Docs recebidos' + CHAR(13) + CHAR(10) + '04/06/2024 - Prorrogação por mais 5 meses, ag retorno' + CHAR(13) + CHAR(10) + '03/06/2024 - Cobrado novamente' + CHAR(13) + CHAR(10) + '30/04/2024 - Cobrado procedimento a ser adotado' + CHAR(13) + CHAR(10) + '19/12/2023 - Juntada efetuada' + CHAR(13) + CHAR(10) + '01/12/2023 - Enviado RPR, TR e Numerario, ag retorno' + CHAR(13) + CHAR(10) + '22/11/2023 - Solicitado renovação por mais 6 meses' + CHAR(13) + CHAR(10) + '26/10/2023 - Cobrado procedimento a ser adotado' + CHAR(13) + CHAR(10) + '28/07/2022 - Processo incluido no controle' | X6: WHEN 4 THEN 'GUINDASTE AUTOPROPELIDO SOBRE ESTEIRAS, NOVO, MARCA TEREX-DEMAG, MODELO CC 38.650-1, NÚMERO DE SÉRIE 36254, ANO DE FABRICAÇÃO 2022, NÚMERO DA FROTA 003380, COMPUTADORIZADO, ACIONADO POR MOTOR DIESEL, CAPACIDADE DE 650 TONELADAS, SUPERLIFT, CONTRAPESOS, COM TODOS ACESSÓRIOS PARA SEU FUNCIONAMENTO, DESMONTADO PARCIALMENTE PARA MANUSEIO E TRANSPORTE.'
A7: =B7&" - "&COUNTIF($B$3:B7,B7) -> DTA ENGENHARIA - 1 | B7: DTA ENGENHARIA | C7: 2411169727 | D7: I-24/1100-DTE | E7: DRAGA FENFORD | H7: =EDATE(I7,-1) -> 45595 | I7: =EDATE(LEFT(L7,10),-1) -> 45626 | J7: PERIODO DE FORNECIMENTO 2017 CONTRATO DE AFRETAMENTO POR TEMPO PARA EMBARCAÇÕES DE APOIO OFFSHORE | K7: NOME DO NAVIO: KENFORD TIPO DE NAVIO: DRAGA DE SUCÇÃO TRANSPORTADORA DE ARRASTO. IMO: 8821826 BANDEIRA: BELIZE, CLASSE: DRAGA DE ARRASTO I HULL MACH, CLASSIFICAÇÃO: BUREAU VERITAS, DISTINTIVO DE CHAMADA V3BE2, CONSTRUÇÃO: 1990, PAÍSES BAIXOS. ESTÁ EQUIPADO COM SALA DE MÁQUINAS, COM SALA DE BOMBAS DE PROA, NO DEPÓSITO DE TINTA, COM SALA DE AR-CONDICIONADO, COM SALA DO LEME, COM TREMONHA E NA PONTE. O NAVIO ESTÁ EQUIPADO COM UMA ACOMODAÇÃO PARA 14 PESSOAS. DIMENSÕES: COMPRIMENTO TOTAL: 81,8M, COMPRIMENTO ENTRE PERPENDICULARES: 76,95M, LARGURA MOLDADA: 14,00M, PROFUNDIDADE MOLDADA NA MEIA-NAU: 6,30M, CALADO DE VERÃO:4,20M, CALADO DA DRAGA:5,25M, ALTURA:24M, TONELAGEM (T): TONELAGEM BRUTA:2172, TONELAGEM LÍQUIDA:664, PESO MORTO:3369 TONELADAS, CAPACIDADE DA TREMONHA (PARTE SUPERIOR DA ARMAÇÃO):2500 M3, TUBO DE SUCÇÃO DE TRILHAMENTO:1 COM DIÂMETRO DE 800 MM, TUBO DE DESCARGA PARA A TREMONHA: DIÂMETRO 800 MM, TUBO DE DESCARGA PARA TERRA: DIÂMETRO 650 MM, PROFUNDIDADE DE DRAGAGEM: 25M, VELOCIDADE MÁXIMA:10 NÓS, POTÊNCIA TOTAL INSTALADA DO MOTOR DIESEL: 1956 KW, MOTORES PRINCIPAIS:2 MOTORES A DIESEL BOLNES DE 7 CILINDROS, TIPO 7DNL 190/600, CADA UM COM POTÊNCIA NOMINAL DE 978 KW/1330 HP, A 600 RPM, CADA UM ACIONANDO 1 HÉLICE DE PASSO FIXO POR MEIO DE UMA CAIXA DE REDUÇÃO MASON. GERADOR AUXILIAR: 2 MOTOR DIESEL CATERPILLAR DE 4 CILINDROS, TIPO CAT 3304(B) DI-T, COM POTÊNCIA NOMINAL DE 80KW A 1.500 RPM, ACIONANDO 1 GERADOR. GERADOR DE EMERGÊNCIA: N/A, HÉLICES: 2 HÉLICES DE PASSO FIXO DE BRONZE COM 4 PÁS EM BOCAIS FIXOS. PROPULSOR DE PROA: 1 MOTOR PRINCIPAL BOLNES, GERADORES ACIONADOS (494KW) E HÉLICE DE PASSO FIXO NO TÚNEL. BOMBA DE DRAGAGEM: 1 BOMBA DE PAREDE SIMPLES VOSTA,TIPO IHC 150-42,5-75, ACIONADA POR UM MOTOR A DIESEL DE 978KW/1330HP, 600RPM, FABRICADO EM BOLNES POR MEIO DE UMA CAIXA DE REDUÇÃO TIPO CEGONHA. BOMBA DE REFORÇO: 1 BOMBA DE PAREDE SIMPLES VOSTA, TIPO IHC 175-37,5-75, ACIONADA POR UM MOTOR DIESEL DE 932 KW/1258 HP, 1800 RPM, CATERPILLAR 3512 DI-TA, POR MEIO DE UMA CAIXA DE REDUÇÃO (STORK). BOMBAS DE JATO DÁGUA: 2 BOMBAS GIW DE 1250M3/H, CADA UMA COM 8 BAR, ACIONADAS POR 1 MOTOR DIESEL CATERPILLAR 3412, MARCA HGT 1-300315-180KW. CAPACIDADE DO TANQUE: ÓLEO COMBUSTÍVEL: 269,0 M3 ÓLEOS LUBRIFICANTES 5,6 M3 ÁGUA DOCE: 55,7 T GUINDASTES DE CONVÉS: 1 GUINDASTE HIDRÁULICO PALFINGER, SWL,990 QUILOGRAMAS A 7M E 1 GUINDASTE ELÉTRICO, SWL, 990 QUILOGRAMAS A 6M.ACOMODAÇÃO: A ACOMODAÇÃO CONSISTE EM 3 BELICHES. APARELHOS SALVA-VIDAS:2 BOTES SALVA-VIDAS PARA 16 PESSOAS CADA, 2 BOTES SALVA VIDAS PARA 8 PESSOAS CADA, 1 BARCO MOB COM MOTOR DE POPA DE 25 HP, VÁRIOS OUTROS EQUIPAMENTOS. | L7: 31/12/2024 (REEXPORTADO) | M7: 45439 | N7: 45439 | O7: PATIO DO PORTO DO RJ | P7: 2385674000187 | R7: 202400238873528 | T7: 26/12/2024 - Reexportaçao através do processo E-24/0425-DTE 01/11/2024 - Cobrado procedimento a ser adotado 25/06/2024 - Processo incluído no controle | U7: MEIOS PRÓPRIOS | V7: ="'"&SUBSTITUTE(T7,CHAR(10),"' + CHAR(13) + CHAR(10) + "&CHAR(10)&"'")&"'" -> '26/12/2024 - Reexportaçao através do processo E-24/0425-DTE' + CHAR(13) + CHAR(10) + '01/11/2024 - Cobrado procedimento a ser adotado' + CHAR(13) + CHAR(10) + '25/06/2024 - Processo incluído no controle' | W7: WHEN 5 THEN '26/12/2024 - Reexportaçao através do processo E-24/0425-DTE' + CHAR(13) + CHAR(10) + '01/11/2024 - Cobrado procedimento a ser adotado' + CHAR(13) + CHAR(10) + '25/06/2024 - Processo incluído no controle' | X7: WHEN 5 THEN 'NOME DO NAVIO: KENFORD TIPO DE NAVIO: DRAGA DE SUCÇÃO TRANSPORTADORA DE ARRASTO. IMO: 8821826 BANDEIRA: BELIZE, CLASSE: DRAGA DE ARRASTO I HULL MACH, CLASSIFICAÇÃO: BUREAU VERITAS, DISTINTIVO DE CHAMADA V3BE2, CONSTRUÇÃO: 1990, PAÍSES BAIXOS. ESTÁ EQUIPADO COM SALA DE MÁQUINAS, COM SALA DE BOMBAS DE PROA, NO DEPÓSITO DE TINTA, COM SALA DE AR-CONDICIONADO, COM SALA DO LEME, COM TREMONHA E NA PONTE. O NAVIO ESTÁ EQUIPADO COM UMA ACOMODAÇÃO PARA 14 PESSOAS. DIMENSÕES: COMPRIMENTO TOTAL: 81,8M, COMPRIMENTO ENTRE PERPENDICULARES: 76,95M, LARGURA MOLDADA: 14,00M, PROFUNDIDADE MOLDADA NA MEIA-NAU: 6,30M, CALADO DE VERÃO:4,20M, CALADO DA DRAGA:5,25M, ALTURA:24M, TONELAGEM (T): TONELAGEM BRUTA:2172, TONELAGEM LÍQUIDA:664, PESO MORTO:3369 TONELADAS, CAPACIDADE DA TREMONHA (PARTE SUPERIOR DA ARMAÇÃO):2500 M3, TUBO DE SUCÇÃO DE TRILHAMENTO:1 COM DIÂMETRO DE 800 MM, TUBO DE DESCARGA PARA A TREMONHA: DIÂMETRO 800 MM, TUBO DE DESCARGA PARA TERRA: DIÂMETRO 650 MM, PROFUNDIDADE DE DRAGAGEM: 25M, VELOCIDADE MÁXIMA:10 NÓS, POTÊNCIA TOTAL INSTALADA DO MOTOR DIESEL: 1956 KW, MOTORES PRINCIPAIS:2 MOTORES A DIESEL BOLNES DE 7 CILINDROS, TIPO 7DNL 190/600, CADA UM COM POTÊNCIA NOMINAL DE 978 KW/1330 HP, A 600 RPM, CADA UM ACIONANDO 1 HÉLICE DE PASSO FIXO POR MEIO DE UMA CAIXA DE REDUÇÃO MASON. GERADOR AUXILIAR: 2 MOTOR DIESEL CATERPILLAR DE 4 CILINDROS, TIPO CAT 3304(B) DI-T, COM POTÊNCIA NOMINAL DE 80KW A 1.500 RPM, ACIONANDO 1 GERADOR. GERADOR DE EMERGÊNCIA: N/A, HÉLICES: 2 HÉLICES DE PASSO FIXO DE BRONZE COM 4 PÁS EM BOCAIS FIXOS. PROPULSOR DE PROA: 1 MOTOR PRINCIPAL BOLNES, GERADORES ACIONADOS (494KW) E HÉLICE DE PASSO FIXO NO TÚNEL. BOMBA DE DRAGAGEM: 1 BOMBA DE PAREDE SIMPLES VOSTA,TIPO IHC 150-42,5-75, ACIONADA POR UM MOTOR A DIESEL DE 978KW/1330HP, 600RPM, FABRICADO EM BOLNES POR MEIO DE UMA CAIXA DE REDUÇÃO TIPO CEGONHA. BOMBA DE REFORÇO: 1 BOMBA DE PAREDE SIMPLES VOSTA, TIPO IHC 175-37,5-75, ACIONADA POR UM MOTOR DIESEL DE 932 KW/1258 HP, 1800 RPM, CATERPILLAR 3512 DI-TA, POR MEIO DE UMA CAIXA DE REDUÇÃO (STORK). BOMBAS DE JATO DÁGUA: 2 BOMBAS GIW DE 1250M3/H, CADA UMA COM 8 BAR, ACIONADAS POR 1 MOTOR DIESEL CATERPILLAR 3412, MARCA HGT 1-300315-180KW. CAPACIDADE DO TANQUE: ÓLEO COMBUSTÍVEL: 269,0 M3 ÓLEOS LUBRIFICANTES 5,6 M3 ÁGUA DOCE: 55,7 T GUINDASTES DE CONVÉS: 1 GUINDASTE HIDRÁULICO PALFINGER, SWL,990 QUILOGRAMAS A 7M E 1 GUINDASTE ELÉTRICO, SWL, 990 QUILOGRAMAS A 6M.ACOMODAÇÃO: A ACOMODAÇÃO CONSISTE EM 3 BELICHES. APARELHOS SALVA-VIDAS:2 BOTES SALVA-VIDAS PARA 16 PESSOAS CADA, 2 BOTES SALVA VIDAS PARA 8 PESSOAS CADA, 1 BARCO MOB COM MOTOR DE POPA DE 25 HP, VÁRIOS OUTROS EQUIPAMENTOS.'
A8: =B8&" - "&COUNTIF($B$3:B8,B8) -> MAMMOET - 5 | B8: MAMMOET | C8: 2111602972 | D8: I-21/0721-MBG | E8: LTM1500-8.1 | F8: PAGA | G8: 72105117508099 | H8: =EDATE(I8,-1) -> 45617 | I8: =EDATE(LEFT(L8,10),-1) -> 45647 | J8: CONTRATO DE LOCAÇÃO 2021060 | K8: Caminhão Guindaste sobre Pneu com lança telescópica até 50 metros, aditivo especial conectado JIB até 91 metros, capacidade máxima de elevação 500 toneladas, com 8 eixos totais sendo 2 eixos fixos + 6 eixos direcionáveis, parcialmente desmontado para transporte e manuseio, com peças e acessórios para montagem e operação. Marca Liebherr, modelo LTM1500-8.1, usado, ano de fabricação 2017, numero de série 095381. | L8: 45678 | M8: 44364 | N8: 44368 | O8: SUATA SERV. LOG-SUAPE | P8: 11426377000123 | R8: 202100109389832 | S8: 46190 | T8: 26/12/2024 - Cobrado procedimento a ser adotado 20/12/2024 - Juntada efetuada 19/12/2024 - Docs recebidos 25/11/2024 - Cobrado procedimento a ser adotado 21/11/2024 - Juntada efetuada 19/11/2024 - Docs recebidos 14/11/2024 - Numerario enviado, ag retorno 12/11/2024 - Solicitado prorrogação por mais 1 mes 30/09/2024 - Cobrado procedimento a ser adotado 21/08/2024 - Juntada efetuada 21/08/2024 - Docs recebidos 07/08/2024 - Numerario enviado, ag numerario 05/08/2024 - Solicitado prorrogação por mais 3 meses 25/07/2024 - Cobrado novamente 25/06/2024 - Cobrado procedimento a ser adotado 21/06/2024 - Juntada efetuada 19/06/2024 - Docs recebidos 10/06/2024 - Enviado Numerario, ag retorno 04/06/2024 -Solicitado prorrogação por mais 2 meses 03/06/2024 - Cobrado novamente 30/04/2024 - Cobrado procedimento a ser adotado 19/04/2024 - Juntada efetuada 12/04/2024 - Dcos recebidos 05/04/2024 - Numerario e TR enviados 04/04/2024 - Informado que será prorrogado por mais 2 meses 22/03/2024 - Cobrado novamente 23/02/2024 - Cobrado procedimento a ser adotado 18/09/2023 - Juntada efetuada pelo DOSSIE 04/09/2023 - Docs recebidos 27/07/2023 - Cobrado procedimento a ser adotado 21/07/2023 - Juntada da Apolice efetuada 20/07/2023 - Juntada efetuada sem Apolice, através do DOSSIE 18/07/2023 - Recebido docs, exceto Apolice 27/06/2023 - Numerario, TR e RPR enviados, ag retorno 21/06/2023 - Informado que será prorrogado por 2 meses 01/06/2023 - Cobrado procedimento a ser adotado 22/03/2023 - Recebido Apolice, juntado ao DOSSIE 21/03/2023 - Juntada efetuada, ag Apolice 21/03/2023 - Docs recebidos exceto Apolice. 01/02/2023 - Enviado Numerario, RPR e TR, aguardando retorno 26/01/2023 - Informado que a prorrogação será até 08/2023 24/01/2023 - Cobrado procedimento a ser adotado 20/12/2022 - Juntada efetuada no DOSSIE 19/12/2022 - Docs recebidos 22/11/2022 - Cobrado novamente 25/10/2022 - Cobrado procedimento a ser adotado 25/06/2021 - Processo incluido no controle | U8: MARÍTIMO | V8: ="'"&SUBSTITUTE(T8,CHAR(10),"' + CHAR(13) + CHAR(10) + "&CHAR(10)&"'")&"'" -> '26/12/2024 - Cobrado procedimento a ser adotado' + CHAR(13) + CHAR(10) + '20/12/2024 - Juntada efetuada' + CHAR(13) + CHAR(10) + '19/12/2024 - Docs recebidos' + CHAR(13) + CHAR(10) + '25/11/2024 - Cobrado procedimento a ser adotado' + CHAR(13) + CHAR(10) + '21/11/2024 - Juntada efetuada' + CHAR(13) + CHAR(10) + '19/11/2024 - Docs recebidos' + CHAR(13) + CHAR(10) + '14/11/2024 - Numerario enviado, ag retorno' + CHAR(13) + CHAR(10) + '12/11/2024 - Solicitado prorrogação por mais 1 mes' + CHAR(13) + CHAR(10) + '30/09/2024 - Cobrado procedimento a ser adotado' + CHAR(13) + CHAR(10) + '21/08/2024 - Juntada efetuada' + CHAR(13) + CHAR(10) + '21/08/2024 - Docs recebidos' + CHAR(13) + CHAR(10) + '07/08/2024 - Numerario enviado, ag numerario' + CHAR(13) + CHAR(10) + '05/08/2024 - Solicitado prorrogação por mais 3 meses' + CHAR(13) + CHAR(10) + '25/07/2024 - Cobrado novamente' + CHAR(13) + CHAR(10) + '25/06/2024 - Cobrado procedimento a ser adotado' + CHAR(13) + CHAR(10) + '21/06/2024 - Juntada efetuada' + CHAR(13) + CHAR(10) + '19/06/2024 - Docs recebidos' + CHAR(13) + CHAR(10) + '10/06/2024 - Enviado Numerario, ag retorno' + CHAR(13) + CHAR(10) + '04/06/2024 -Solicitado prorrogação por mais 2 meses' + CHAR(13) + CHAR(10) + '03/06/2024 - Cobrado novamente' + CHAR(13) + CHAR(10) + '30/04/2024 - Cobrado procedimento a ser adotado' + CHAR(13) + CHAR(10) + '19/04/2024 - Juntada efetuada' + CHAR(13) + CHAR(10) + '12/04/2024 - Dcos recebidos' + CHAR(13) + CHAR(10) + '05/04/2024 - Numerario e TR enviados' + CHAR(13) + CHAR(10) + '04/04/2024 - Informado que será prorrogado por mais 2 meses' + CHAR(13) + CHAR(10) + '22/03/2024 - Cobrado novamente' + CHAR(13) + CHAR(10) + '23/02/2024 - Cobrado procedimento a ser adotado' + CHAR(13) + CHAR(10) + '18/09/2023 - Juntada efetuada pelo DOSSIE' + CHAR(13) + CHAR(10) + '04/09/2023 - Docs recebidos' + CHAR(13) + CHAR(10) + '27/07/2023 - Cobrado procedimento a ser adotado' + CHAR(13) + CHAR(10) + '21/07/2023 - Juntada da Apolice efetuada' + CHAR(13) + CHAR(10) + '20/07/2023 - Juntada efetuada sem Apolice, através do DOSSIE' + CHAR(13) + CHAR(10) + '18/07/2023 - Recebido docs, exceto Apolice' + CHAR(13) + CHAR(10) + '27/06/2023 - Numerario, TR e RPR enviados, ag retorno' + CHAR(13) + CHAR(10) + '21/06/2023 - Informado que será prorrogado por 2 meses' + CHAR(13) + CHAR(10) + '01/06/2023 - Cobrado procedimento a ser adotado' + CHAR(13) + CHAR(10) + '22/03/2023 - Recebido Apolice, juntado ao DOSSIE' + CHAR(13) + CHAR(10) + '21/03/2023 - Juntada efetuada, ag Apolice' + CHAR(13) + CHAR(10) + '21/03/2023 - Docs recebidos exceto Apolice.' + CHAR(13) + CHAR(10) + '01/02/2023 - Enviado Numerario, RPR e TR, aguardando retorno' + CHAR(13) + CHAR(10) + '26/01/2023 - Informado que a prorrogação será até 08/2023' + CHAR(13) + CHAR(10) + '24/01/2023 - Cobrado procedimento a ser adotado' + CHAR(13) + CHAR(10) + '20/12/2022 - Juntada efetuada no DOSSIE' + CHAR(13) + CHAR(10) + '19/12/2022 - Docs recebidos' + CHAR(13) + CHAR(10) + '22/11/2022 - Cobrado novamente' + CHAR(13) + CHAR(10) + '25/10/2022 - Cobrado procedimento a ser adotado' + CHAR(13) + CHAR(10) + '25/06/2021 - Processo incluido no controle' | W8: WHEN 6 THEN '26/12/2024 - Cobrado procedimento a ser adotado' + CHAR(13) + CHAR(10) + '20/12/2024 - Juntada efetuada' + CHAR(13) + CHAR(10) + '19/12/2024 - Docs recebidos' + CHAR(13) + CHAR(10) + '25/11/2024 - Cobrado procedimento a ser adotado' + CHAR(13) + CHAR(10) + '21/11/2024 - Juntada efetuada' + CHAR(13) + CHAR(10) + '19/11/2024 - Docs recebidos' + CHAR(13) + CHAR(10) + '14/11/2024 - Numerario enviado, ag retorno' + CHAR(13) + CHAR(10) + '12/11/2024 - Solicitado prorrogação por mais 1 mes' + CHAR(13) + CHAR(10) + '30/09/2024 - Cobrado procedimento a ser adotado' + CHAR(13) + CHAR(10) + '21/08/2024 - Juntada efetuada' + CHAR(13) + CHAR(10) + '21/08/2024 - Docs recebidos' + CHAR(13) + CHAR(10) + '07/08/2024 - Numerario enviado, ag numerario' + CHAR(13) + CHAR(10) + '05/08/2024 - Solicitado prorrogação por mais 3 meses' + CHAR(13) + CHAR(10) + '25/07/2024 - Cobrado novamente' + CHAR(13) + CHAR(10) + '25/06/2024 - Cobrado procedimento a ser adotado' + CHAR(13) + CHAR(10) + '21/06/2024 - Juntada efetuada' + CHAR(13) + CHAR(10) + '19/06/2024 - Docs recebidos' + CHAR(13) + CHAR(10) + '10/06/2024 - Enviado Numerario, ag retorno' + CHAR(13) + CHAR(10) + '04/06/2024 -Solicitado prorrogação por mais 2 meses' + CHAR(13) + CHAR(10) + '03/06/2024 - Cobrado novamente' + CHAR(13) + CHAR(10) + '30/04/2024 - Cobrado procedimento a ser adotado' + CHAR(13) + CHAR(10) + '19/04/2024 - Juntada efetuada' + CHAR(13) + CHAR(10) + '12/04/2024 - Dcos recebidos' + CHAR(13) + CHAR(10) + '05/04/2024 - Numerario e TR enviados' + CHAR(13) + CHAR(10) + '04/04/2024 - Informado que será prorrogado por mais 2 meses' + CHAR(13) + CHAR(10) + '22/03/2024 - Cobrado novamente' + CHAR(13) + CHAR(10) + '23/02/2024 - Cobrado procedimento a ser adotado' + CHAR(13) + CHAR(10) + '18/09/2023 - Juntada efetuada pelo DOSSIE' + CHAR(13) + CHAR(10) + '04/09/2023 - Docs recebidos' + CHAR(13) + CHAR(10) + '27/07/2023 - Cobrado procedimento a ser adotado' + CHAR(13) + CHAR(10) + '21/07/2023 - Juntada da Apolice efetuada' + CHAR(13) + CHAR(10) + '20/07/2023 - Juntada efetuada sem Apolice, através do DOSSIE' + CHAR(13) + CHAR(10) + '18/07/2023 - Recebido docs, exceto Apolice' + CHAR(13) + CHAR(10) + '27/06/2023 - Numerario, TR e RPR enviados, ag retorno' + CHAR(13) + CHAR(10) + '21/06/2023 - Informado que será prorrogado por 2 meses' + CHAR(13) + CHAR(10) + '01/06/2023 - Cobrado procedimento a ser adotado' + CHAR(13) + CHAR(10) + '22/03/2023 - Recebido Apolice, juntado ao DOSSIE' + CHAR(13) + CHAR(10) + '21/03/2023 - Juntada efetuada, ag Apolice' + CHAR(13) + CHAR(10) + '21/03/2023 - Docs recebidos exceto Apolice.' + CHAR(13) + CHAR(10) + '01/02/2023 - Enviado Numerario, RPR e TR, aguardando retorno' + CHAR(13) + CHAR(10) + '26/01/2023 - Informado que a prorrogação será até 08/2023' + CHAR(13) + CHAR(10) + '24/01/2023 - Cobrado procedimento a ser adotado' + CHAR(13) + CHAR(10) + '20/12/2022 - Juntada efetuada no DOSSIE' + CHAR(13) + CHAR(10) + '19/12/2022 - Docs recebidos' + CHAR(13) + CHAR(10) + '22/11/2022 - Cobrado novamente' + CHAR(13) + CHAR(10) + '25/10/2022 - Cobrado procedimento a ser adotado' + CHAR(13) + CHAR(10) + '25/06/2021 - Processo incluido no controle' | X8: WHEN 6 THEN 'CAMINHÃO GUINDASTE SOBRE PNEU COM LANÇA TELESCÓPICA ATÉ 50 METROS, ADITIVO ESPECIAL CONECTADO JIB ATÉ 91 METROS, CAPACIDADE MÁXIMA DE ELEVAÇÃO 500 TONELADAS, COM 8 EIXOS TOTAIS SENDO 2 EIXOS FIXOS + 6 EIXOS DIRECIONÁVEIS, PARCIALMENTE DESMONTADO PARA TRANSPORTE E MANUSEIO, COM PEÇAS E ACESSÓRIOS PARA MONTAGEM E OPERAÇÃO. MARCA LIEBHERR, MODELO LTM1500-8.1, USADO, ANO DE FABRICAÇÃO 2017, NUMERO DE SÉRIE 095381.'
A9: =B9&" - "&COUNTIF($B$3:B9,B9) -> KARINA - 1 | B9: KARINA | C9: 240010523748 | D9: E-24/0208-KRN | E9: EXP TEMPORARIA | H9: =EDATE(I9,-1) -> 45618 | I9: =EDATE(LEFT(L9,10),-1) -> 45648 | J9: CRONOGRAMA DE 20/06/2024 | K9: UNIDADE DE ACIONAMENTO EXTRUSORA E20 3F/1,1KW/I=16, DE MATERIAL EM AÇO, MODELO: M332.00256, NUMERO DE SERIE: 2021.3888.010.004, FABRICANTE: COLLIN LAB & PILOT SOLUTIONS GMBH | L9: 45679 | M9: 45467 | N9: 45468 | O9: AEROPORTO INTERNACIONAL DE SAO PAULO/GUARULHOS | P9: 51254159000173 | R9: 202400242169252 | T9: 26/12/2024 - Cobrado procedimento a ser adotado 18/12/2024 - Juntada efetuada 18/12/2024 - Docs recebidos 27/11/2024 - Informado que será reimportado 27/11/2024 - Cobrado novamente 28/10/2024 - Cobrado procedimento a ser adotado 23/10/2024 - Juntada efetuada 23/10/2024 - Docs recebidos 09/09/2024 - Cobrado procedimento a ser adotado 11/07/2024 - Processo incluído no controle | U9: AÉREO | V9: ="'"&SUBSTITUTE(T9,CHAR(10),"' + CHAR(13) + CHAR(10) + "&CHAR(10)&"'")&"'" -> '26/12/2024 - Cobrado procedimento a ser adotado' + CHAR(13) + CHAR(10) + '18/12/2024 - Juntada efetuada' + CHAR(13) + CHAR(10) + '18/12/2024 - Docs recebidos' + CHAR(13) + CHAR(10) + '27/11/2024 - Informado que será reimportado' + CHAR(13) + CHAR(10) + '27/11/2024 - Cobrado novamente' + CHAR(13) + CHAR(10) + '28/10/2024 - Cobrado procedimento a ser adotado' + CHAR(13) + CHAR(10) + '23/10/2024 - Juntada efetuada' + CHAR(13) + CHAR(10) + '23/10/2024 - Docs recebidos' + CHAR(13) + CHAR(10) + '09/09/2024 - Cobrado procedimento a ser adotado' + CHAR(13) + CHAR(10) + '11/07/2024 - Processo incluído no controle' | W9: WHEN 7 THEN '26/12/2024 - Cobrado procedimento a ser adotado' + CHAR(13) + CHAR(10) + '18/12/2024 - Juntada efetuada' + CHAR(13) + CHAR(10) + '18/12/2024 - Docs recebidos' + CHAR(13) + CHAR(10) + '27/11/2024 - Informado que será reimportado' + CHAR(13) + CHAR(10) + '27/11/2024 - Cobrado novamente' + CHAR(13) + CHAR(10) + '28/10/2024 - Cobrado procedimento a ser adotado' + CHAR(13) + CHAR(10) + '23/10/2024 - Juntada efetuada' + CHAR(13) + CHAR(10) + '23/10/2024 - Docs recebidos' + CHAR(13) + CHAR(10) + '09/09/2024 - Cobrado procedimento a ser adotado' + CHAR(13) + CHAR(10) + '11/07/2024 - Processo incluído no controle' | X9: WHEN 7 THEN 'UNIDADE DE ACIONAMENTO EXTRUSORA E20 3F/1,1KW/I=16, DE MATERIAL EM AÇO, MODELO: M332.00256, NUMERO DE SERIE: 2021.3888.010.004, FABRICANTE: COLLIN LAB & PILOT SOLUTIONS GMBH'
A10: =B10&" - "&COUNTIF($B$3:B10,B10) -> MEGASIL - 1 | B10: MEGASIL | C10: 2102189170 | D10: I-20/1533-MEG | E10: FORRAGEIRA+PLATAFORMA | F10: PAGA | G10: 152005271192929 | H10: =EDATE(I10,-1) -> 45630 | I10: =EDATE(LEFT(L10,10),-1) -> 45661 | J10: CONTRATO DE LOCAÇÃO Nº DH-MEGA17 | K10: DIVERSOS EQUIPAMENTOS CONFORME DI | L10: 45692 | M10: 44230 | N10: 44231 | O10: EADI AURORA - SOROCABA | P10: 2295964000130 | R10: 202100097363944 | T10: 26/12/2024 - Cobrado procedimento a ser adotado 23/03/2021 - Processo incluido no controle | U10: MARÍTIMO | V10: ="'"&SUBSTITUTE(T10,CHAR(10),"' + CHAR(13) + CHAR(10) + "&CHAR(10)&"'")&"'" -> '26/12/2024 - Cobrado procedimento a ser adotado' + CHAR(13) + CHAR(10) + '23/03/2021 - Processo incluido no controle' | W10: WHEN 8 THEN '26/12/2024 - Cobrado procedimento a ser adotado' + CHAR(13) + CHAR(10) + '23/03/2021 - Processo incluido no controle' | X10: WHEN 8 THEN 'DIVERSOS EQUIPAMENTOS CONFORME DI'
A11: =B11&" - "&COUNTIF($B$3:B11,B11) -> DTA ENGENHARIA - 2 | B11: DTA ENGENHARIA | C11: 2412607809 | D11: I-24/1261-DTE | E11: DRAGA ELBE | H11: =EDATE(I11,-1) -> 45644 | I11: =EDATE(LEFT(L11,10),-1) -> 45675 | J11: CONTRATO Nº 01 DE AFRETAMENTO DE DRAGA A CASCO NU | K11: DRAGA TSHD DE SUCÇÃO EM MOVIMENTO, M/V ELBE, CONSTRUÍDA EM 2007 NO ESTALEIRO BEN KIEN SHIPYARD, VIETNAM, REGISTRADA NO PORTO DE SLIEDRECH, DE BANDEIRA DOS PAISES BAIXOS, IMO NUMERO 9452842, INDICATIVO PBMK, A EMBARCAÇÃO ESTÁ EQUIPADO COM UM SISTEMA DE SUCÇÃO DE REBOQUE, DESPEJO E DESCARGA DE AREIA E LODO. ESTÁ EQUIPADA DE SALA DE MÁQUINAS, SALA DE BOMBA, LOJA DE TINTAS, QUARTO COM AR CONDICIONADO, SALA DE LEME, SALA DE HIDRÁULICA, 2 HOPPER (1 A BOMBORDO E 1 A ESTIBORDO), SALA DE CONVERSOR, SALA DE GERADOR, DE EMERGÊNCIA E PONTE. O NAVIO É EQUIPADO COM UM ALOJAMENTO PARA 13 PESSOAS. DRAGA AVALIADA EM 5.000.000,00 DIMENSÕES: COMPRIMENTO SOBRE TUDO: 77,15 M COMPRIMENTO PERPENDICULARES: 71,80 M BOCA MOLDADA: 15,00 M PROFUNDIDADE MEIA NAU MOLDADO: 5,70 M PROJECTO DE VERÃO: 4,45 M DRAGA PROJECTO: 6,10 M ALTURA: 28,85 M TONELAGEM (T): TONELAGEM BRUTA: 2472 TONELAGEM LIQUIDA: 741 PESO MORTO: 3341 MT CAPACIDADE HOPPER (TOPO DA BRAÇOLA): 2.800 M3 TUBO DE SUCÇÃO EM MOVIMENTO: 1 COM 800 MILÍMETROS DE DIÂMETRO TUBO DE DESCARGA PARA HOPER: 800 MILÍMETROS DE DIÂMETRO TUBO DE DESCARGA PARA TERRA: 600 MILÍMETROS DE DIÂMETRO PROFUNDIDADE DE DRAGAGEM: 30M VELOCIDADE MÁXIMA: 10,3 NÓS TOTAL DE ENERGIA A DIESEL INSTALADOS: 2.529 KW MOTORES PRICIPAIS: 2 MOTORES DIESEL DE 12 CILINDROS, MITSUBISHI, TIPO S12RMPTK, CADA UM DE 940 KW NOMINAL DE 1,600 RPM, DIRIGINDO UMA HÉLICE DE PASSO FIXO ATRAVÉS DE UMA CAIXA REDUTORA MASON. MOTORES AUXILIARES: 3 MOTORES DIESEL DE 6 CILINDROS, JOHN DEERE, TIPO 6090AFM85, DE 192KW NOMINAL DE 1,500 RPM, DE UNICA DIREÇÃO. MOTOR DE EMERGÊNCIA: 1 MOTOR DIESEL DE 6 CILINDROS, MITSUBISHI,TIPO 6D16T DE 106 KW NOMINAL DE 1500 RPM, DE UNICA DIREÇÃO. HÉLICES: 2 HÉLICES DE 5 PÁS DE BRONZE DE PASSO E BICOS FIXOS. MOTOR PROA: 1 MOTOR DIESEL, MITSUBSHI, HÉLICE DE PASSO FIXO CONDUZIDO EM TÚNEL DE 360KW. BOMBA DE DRAGAGEM: 1 BOMBA PARA DRAGAGEM VOSTA, TIPO VL 750, IMPULSIONADA POR UM MOTOR A DIESEL DE 870 KW MITSUBISHI, VIA CAIXA DE REDUÇÃO STORK. BOMBA DE MOVIMENTO: 1 BOMBA DE MOVIMENTO VOSTA, TIPO VL 750, IMPULSIONADA POR UM MOTOR A DIESEL DE 870 KW MITSUBISHI, VIA CAIXA DE REDUÇÃO STORK. BOMBAS DE JATO DE ÁGUA: 1 BOMBA GIW DE 2300 M3/H, DE 8 BAR, IMPULSIONADA POR UM MOTOR DIESEL, MITSHUBISHI DE 634 KW, COM REDUÇÃO VIA CAIXA MASON. CAPACIDADE DOS TANQUES DE: ÓLEO COMBUSTÍVEL: 219,0 M3 ÓLEOS LUBRIFICANTES: 13,0 M3 ÁGUA DOCE: 91,0 M3 GUINDASTES: 2 GRUAS HIDRÁULICAS PALFINGER, TIPO SWM, DE 7 TON ATÉ 10M. ACOMODAÇÕES: AS ACOMODAÇÕES CONSISTEM DE 5 DECKS. MEIOS DE SALVAÇÃO: 2 BOTES SALVA-VIDAS PARA CADA 16 PESSOAS, 1 BARCO MOB COM MOTOR DE POPA DE 25 HP. | L11: 45706 | M11: 45457 | N11: 45461 | O11: PORTO DE FORTALEZA - DOCAS DO CEARA | P11: 2385674000187 | R11: 202400241046459 | T11: 26/12/2024 - Cobrado procedimento a ser adotado 14/10/2024 - Juntada efetuada 14/10/2024 - Docs recebidos 07/10/2024 - Solicitado prorrogaçao por mais 3 meses, numerario e RPR enviados, ag retorno 14/08/2024 - Cobrado procedimento a ser adotado 22/07/2024 - Processo incluído no controle | U11: MEIOS PRÓPRIOS | V11: ="'"&SUBSTITUTE(T11,CHAR(10),"' + CHAR(13) + CHAR(10) + "&CHAR(10)&"'")&"'" -> '26/12/2024 - Cobrado procedimento a ser adotado' + CHAR(13) + CHAR(10) + '14/10/2024 - Juntada efetuada' + CHAR(13) + CHAR(10) + '14/10/2024 - Docs recebidos' + CHAR(13) + CHAR(10) + '07/10/2024 - Solicitado prorrogaçao por mais 3 meses, numerario e RPR enviados, ag retorno' + CHAR(13) + CHAR(10) + '14/08/2024 - Cobrado procedimento a ser adotado' + CHAR(13) + CHAR(10) + '22/07/2024 - Processo incluído no controle' | W11: WHEN 9 THEN '26/12/2024 - Cobrado procedimento a ser adotado' + CHAR(13) + CHAR(10) + '14/10/2024 - Juntada efetuada' + CHAR(13) + CHAR(10) + '14/10/2024 - Docs recebidos' + CHAR(13) + CHAR(10) + '07/10/2024 - Solicitado prorrogaçao por mais 3 meses, numerario e RPR enviados, ag retorno' + CHAR(13) + CHAR(10) + '14/08/2024 - Cobrado procedimento a ser adotado' + CHAR(13) + CHAR(10) + '22/07/2024 - Processo incluído no controle' | X11: WHEN 9 THEN 'DRAGA TSHD DE SUCÇÃO EM MOVIMENTO, M/V ELBE, CONSTRUÍDA EM 2007 NO ESTALEIRO BEN KIEN SHIPYARD, VIETNAM, REGISTRADA NO PORTO DE SLIEDRECH, DE BANDEIRA DOS PAISES BAIXOS, IMO NUMERO 9452842, INDICATIVO PBMK, A EMBARCAÇÃO ESTÁ EQUIPADO COM UM SISTEMA DE SUCÇÃO DE REBOQUE, DESPEJO E DESCARGA DE AREIA E LODO. ESTÁ EQUIPADA DE SALA DE MÁQUINAS, SALA DE BOMBA, LOJA DE TINTAS, QUARTO COM AR CONDICIONADO, SALA DE LEME, SALA DE HIDRÁULICA, 2 HOPPER (1 A BOMBORDO E 1 A ESTIBORDO), SALA DE CONVERSOR, SALA DE GERADOR, DE EMERGÊNCIA E PONTE. O NAVIO É EQUIPADO COM UM ALOJAMENTO PARA 13 PESSOAS. DRAGA AVALIADA EM 5.000.000,00 DIMENSÕES: COMPRIMENTO SOBRE TUDO: 77,15 M COMPRIMENTO PERPENDICULARES: 71,80 M BOCA MOLDADA: 15,00 M PROFUNDIDADE MEIA NAU MOLDADO: 5,70 M PROJECTO DE VERÃO: 4,45 M DRAGA PROJECTO: 6,10 M ALTURA: 28,85 M TONELAGEM (T): TONELAGEM BRUTA: 2472 TONELAGEM LIQUIDA: 741 PESO MORTO: 3341 MT CAPACIDADE HOPPER (TOPO DA BRAÇOLA): 2.800 M3 TUBO DE SUCÇÃO EM MOVIMENTO: 1 COM 800 MILÍMETROS DE DIÂMETRO TUBO DE DESCARGA PARA HOPER: 800 MILÍMETROS DE DIÂMETRO TUBO DE DESCARGA PARA TERRA: 600 MILÍMETROS DE DIÂMETRO PROFUNDIDADE DE DRAGAGEM: 30M VELOCIDADE MÁXIMA: 10,3 NÓS TOTAL DE ENERGIA A DIESEL INSTALADOS: 2.529 KW MOTORES PRICIPAIS: 2 MOTORES DIESEL DE 12 CILINDROS, MITSUBISHI, TIPO S12RMPTK, CADA UM DE 940 KW NOMINAL DE 1,600 RPM, DIRIGINDO UMA HÉLICE DE PASSO FIXO ATRAVÉS DE UMA CAIXA REDUTORA MASON. MOTORES AUXILIARES: 3 MOTORES DIESEL DE 6 CILINDROS, JOHN DEERE, TIPO 6090AFM85, DE 192KW NOMINAL DE 1,500 RPM, DE UNICA DIREÇÃO. MOTOR DE EMERGÊNCIA: 1 MOTOR DIESEL DE 6 CILINDROS, MITSUBISHI,TIPO 6D16T DE 106 KW NOMINAL DE 1500 RPM, DE UNICA DIREÇÃO. HÉLICES: 2 HÉLICES DE 5 PÁS DE BRONZE DE PASSO E BICOS FIXOS. MOTOR PROA: 1 MOTOR DIESEL, MITSUBSHI, HÉLICE DE PASSO FIXO CONDUZIDO EM TÚNEL DE 360KW. BOMBA DE DRAGAGEM: 1 BOMBA PARA DRAGAGEM VOSTA, TIPO VL 750, IMPULSIONADA POR UM MOTOR A DIESEL DE 870 KW MITSUBISHI, VIA CAIXA DE REDUÇÃO STORK. BOMBA DE MOVIMENTO: 1 BOMBA DE MOVIMENTO VOSTA, TIPO VL 750, IMPULSIONADA POR UM MOTOR A DIESEL DE 870 KW MITSUBISHI, VIA CAIXA DE REDUÇÃO STORK. BOMBAS DE JATO DE ÁGUA: 1 BOMBA GIW DE 2300 M3/H, DE 8 BAR, IMPULSIONADA POR UM MOTOR DIESEL, MITSHUBISHI DE 634 KW, COM REDUÇÃO VIA CAIXA MASON. CAPACIDADE DOS TANQUES DE: ÓLEO COMBUSTÍVEL: 219,0 M3 ÓLEOS LUBRIFICANTES: 13,0 M3 ÁGUA DOCE: 91,0 M3 GUINDASTES: 2 GRUAS HIDRÁULICAS PALFINGER, TIPO SWM, DE 7 TON ATÉ 10M. ACOMODAÇÕES: AS ACOMODAÇÕES CONSISTEM DE 5 DECKS. MEIOS DE SALVAÇÃO: 2 BOTES SALVA-VIDAS PARA CADA 16 PESSOAS, 1 BARCO MOB COM MOTOR DE POPA DE 25 HP.'
A12: =B12&" - "&COUNTIF($B$3:B12,B12) -> NEA TANKS - 1 | B12: NEA TANKS | C12: 240003252912 | D12: E-24/0052-NEA | H12: =EDATE(I12,-1) -> 45666 | I12: =EDATE(LEFT(L12,10),-1) -> 45697 | J12: CONTRATO Nº Nº BPCRC-014-2022-PRD | K12: DIVERSOS EQUIPAMENTOS CONFORME DI | L12: 45725 | M12: 45349 | N12: 45350 | O12: PORTO DE SANTOS - SP | P12: 10567976000102 | R12: 202400227845285 | T12: 29/11/2024 - Juntada efetuada 27/11/2024 - Docs recebidos 27/11/2024 - Cobrado novamente 18/10/2024 - Cobrado procedimento a ser adotado 09/10/2024 - Juntada efetuada 04/10/2024 - Docs recebidos 14/08/2024 - Cobrado procedimento a ser adotado 15/04/2024 - Processo incluído no controle | U12: AÉREO | V12: ="'"&SUBSTITUTE(T12,CHAR(10),"' + CHAR(13) + CHAR(10) + "&CHAR(10)&"'")&"'" -> '29/11/2024 - Juntada efetuada' + CHAR(13) + CHAR(10) + '27/11/2024 - Docs recebidos' + CHAR(13) + CHAR(10) + '27/11/2024 - Cobrado novamente' + CHAR(13) + CHAR(10) + '18/10/2024 - Cobrado procedimento a ser adotado' + CHAR(13) + CHAR(10) + '09/10/2024 - Juntada efetuada' + CHAR(13) + CHAR(10) + '04/10/2024 - Docs recebidos' + CHAR(13) + CHAR(10) + '14/08/2024 - Cobrado procedimento a ser adotado' + CHAR(13) + CHAR(10) + '15/04/2024 - Processo incluído no controle' | W12: WHEN 10 THEN '29/11/2024 - Juntada efetuada' + CHAR(13) + CHAR(10) + '27/11/2024 - Docs recebidos' + CHAR(13) + CHAR(10) + '27/11/2024 - Cobrado novamente' + CHAR(13) + CHAR(10) + '18/10/2024 - Cobrado procedimento a ser adotado' + CHAR(13) + CHAR(10) + '09/10/2024 - Juntada efetuada' + CHAR(13) + CHAR(10) + '04/10/2024 - Docs recebidos' + CHAR(13) + CHAR(10) + '14/08/2024 - Cobrado procedimento a ser adotado' + CHAR(13) + CHAR(10) + '15/04/2024 - Processo incluído no controle' | X12: WHEN 10 THEN 'DIVERSOS EQUIPAMENTOS CONFORME DI'
A13: =B13&" - "&COUNTIF($B$3:B13,B13) -> NEA TANKS - 2 | B13: NEA TANKS | C13: 240000198208 | D13: E-24/0004-NEA | H13: =EDATE(I13,-1) -> 45666 | I13: =EDATE(LEFT(L13,10),-1) -> 45697 | J13: CONTRATO Nº BPCRC-014-2022-PRD | K13: DIVERSOS EQUIPAMENTOS CONFORME DUE | L13: 45725 | M13: 45296 | N13: 45303 | O13: PORTO DE SANTOS - SP | P13: 10567976000102 | R13: 202400222101024 | T13: 29/11/2024 - Juntada efetuada 27/11/2024 - Cobrado novamente, docs recebidos 18/10/2024 - Cobrado procedimento a ser adotado 09/10/2024 - Juntada efetuada 04/10/2024 - Docs recebidos 14/08/2024 - Cobrado procedimento a ser adotado 16/02/2024 - Processo incluido no controle | U13: AÉREO | V13: ="'"&SUBSTITUTE(T13,CHAR(10),"' + CHAR(13) + CHAR(10) + "&CHAR(10)&"'")&"'" -> '29/11/2024 - Juntada efetuada' + CHAR(13) + CHAR(10) + '27/11/2024 - Cobrado novamente, docs recebidos' + CHAR(13) + CHAR(10) + '18/10/2024 - Cobrado procedimento a ser adotado' + CHAR(13) + CHAR(10) + '09/10/2024 - Juntada efetuada' + CHAR(13) + CHAR(10) + '04/10/2024 - Docs recebidos' + CHAR(13) + CHAR(10) + '14/08/2024 - Cobrado procedimento a ser adotado' + CHAR(13) + CHAR(10) + '16/02/2024 - Processo incluido no controle' | W13: WHEN 11 THEN '29/11/2024 - Juntada efetuada' + CHAR(13) + CHAR(10) + '27/11/2024 - Cobrado novamente, docs recebidos' + CHAR(13) + CHAR(10) + '18/10/2024 - Cobrado procedimento a ser adotado' + CHAR(13) + CHAR(10) + '09/10/2024 - Juntada efetuada' + CHAR(13) + CHAR(10) + '04/10/2024 - Docs recebidos' + CHAR(13) + CHAR(10) + '14/08/2024 - Cobrado procedimento a ser adotado' + CHAR(13) + CHAR(10) + '16/02/2024 - Processo incluido no controle' | X13: WHEN 11 THEN 'DIVERSOS EQUIPAMENTOS CONFORME DUE'
A14: =B14&" - "&COUNTIF($B$3:B14,B14) -> MAMMOET - 6 | B14: MAMMOET | C14: 2105759393 | D14: I-21/0343-MBG | E14: EXP-MUSA-12521 | F14: PAGA | G14: 132105065072039 | H14: =EDATE(I14,-1) -> 45683 | I14: =EDATE(LEFT(L14,10),-1) -> 45714 | J14: CONTRATO DE LOCAÇÃO S/NR DATADO DE 16/03/2021 | K14: Conjunto de Trilha Estreita usado para Guindaste Terex Demag CC 2800 - 1 com todas as peças e acessórios para montagem e operação, marca: Terex Demag, modelo: CC 2800-1, sem número de serie, ano de fabricação 2006. Uma seçao de Jib/lança de 12 metros usada para guindaste Terex-Demag CC 2800-1 com todas as peças e acessórios para montagem e operação, marca: Terex Demag, modelo: CC 2800-1, sem numero de série, ano de fabricação 2006.0 | L14: 45742 | M14: 44279 | N14: 44281 | O14: MULTIRIO-RJ | P14: 11426377000638 | R14: 202100103816828 | S14: 46105 | T14: 26/12/2024 - Juntada efetuada 23/12/2024 - Docs recebidos 29/11/2024 - Numerario enviado, ag retorno 28/11/2024 - Solicitado prorrogaçao por mais 3 mese 27/11/2024 - Cobrado procedimento a ser adotado 26/11/2024 - Juntada efetuada 22/11/2024 - Docs recebidos 14/11/2024 - Numerario enviado, ag retorno 12/11/2024 - Solicitado prorrogaçao por mais 1 mes 30/09/2024 - Cobrado procedimento a ser adotado 26/06/2024 - Juntada efetuada 26/06/2024 - Docs recebidos 14/06/2024 - Enviado Numerario, ag retorno 13/06/2024 - Solicitado prorrogação por mais 5 meses 03/06/2024 - Cobrado novamente 30/04/2024 - Cobrado procedimento a ser adotado 26/04/2024 - Juntada efetuada 19/04/2024 - Docs recebidos 05/04/2024 - Numerario e RPR enviados, ag retorno 04/04/2024 - Informado que será prorrogado por mais 2 meses 28/02/2024 - Cobrado procedimento a ser adotado 25/10/2023 - Juntada efetuada 23/10/2023 - Docs recebidos 06/10/2023 - RPR, TR e Numerario enviados, ag retorno 03/10/2023 - Solicitado prorrogação por mais 6 meses 30/08/2023 - Cobrado procedimento a ser adotado 25/07/2023 - Juntada efetuada atraves do DOSSIE 21/07/2023 - Docs recebidos 27/06/2023 - Enviado Numerario, TR e RPR, ag retorno 22/06/2023 - Solicitado renovação por 3 meses 01/06/2023 - Cobrado procedimento a ser adotado 23/03/2023 - Juntada efetuada através do DOSSIE 20/03/2023 - Recebido documentação 28/02/2023 - Cobrado novamente 31/01/2023 - Cobrado procedimento a ser adotado 25/03/2022 - Juntada anexada através do DOSSIE 17/02/2022 - Solicitado prorrogação por 12 meses, TR, RAT e Numerário enviados, aguardando retorno 27/01/2022 - Cobrado procedimento a ser adotado 24/09/2021 - Recebido documentos, juntada efetuada pelo DOSSIE 20/09/2021 - Cobrado novamente 27/08/2021 - Cobrado novamente, solicitado prorrogação por 6 meses, TR e Numerario enviados, aguardando retorno 27/07/2021 - Cobrado procedimento a ser adotado 11/05/2021 - Processo incluído no controle | U14: MARÍTIMO | V14: ="'"&SUBSTITUTE(T14,CHAR(10),"' + CHAR(13) + CHAR(10) + "&CHAR(10)&"'")&"'" -> '26/12/2024 - Juntada efetuada' + CHAR(13) + CHAR(10) + '23/12/2024 - Docs recebidos' + CHAR(13) + CHAR(10) + '29/11/2024 - Numerario enviado, ag retorno' + CHAR(13) + CHAR(10) + '28/11/2024 - Solicitado prorrogaçao por mais 3 mese' + CHAR(13) + CHAR(10) + '27/11/2024 - Cobrado procedimento a ser adotado' + CHAR(13) + CHAR(10) + '26/11/2024 - Juntada efetuada' + CHAR(13) + CHAR(10) + '22/11/2024 - Docs recebidos' + CHAR(13) + CHAR(10) + '14/11/2024 - Numerario enviado, ag retorno' + CHAR(13) + CHAR(10) + '12/11/2024 - Solicitado prorrogaçao por mais 1 mes' + CHAR(13) + CHAR(10) + '30/09/2024 - Cobrado procedimento a ser adotado' + CHAR(13) + CHAR(10) + '26/06/2024 - Juntada efetuada' + CHAR(13) + CHAR(10) + '26/06/2024 - Docs recebidos' + CHAR(13) + CHAR(10) + '14/06/2024 - Enviado Numerario, ag retorno' + CHAR(13) + CHAR(10) + '13/06/2024 - Solicitado prorrogação por mais 5 meses' + CHAR(13) + CHAR(10) + '03/06/2024 - Cobrado novamente' + CHAR(13) + CHAR(10) + '30/04/2024 - Cobrado procedimento a ser adotado' + CHAR(13) + CHAR(10) + '26/04/2024 - Juntada efetuada' + CHAR(13) + CHAR(10) + '19/04/2024 - Docs recebidos' + CHAR(13) + CHAR(10) + '05/04/2024 - Numerario e RPR enviados, ag retorno' + CHAR(13) + CHAR(10) + '04/04/2024 - Informado que será prorrogado por mais 2 meses' + CHAR(13) + CHAR(10) + '28/02/2024 - Cobrado procedimento a ser adotado' + CHAR(13) + CHAR(10) + '25/10/2023 - Juntada efetuada' + CHAR(13) + CHAR(10) + '23/10/2023 - Docs recebidos' + CHAR(13) + CHAR(10) + '06/10/2023 - RPR, TR e Numerario enviados, ag retorno' + CHAR(13) + CHAR(10) + '03/10/2023 - Solicitado prorrogação por mais 6 meses' + CHAR(13) + CHAR(10) + '30/08/2023 - Cobrado procedimento a ser adotado' + CHAR(13) + CHAR(10) + '25/07/2023 - Juntada efetuada atraves do DOSSIE' + CHAR(13) + CHAR(10) + '21/07/2023 - Docs recebidos' + CHAR(13) + CHAR(10) + '27/06/2023 - Enviado Numerario, TR e RPR, ag retorno' + CHAR(13) + CHAR(10) + '22/06/2023 - Solicitado renovação por 3 meses' + CHAR(13) + CHAR(10) + '01/06/2023 - Cobrado procedimento a ser adotado' + CHAR(13) + CHAR(10) + '23/03/2023 - Juntada efetuada através do DOSSIE' + CHAR(13) + CHAR(10) + '20/03/2023 - Recebido documentação' + CHAR(13) + CHAR(10) + '28/02/2023 - Cobrado novamente' + CHAR(13) + CHAR(10) + '31/01/2023 - Cobrado procedimento a ser adotado' + CHAR(13) + CHAR(10) + '25/03/2022 - Juntada anexada através do DOSSIE' + CHAR(13) + CHAR(10) + '17/02/2022 - Solicitado prorrogação por 12 meses, TR, RAT e Numerário enviados, aguardando retorno' + CHAR(13) + CHAR(10) + '27/01/2022 - Cobrado procedimento a ser adotado' + CHAR(13) + CHAR(10) + '24/09/2021 - Recebido documentos, juntada efetuada pelo DOSSIE' + CHAR(13) + CHAR(10) + '20/09/2021 - Cobrado novamente' + CHAR(13) + CHAR(10) + '27/08/2021 - Cobrado novamente, solicitado prorrogação por 6 meses, TR e Numerario enviados, aguardando retorno' + CHAR(13) + CHAR(10) + '27/07/2021 - Cobrado procedimento a ser adotado' + CHAR(13) + CHAR(10) + '11/05/2021 - Processo incluído no controle' | W14: WHEN 12 THEN '26/12/2024 - Juntada efetuada' + CHAR(13) + CHAR(10) + '23/12/2024 - Docs recebidos' + CHAR(13) + CHAR(10) + '29/11/2024 - Numerario enviado, ag retorno' + CHAR(13) + CHAR(10) + '28/11/2024 - Solicitado prorrogaçao por mais 3 mese' + CHAR(13) + CHAR(10) + '27/11/2024 - Cobrado procedimento a ser adotado' + CHAR(13) + CHAR(10) + '26/11/2024 - Juntada efetuada' + CHAR(13) + CHAR(10) + '22/11/2024 - Docs recebidos' + CHAR(13) + CHAR(10) + '14/11/2024 - Numerario enviado, ag retorno' + CHAR(13) + CHAR(10) + '12/11/2024 - Solicitado prorrogaçao por mais 1 mes' + CHAR(13) + CHAR(10) + '30/09/2024 - Cobrado procedimento a ser adotado' + CHAR(13) + CHAR(10) + '26/06/2024 - Juntada efetuada' + CHAR(13) + CHAR(10) + '26/06/2024 - Docs recebidos' + CHAR(13) + CHAR(10) + '14/06/2024 - Enviado Numerario, ag retorno' + CHAR(13) + CHAR(10) + '13/06/2024 - Solicitado prorrogação por mais 5 meses' + CHAR(13) + CHAR(10) + '03/06/2024 - Cobrado novamente' + CHAR(13) + CHAR(10) + '30/04/2024 - Cobrado procedimento a ser adotado' + CHAR(13) + CHAR(10) + '26/04/2024 - Juntada efetuada' + CHAR(13) + CHAR(10) + '19/04/2024 - Docs recebidos' + CHAR(13) + CHAR(10) + '05/04/2024 - Numerario e RPR enviados, ag retorno' + CHAR(13) + CHAR(10) + '04/04/2024 - Informado que será prorrogado por mais 2 meses' + CHAR(13) + CHAR(10) + '28/02/2024 - Cobrado procedimento a ser adotado' + CHAR(13) + CHAR(10) + '25/10/2023 - Juntada efetuada' + CHAR(13) + CHAR(10) + '23/10/2023 - Docs recebidos' + CHAR(13) + CHAR(10) + '06/10/2023 - RPR, TR e Numerario enviados, ag retorno' + CHAR(13) + CHAR(10) + '03/10/2023 - Solicitado prorrogação por mais 6 meses' + CHAR(13) + CHAR(10) + '30/08/2023 - Cobrado procedimento a ser adotado' + CHAR(13) + CHAR(10) + '25/07/2023 - Juntada efetuada atraves do DOSSIE' + CHAR(13) + CHAR(10) + '21/07/2023 - Docs recebidos' + CHAR(13) + CHAR(10) + '27/06/2023 - Enviado Numerario, TR e RPR, ag retorno' + CHAR(13) + CHAR(10) + '22/06/2023 - Solicitado renovação por 3 meses' + CHAR(13) + CHAR(10) + '01/06/2023 - Cobrado procedimento a ser adotado' + CHAR(13) + CHAR(10) + '23/03/2023 - Juntada efetuada através do DOSSIE' + CHAR(13) + CHAR(10) + '20/03/2023 - Recebido documentação' + CHAR(13) + CHAR(10) + '28/02/2023 - Cobrado novamente' + CHAR(13) + CHAR(10) + '31/01/2023 - Cobrado procedimento a ser adotado' + CHAR(13) + CHAR(10) + '25/03/2022 - Juntada anexada através do DOSSIE' + CHAR(13) + CHAR(10) + '17/02/2022 - Solicitado prorrogação por 12 meses, TR, RAT e Numerário enviados, aguardando retorno' + CHAR(13) + CHAR(10) + '27/01/2022 - Cobrado procedimento a ser adotado' + CHAR(13) + CHAR(10) + '24/09/2021 - Recebido documentos, juntada efetuada pelo DOSSIE' + CHAR(13) + CHAR(10) + '20/09/2021 - Cobrado novamente' + CHAR(13) + CHAR(10) + '27/08/2021 - Cobrado novamente, solicitado prorrogação por 6 meses, TR e Numerario enviados, aguardando retorno' + CHAR(13) + CHAR(10) + '27/07/2021 - Cobrado procedimento a ser adotado' + CHAR(13) + CHAR(10) + '11/05/2021 - Processo incluído no controle' | X14: WHEN 12 THEN 'CONJUNTO DE TRILHA ESTREITA USADO PARA GUINDASTE TEREX DEMAG CC 2800 - 1 COM TODAS AS PEÇAS E ACESSÓRIOS PARA MONTAGEM E OPERAÇÃO, MARCA: TEREX DEMAG, MODELO: CC 2800-1, SEM NÚMERO DE SERIE, ANO DE FABRICAÇÃO 2006. UMA SEÇAO DE JIB/LANÇA DE 12 METROS USADA PARA GUINDASTE TEREX-DEMAG CC 2800-1 COM TODAS AS PEÇAS E ACESSÓRIOS PARA MONTAGEM E OPERAÇÃO, MARCA: TEREX DEMAG, MODELO: CC 2800-1, SEM NUMERO DE SÉRIE, ANO DE FABRICAÇÃO 2006.0'
A15: =B15&" - "&COUNTIF($B$3:B15,B15) -> MAMMOET - 7 | B15: MAMMOET | C15: 2306782082 | D15: I-23/0175-MBG | E15: REP. DOMINICANA | F15: SUSPENSA | G15: 132305053620239 | H15: =EDATE(I15,-1) -> 45685 | I15: =EDATE(LEFT(L15,10),-1) -> 45716 | J15: CONTRATO DE ALUGUEL DE 26/03/2023 | K15: POWER PACK DE MOVIMENTO RETILÍNEO (CILINDROS), MARCA GOLDHOFER AKTIENGESELLSCHAFT, MODELO PFV-490/60-31, NÚMERO DE SÉRIE 61402, FROTA 302920, ANO DE FABRICAÇÃO 2016, USADO, COM DISPOSITIVOS E FERRAMENTAS DE MONTAGEM E ACESSÓRIOS NECESSÁRIOS PARA OPERAÇÃO. | L15: 45746 | M15: 45026 | N15: 45029 | O15: ICTSI RIO BRASIL TERMINAL 1 SA - RIO DE JANEIRO/RJ | P15: 11426377000123 | R15: 202300188957138 | T15: 29/11/2024 - Juntada efetuada 27/11/2024 - Docs recebidos 25/11/2024 - Numerario enviado, ag retorno 22/11/2024 - Solicitado prorrogaçao por mais 4 meses 30/09/2024 - Cobrado procedimento a ser adotado 30/08/2024 - Juntada efetuada 29/08/2024 - Docs recebidos 22/08/2024 - Numerario e RPR enviados, ag retorno 21/08/2024 - Prorrogação por mais 3 meses 14/08/2024 - Cobrado novamente 02/07/2024 - Cobrado procedimento a ser adotado 25/06/2024 - Juntada efetuada 25/06/2024 - Docs recebidos 17/06/2024 - Numerario enviado, ag retorno 13/06/2024 - Prorrogaçao por mais 2 meses 30/04/2024 - Cobrado procedimento a ser adotado 28/03/2024 - Juntada efetuada 27/03/2024 - Recebido docs 13/03/2024 - Enviado Numerario e RPR, ag retorno 12/03/2024 - Solicitado prorrogação por mais 3 meses 01/02/2024 - Cobrado procedimento a ser adotado 27/10/2023 - Juntada efetuada 26/10/2023 - Docs recebidos 06/10/2023 - RPR e Numerario enviados, ag retorno 03/10/2023 - Solicitado prorrogação por mais 5 meses 30/08/2023 - Cobrado procedimento a ser adotado 11/07/2023 - Processo incluido no controle | U15: MARÍTIMO | V15: ="'"&SUBSTITUTE(T15,CHAR(10),"' + CHAR(13) + CHAR(10) + "&CHAR(10)&"'")&"'" -> '29/11/2024 - Juntada efetuada' + CHAR(13) + CHAR(10) + '27/11/2024 - Docs recebidos' + CHAR(13) + CHAR(10) + '25/11/2024 - Numerario enviado, ag retorno' + CHAR(13) + CHAR(10) + '22/11/2024 - Solicitado prorrogaçao por mais 4 meses' + CHAR(13) + CHAR(10) + '30/09/2024 - Cobrado procedimento a ser adotado' + CHAR(13) + CHAR(10) + '30/08/2024 - Juntada efetuada' + CHAR(13) + CHAR(10) + '29/08/2024 - Docs recebidos' + CHAR(13) + CHAR(10) + '22/08/2024 - Numerario e RPR enviados, ag retorno' + CHAR(13) + CHAR(10) + '21/08/2024 - Prorrogação por mais 3 meses' + CHAR(13) + CHAR(10) + '14/08/2024 - Cobrado novamente' + CHAR(13) + CHAR(10) + '02/07/2024 - Cobrado procedimento a ser adotado' + CHAR(13) + CHAR(10) + '25/06/2024 - Juntada efetuada' + CHAR(13) + CHAR(10) + '25/06/2024 - Docs recebidos' + CHAR(13) + CHAR(10) + '17/06/2024 - Numerario enviado, ag retorno' + CHAR(13) + CHAR(10) + '13/06/2024 - Prorrogaçao por mais 2 meses' + CHAR(13) + CHAR(10) + '30/04/2024 - Cobrado procedimento a ser adotado' + CHAR(13) + CHAR(10) + '28/03/2024 - Juntada efetuada' + CHAR(13) + CHAR(10) + '27/03/2024 - Recebido docs' + CHAR(13) + CHAR(10) + '13/03/2024 - Enviado Numerario e RPR, ag retorno' + CHAR(13) + CHAR(10) + '12/03/2024 - Solicitado prorrogação por mais 3 meses' + CHAR(13) + CHAR(10) + '01/02/2024 - Cobrado procedimento a ser adotado' + CHAR(13) + CHAR(10) + '27/10/2023 - Juntada efetuada' + CHAR(13) + CHAR(10) + '26/10/2023 - Docs recebidos' + CHAR(13) + CHAR(10) + '06/10/2023 - RPR e Numerario enviados, ag retorno' + CHAR(13) + CHAR(10) + '03/10/2023 - Solicitado prorrogação por mais 5 meses' + CHAR(13) + CHAR(10) + '30/08/2023 - Cobrado procedimento a ser adotado' + CHAR(13) + CHAR(10) + '11/07/2023 - Processo incluido no controle' | W15: WHEN 13 THEN '29/11/2024 - Juntada efetuada' + CHAR(13) + CHAR(10) + '27/11/2024 - Docs recebidos' + CHAR(13) + CHAR(10) + '25/11/2024 - Numerario enviado, ag retorno' + CHAR(13) + CHAR(10) + '22/11/2024 - Solicitado prorrogaçao por mais 4 meses' + CHAR(13) + CHAR(10) + '30/09/2024 - Cobrado procedimento a ser adotado' + CHAR(13) + CHAR(10) + '30/08/2024 - Juntada efetuada' + CHAR(13) + CHAR(10) + '29/08/2024 - Docs recebidos' + CHAR(13) + CHAR(10) + '22/08/2024 - Numerario e RPR enviados, ag retorno' + CHAR(13) + CHAR(10) + '21/08/2024 - Prorrogação por mais 3 meses' + CHAR(13) + CHAR(10) + '14/08/2024 - Cobrado novamente' + CHAR(13) + CHAR(10) + '02/07/2024 - Cobrado procedimento a ser adotado' + CHAR(13) + CHAR(10) + '25/06/2024 - Juntada efetuada' + CHAR(13) + CHAR(10) + '25/06/2024 - Docs recebidos' + CHAR(13) + CHAR(10) + '17/06/2024 - Numerario enviado, ag retorno' + CHAR(13) + CHAR(10) + '13/06/2024 - Prorrogaçao por mais 2 meses' + CHAR(13) + CHAR(10) + '30/04/2024 - Cobrado procedimento a ser adotado' + CHAR(13) + CHAR(10) + '28/03/2024 - Juntada efetuada' + CHAR(13) + CHAR(10) + '27/03/2024 - Recebido docs' + CHAR(13) + CHAR(10) + '13/03/2024 - Enviado Numerario e RPR, ag retorno' + CHAR(13) + CHAR(10) + '12/03/2024 - Solicitado prorrogação por mais 3 meses' + CHAR(13) + CHAR(10) + '01/02/2024 - Cobrado procedimento a ser adotado' + CHAR(13) + CHAR(10) + '27/10/2023 - Juntada efetuada' + CHAR(13) + CHAR(10) + '26/10/2023 - Docs recebidos' + CHAR(13) + CHAR(10) + '06/10/2023 - RPR e Numerario enviados, ag retorno' + CHAR(13) + CHAR(10) + '03/10/2023 - Solicitado prorrogação por mais 5 meses' + CHAR(13) + CHAR(10) + '30/08/2023 - Cobrado procedimento a ser adotado' + CHAR(13) + CHAR(10) + '11/07/2023 - Processo incluido no controle' | X15: WHEN 13 THEN 'POWER PACK DE MOVIMENTO RETILÍNEO (CILINDROS), MARCA GOLDHOFER AKTIENGESELLSCHAFT, MODELO PFV-490/60-31, NÚMERO DE SÉRIE 61402, FROTA 302920, ANO DE FABRICAÇÃO 2016, USADO, COM DISPOSITIVOS E FERRAMENTAS DE MONTAGEM E ACESSÓRIOS NECESSÁRIOS PARA OPERAÇÃO.'
A16: =B16&" - "&COUNTIF($B$3:B16,B16) -> MAMMOET - 8 | B16: MAMMOET | C16: 2308248563 | D16: I-23/0432-MBG | E16: REP. LINHA DE EIXO | F16: SUSPENSA | G16: 132305077973964 | H16: =EDATE(I16,-1) -> 45691 | I16: =EDATE(LEFT(L16,10),-1) -> 45719 | J16: CONTRATO DE ALUGUEL DE 26/03/2023 | K16: VEÍCULO AUTOPROPELIDO PARA TRANSPORTE A DE GRANDES ESTRUTURAS EM CURTAS DISTÂNCIAS, COM 6 LINHAS DE EIXO, ANO DE FABRICAÇÃO 2016, USADO, COM CADA LINHA DE EIXO COMPOSTA POR 8 PNEUS (TOTAL DO CONJUNTO 48 PNEUS),COMPLETA, COM DISPOSITIVOS E FERRAMENTAS DE MONTAGEM E ACESSÓRIOS NECESSÁRIOS PARA OPERAÇÃO (PARCIALMENTE DESMONTADO PARA MANUSEIO E TRANSPORTE). NÚMERO DE SÉRIE WG0PST061G0061401 E FROTA 302919 E MARCA GOLDHOFER AKTIENGESELLSCHAFT, MODELO: PST/SL 6-12X08. | L16: 45750 | M16: 45044 | N16: 45056 | O16: ICTSI RIO BRASIL TERMINAL 1 SA - RIO DE JANEIRO/RJ | P16: 11426377000123 | R16: 202300191329045 | S16: 46871 | T16: 29/11/2024 - Juntada efetuada 28/11/2024 - Docs recebidos 25/11/2024 - Numerario enviado, ag retorno 22/11/2024 - Solicitado prorrogaçao por mais 4 meses 07/10/2024 - Cobrado procedimento a ser adotado 03/09/2024 - Juntada efetuada 29/08/2024 - Docs recebidos 22/08/2024 - Numerario e RPR enviados 21/08/2024 - Solicitado prorrogaçao por mais 3 meses 14/08/2024 - Cobrado novamente 05/07/2024 - Cobrado procedimento a ser adotado 24/06/2024 - Juntada efetuada 17/06/2024 - Docs recebidos 17/06/2024 - Numerario enviado, ag retorno 13/06/2024 - Prorrogação por mais 2 meses 10/06/2024 - Cobrado procedimento 03/06/2024 - Juntada efetuada 29/05/2024 - Docs recebidos 24/05/2024 - RPR e Numerario enviados, ag retorno 21/05/2024 - Solicitado prorrogação por mais 1 mes 08/05/2024 - Cobrado novamente 05/04/2024 - Cobrado procedimento a ser adotado 04/12/2023 - Juntada efetuada, aguardando apolice. 10/11/2023 - Solicitado prorrogação por mais 6 meses, Numerario, TR e RPR enviados, ag retorno 06/10/2023 - Cobrado procedimento a ser adotado 12/06/2023 - Processo incluido no controle | U16: MARÍTIMO | V16: ="'"&SUBSTITUTE(T16,CHAR(10),"' + CHAR(13) + CHAR(10) + "&CHAR(10)&"'")&"'" -> '29/11/2024 - Juntada efetuada' + CHAR(13) + CHAR(10) + '28/11/2024 - Docs recebidos' + CHAR(13) + CHAR(10) + '25/11/2024 - Numerario enviado, ag retorno' + CHAR(13) + CHAR(10) + '22/11/2024 - Solicitado prorrogaçao por mais 4 meses' + CHAR(13) + CHAR(10) + '07/10/2024 - Cobrado procedimento a ser adotado' + CHAR(13) + CHAR(10) + '03/09/2024 - Juntada efetuada' + CHAR(13) + CHAR(10) + '29/08/2024 - Docs recebidos' + CHAR(13) + CHAR(10) + '22/08/2024 - Numerario e RPR enviados' + CHAR(13) + CHAR(10) + '21/08/2024 - Solicitado prorrogaçao por mais 3 meses' + CHAR(13) + CHAR(10) + '14/08/2024 - Cobrado novamente' + CHAR(13) + CHAR(10) + '05/07/2024 - Cobrado procedimento a ser adotado' + CHAR(13) + CHAR(10) + '24/06/2024 - Juntada efetuada' + CHAR(13) + CHAR(10) + '17/06/2024 - Docs recebidos' + CHAR(13) + CHAR(10) + '17/06/2024 - Numerario enviado, ag retorno' + CHAR(13) + CHAR(10) + '13/06/2024 - Prorrogação por mais 2 meses' + CHAR(13) + CHAR(10) + '10/06/2024 - Cobrado procedimento' + CHAR(13) + CHAR(10) + '03/06/2024 - Juntada efetuada' + CHAR(13) + CHAR(10) + '29/05/2024 - Docs recebidos' + CHAR(13) + CHAR(10) + '24/05/2024 - RPR e Numerario enviados, ag retorno' + CHAR(13) + CHAR(10) + '21/05/2024 - Solicitado prorrogação por mais 1 mes' + CHAR(13) + CHAR(10) + '08/05/2024 - Cobrado novamente' + CHAR(13) + CHAR(10) + '05/04/2024 - Cobrado procedimento a ser adotado' + CHAR(13) + CHAR(10) + '04/12/2023 - Juntada efetuada, aguardando apolice.' + CHAR(13) + CHAR(10) + '10/11/2023 - Solicitado prorrogação por mais 6 meses, Numerario, TR e RPR enviados, ag retorno' + CHAR(13) + CHAR(10) + '06/10/2023 - Cobrado procedimento a ser adotado' + CHAR(13) + CHAR(10) + '12/06/2023 - Processo incluido no controle' | W16: WHEN 14 THEN '29/11/2024 - Juntada efetuada' + CHAR(13) + CHAR(10) + '28/11/2024 - Docs recebidos' + CHAR(13) + CHAR(10) + '25/11/2024 - Numerario enviado, ag retorno' + CHAR(13) + CHAR(10) + '22/11/2024 - Solicitado prorrogaçao por mais 4 meses' + CHAR(13) + CHAR(10) + '07/10/2024 - Cobrado procedimento a ser adotado' + CHAR(13) + CHAR(10) + '03/09/2024 - Juntada efetuada' + CHAR(13) + CHAR(10) + '29/08/2024 - Docs recebidos' + CHAR(13) + CHAR(10) + '22/08/2024 - Numerario e RPR enviados' + CHAR(13) + CHAR(10) + '21/08/2024 - Solicitado prorrogaçao por mais 3 meses' + CHAR(13) + CHAR(10) + '14/08/2024 - Cobrado novamente' + CHAR(13) + CHAR(10) + '05/07/2024 - Cobrado procedimento a ser adotado' + CHAR(13) + CHAR(10) + '24/06/2024 - Juntada efetuada' + CHAR(13) + CHAR(10) + '17/06/2024 - Docs recebidos' + CHAR(13) + CHAR(10) + '17/06/2024 - Numerario enviado, ag retorno' + CHAR(13) + CHAR(10) + '13/06/2024 - Prorrogação por mais 2 meses' + CHAR(13) + CHAR(10) + '10/06/2024 - Cobrado procedimento' + CHAR(13) + CHAR(10) + '03/06/2024 - Juntada efetuada' + CHAR(13) + CHAR(10) + '29/05/2024 - Docs recebidos' + CHAR(13) + CHAR(10) + '24/05/2024 - RPR e Numerario enviados, ag retorno' + CHAR(13) + CHAR(10) + '21/05/2024 - Solicitado prorrogação por mais 1 mes' + CHAR(13) + CHAR(10) + '08/05/2024 - Cobrado novamente' + CHAR(13) + CHAR(10) + '05/04/2024 - Cobrado procedimento a ser adotado' + CHAR(13) + CHAR(10) + '04/12/2023 - Juntada efetuada, aguardando apolice.' + CHAR(13) + CHAR(10) + '10/11/2023 - Solicitado prorrogação por mais 6 meses, Numerario, TR e RPR enviados, ag retorno' + CHAR(13) + CHAR(10) + '06/10/2023 - Cobrado procedimento a ser adotado' + CHAR(13) + CHAR(10) + '12/06/2023 - Processo incluido no controle' | X16: WHEN 14 THEN 'VEÍCULO AUTOPROPELIDO PARA TRANSPORTE A DE GRANDES ESTRUTURAS EM CURTAS DISTÂNCIAS, COM 6 LINHAS DE EIXO, ANO DE FABRICAÇÃO 2016, USADO, COM CADA LINHA DE EIXO COMPOSTA POR 8 PNEUS (TOTAL DO CONJUNTO 48 PNEUS),COMPLETA, COM DISPOSITIVOS E FERRAMENTAS DE MONTAGEM E ACESSÓRIOS NECESSÁRIOS PARA OPERAÇÃO (PARCIALMENTE DESMONTADO PARA MANUSEIO E TRANSPORTE). NÚMERO DE SÉRIE WG0PST061G0061401 E FROTA 302919 E MARCA GOLDHOFER AKTIENGESELLSCHAFT, MODELO: PST/SL 6-12X08.'
A17: =B17&" - "&COUNTIF($B$3:B17,B17) -> MAMMOET - 9 | B17: MAMMOET | C17: 2221403214 | D17: I-22/1173-MBG | E17: EXPO-CHL-BRL-034 | F17: SUSPENSA | G17: 162205256553652 | H17: =EDATE(I17,-1) -> 45700 | I17: =EDATE(LEFT(L17,10),-1) -> 45728 | J17: CONTRATO DE ALUGUEL DE 22/09/2022 | K17: Caminhão Guindaste sobre Pneu com lança telescópica até 60 metros, aditivo especial conectado JIB até 88 metros, capacidade máxima de elevação 220 toneladas, com 5 eixos totais direcionáveis,parcialmente desmontado para transporte e manuseio, com peças e acessórios para montagem e operação. Marca Liebherr, modelo LTM-1220 5.2, usado, ano de fabricação 2012, número de série 045767, CHASSIS NO.: W09585700DEL05385. | L17: 45759 | M17: 44862 | N17: 44873 | O17: TCP - TERMINAL DE CONTEINERES DE PARANAGUA S/A | P17: 11426377000123 | R17: 202200171178807 | S17: 46688 | T17: 10/12/2024 - Juntada efetuada 03/12/2024 - Docs recebidos 29/11/2024 - Numerario enviado, ag retorno 27/11/2024 - Solicitado prorrogaçao por mais 4 meses 27/11/2024 - Cobrado novamente 11/11/2024 - Cobrado procedimento a ser adotado 08/11/2024 - Juntada efetuada 04/11/2024 - Docs recebidos 22/10/2024 - Numerario enviado, ag retorno 21/10/2024 - Solciitado prorrogaçao por mais 1 mes 14/10/2024 - Cobrado novamente 30/09/2024 - Cobrado procedimento a ser adotado 13/06/2024 - Juntada efetuada 11/06/2024 - Docs recebidos 10/06/2024 - Numerario enviado, ag retorno 04/06/2024 - Prorrogação por mais 5 meses 03/06/2024 - Cobrado novamente 15/04/2024 - Cobrado procedimento a ser adotado 12/04/2024 - Juntada efetuada 11/04/2024 - Docs recebidos 03/04/2024 - Enviado Numerario e RPR 01/04/2024 - Informado que será prorrogado por mais 2 meses 22/03/2024 - Cobrado novamente 14/02/2024 - Cobrado procedimento a ser adotado 03/11/2023 - Juntada da Apolice efetuada 26/10/2023 - Apolice atualizada recebida 11/10/2023 - Juntada efetuada 06/10/2023 - Recebido docs exceto Apolice atualizada 21/08/2023 - Cobrado procedimento a ser adotado 02/01/2023 - Processo incluido no controle | U17: MARÍTIMO | V17: ="'"&SUBSTITUTE(T17,CHAR(10),"' + CHAR(13) + CHAR(10) + "&CHAR(10)&"'")&"'" -> '10/12/2024 - Juntada efetuada' + CHAR(13) + CHAR(10) + '03/12/2024 - Docs recebidos' + CHAR(13) + CHAR(10) + '29/11/2024 - Numerario enviado, ag retorno' + CHAR(13) + CHAR(10) + '27/11/2024 - Solicitado prorrogaçao por mais 4 meses' + CHAR(13) + CHAR(10) + '27/11/2024 - Cobrado novamente' + CHAR(13) + CHAR(10) + '11/11/2024 - Cobrado procedimento a ser adotado' + CHAR(13) + CHAR(10) + '08/11/2024 - Juntada efetuada' + CHAR(13) + CHAR(10) + '04/11/2024 - Docs recebidos' + CHAR(13) + CHAR(10) + '22/10/2024 - Numerario enviado, ag retorno' + CHAR(13) + CHAR(10) + '21/10/2024 - Solciitado prorrogaçao por mais 1 mes' + CHAR(13) + CHAR(10) + '14/10/2024 - Cobrado novamente' + CHAR(13) + CHAR(10) + '30/09/2024 - Cobrado procedimento a ser adotado' + CHAR(13) + CHAR(10) + '13/06/2024 - Juntada efetuada' + CHAR(13) + CHAR(10) + '11/06/2024 - Docs recebidos' + CHAR(13) + CHAR(10) + '10/06/2024 - Numerario enviado, ag retorno' + CHAR(13) + CHAR(10) + '04/06/2024 - Prorrogação por mais 5 meses' + CHAR(13) + CHAR(10) + '03/06/2024 - Cobrado novamente' + CHAR(13) + CHAR(10) + '15/04/2024 - Cobrado procedimento a ser adotado' + CHAR(13) + CHAR(10) + '12/04/2024 - Juntada efetuada' + CHAR(13) + CHAR(10) + '11/04/2024 - Docs recebidos' + CHAR(13) + CHAR(10) + '03/04/2024 - Enviado Numerario e RPR' + CHAR(13) + CHAR(10) + '01/04/2024 - Informado que será prorrogado por mais 2 meses' + CHAR(13) + CHAR(10) + '22/03/2024 - Cobrado novamente' + CHAR(13) + CHAR(10) + '14/02/2024 - Cobrado procedimento a ser adotado' + CHAR(13) + CHAR(10) + '03/11/2023 - Juntada da Apolice efetuada' + CHAR(13) + CHAR(10) + '26/10/2023 - Apolice atualizada recebida' + CHAR(13) + CHAR(10) + '11/10/2023 - Juntada efetuada' + CHAR(13) + CHAR(10) + '06/10/2023 - Recebido docs exceto Apolice atualizada' + CHAR(13) + CHAR(10) + '21/08/2023 - Cobrado procedimento a ser adotado' + CHAR(13) + CHAR(10) + '02/01/2023 - Processo incluido no controle' | W17: WHEN 15 THEN '10/12/2024 - Juntada efetuada' + CHAR(13) + CHAR(10) + '03/12/2024 - Docs recebidos' + CHAR(13) + CHAR(10) + '29/11/2024 - Numerario enviado, ag retorno' + CHAR(13) + CHAR(10) + '27/11/2024 - Solicitado prorrogaçao por mais 4 meses' + CHAR(13) + CHAR(10) + '27/11/2024 - Cobrado novamente' + CHAR(13) + CHAR(10) + '11/11/2024 - Cobrado procedimento a ser adotado' + CHAR(13) + CHAR(10) + '08/11/2024 - Juntada efetuada' + CHAR(13) + CHAR(10) + '04/11/2024 - Docs recebidos' + CHAR(13) + CHAR(10) + '22/10/2024 - Numerario enviado, ag retorno' + CHAR(13) + CHAR(10) + '21/10/2024 - Solciitado prorrogaçao por mais 1 mes' + CHAR(13) + CHAR(10) + '14/10/2024 - Cobrado novamente' + CHAR(13) + CHAR(10) + '30/09/2024 - Cobrado procedimento a ser adotado' + CHAR(13) + CHAR(10) + '13/06/2024 - Juntada efetuada' + CHAR(13) + CHAR(10) + '11/06/2024 - Docs recebidos' + CHAR(13) + CHAR(10) + '10/06/2024 - Numerario enviado, ag retorno' + CHAR(13) + CHAR(10) + '04/06/2024 - Prorrogação por mais 5 meses' + CHAR(13) + CHAR(10) + '03/06/2024 - Cobrado novamente' + CHAR(13) + CHAR(10) + '15/04/2024 - Cobrado procedimento a ser adotado' + CHAR(13) + CHAR(10) + '12/04/2024 - Juntada efetuada' + CHAR(13) + CHAR(10) + '11/04/2024 - Docs recebidos' + CHAR(13) + CHAR(10) + '03/04/2024 - Enviado Numerario e RPR' + CHAR(13) + CHAR(10) + '01/04/2024 - Informado que será prorrogado por mais 2 meses' + CHAR(13) + CHAR(10) + '22/03/2024 - Cobrado novamente' + CHAR(13) + CHAR(10) + '14/02/2024 - Cobrado procedimento a ser adotado' + CHAR(13) + CHAR(10) + '03/11/2023 - Juntada da Apolice efetuada' + CHAR(13) + CHAR(10) + '26/10/2023 - Apolice atualizada recebida' + CHAR(13) + CHAR(10) + '11/10/2023 - Juntada efetuada' + CHAR(13) + CHAR(10) + '06/10/2023 - Recebido docs exceto Apolice atualizada' + CHAR(13) + CHAR(10) + '21/08/2023 - Cobrado procedimento a ser adotado' + CHAR(13) + CHAR(10) + '02/01/2023 - Processo incluido no controle' | X17: WHEN 15 THEN 'CAMINHÃO GUINDASTE SOBRE PNEU COM LANÇA TELESCÓPICA ATÉ 60 METROS, ADITIVO ESPECIAL CONECTADO JIB ATÉ 88 METROS, CAPACIDADE MÁXIMA DE ELEVAÇÃO 220 TONELADAS, COM 5 EIXOS TOTAIS DIRECIONÁVEIS,PARCIALMENTE DESMONTADO PARA TRANSPORTE E MANUSEIO, COM PEÇAS E ACESSÓRIOS PARA MONTAGEM E OPERAÇÃO. MARCA LIEBHERR, MODELO LTM-1220 5.2, USADO, ANO DE FABRICAÇÃO 2012, NÚMERO DE SÉRIE 045767, CHASSIS NO.: W09585700DEL05385.'
A18: =B18&" - "&COUNTIF($B$3:B18,B18) -> MAMMOET - 10 | B18: MAMMOET | C18: 2225612292 | D18: I-22/1955-MBG | E18: CC 2800-1 | F18: SUSPENSA | G18: 132205315120298 | H18: =EDATE(I18,-1) -> 45707 | I18: =EDATE(LEFT(L18,10),-1) -> 45735 | J18: CONTRATO DE ALUGUEL DE 13/12/2022 | K18: Seções de lança para guindaste CC2800-1, usadas, tipo (S7) 2724-22-03/ 2724-22-04, completas com pendentes e pinos para montagem. Marca: Terex Demag, modelo: CC 2800-1, número de serie 62240, capacidade da lança 600 ton, fleet number: 1169, ano de fabricação 2008, usado. | L18: 45766 | M18: 44921 | N18: 44945 | O18: INST.PORT.MAR.ALF.USO PUBL.CONS.MULT RIO-T.II-PORTO RJ | P18: 11426377000123 | R18: 202200177717807 | S18: 46927 | T18: 17/12/2024 - Juntada efetuada 16/12/2024 - Docs recebidos 29/11/2024 - Numerario enviado, ag retorno 28/11/2024 - Solicitado prorrogaçao por mais 4 meses 25/11/2024 - Cobrado procedimento a ser adotado 19/11/2024 - Juntada efetuada 19/11/2024 - Recebido documentos 24/10/2024 - Enviado numerario, ag retorno 23/10/2024 - Solciitado prorrogaçao por mais 1 mes 30/09/2024 - Cobrado procedimento a ser adotado 19/06/2024 - Juntada efetuada 19/06/2024 - Docs recebidos 10/06/2024 - Numerario enviado, ag retorno 04/06/2024 - Prorrogação por mais 5 meses 03/06/2024 - Cobrado novamente 30/04/2024 - Cobrado procedimento a ser adotado 15/01/2024 - Juntada efetuada 12/01/2024 - Docs recebidos 05/01/2024 - RPR e Numerario enviados, ag retorno 04/01/2024 - Solicitado prorrogação por mais 5 meses 28/12/2023 - Cobrado novamente 21/11/2023 - Cobrado procedimento a ser adotado 17/07/2023 - Juntada efetuada através do DOSSIE 17/07/2023 - Docs recebidos 20/06/2023 - Numerario, TR e RPR enviados, ag retorno 19/06/2023 - Informado que será prorrogado por 6 meses 18/05/2023 - Cobrado procedimento a ser adotado 03/03/2023 - Processo incluido no controle | U18: MARÍTIMO | V18: ="'"&SUBSTITUTE(T18,CHAR(10),"' + CHAR(13) + CHAR(10) + "&CHAR(10)&"'")&"'" -> '17/12/2024 - Juntada efetuada' + CHAR(13) + CHAR(10) + '16/12/2024 - Docs recebidos' + CHAR(13) + CHAR(10) + '29/11/2024 - Numerario enviado, ag retorno' + CHAR(13) + CHAR(10) + '28/11/2024 - Solicitado prorrogaçao por mais 4 meses' + CHAR(13) + CHAR(10) + '25/11/2024 - Cobrado procedimento a ser adotado' + CHAR(13) + CHAR(10) + '19/11/2024 - Juntada efetuada' + CHAR(13) + CHAR(10) + '19/11/2024 - Recebido documentos' + CHAR(13) + CHAR(10) + '24/10/2024 - Enviado numerario, ag retorno' + CHAR(13) + CHAR(10) + '23/10/2024 - Solciitado prorrogaçao por mais 1 mes' + CHAR(13) + CHAR(10) + '30/09/2024 - Cobrado procedimento a ser adotado' + CHAR(13) + CHAR(10) + '19/06/2024 - Juntada efetuada' + CHAR(13) + CHAR(10) + '19/06/2024 - Docs recebidos' + CHAR(13) + CHAR(10) + '10/06/2024 - Numerario enviado, ag retorno' + CHAR(13) + CHAR(10) + '04/06/2024 - Prorrogação por mais 5 meses' + CHAR(13) + CHAR(10) + '03/06/2024 - Cobrado novamente' + CHAR(13) + CHAR(10) + '30/04/2024 - Cobrado procedimento a ser adotado' + CHAR(13) + CHAR(10) + '15/01/2024 - Juntada efetuada' + CHAR(13) + CHAR(10) + '12/01/2024 - Docs recebidos' + CHAR(13) + CHAR(10) + '05/01/2024 - RPR e Numerario enviados, ag retorno' + CHAR(13) + CHAR(10) + '04/01/2024 - Solicitado prorrogação por mais 5 meses' + CHAR(13) + CHAR(10) + '28/12/2023 - Cobrado novamente' + CHAR(13) + CHAR(10) + '21/11/2023 - Cobrado procedimento a ser adotado' + CHAR(13) + CHAR(10) + '17/07/2023 - Juntada efetuada através do DOSSIE' + CHAR(13) + CHAR(10) + '17/07/2023 - Docs recebidos' + CHAR(13) + CHAR(10) + '20/06/2023 - Numerario, TR e RPR enviados, ag retorno' + CHAR(13) + CHAR(10) + '19/06/2023 - Informado que será prorrogado por 6 meses' + CHAR(13) + CHAR(10) + '18/05/2023 - Cobrado procedimento a ser adotado' + CHAR(13) + CHAR(10) + '03/03/2023 - Processo incluido no controle' | W18: WHEN 16 THEN '17/12/2024 - Juntada efetuada' + CHAR(13) + CHAR(10) + '16/12/2024 - Docs recebidos' + CHAR(13) + CHAR(10) + '29/11/2024 - Numerario enviado, ag retorno' + CHAR(13) + CHAR(10) + '28/11/2024 - Solicitado prorrogaçao por mais 4 meses' + CHAR(13) + CHAR(10) + '25/11/2024 - Cobrado procedimento a ser adotado' + CHAR(13) + CHAR(10) + '19/11/2024 - Juntada efetuada' + CHAR(13) + CHAR(10) + '19/11/2024 - Recebido documentos' + CHAR(13) + CHAR(10) + '24/10/2024 - Enviado numerario, ag retorno' + CHAR(13) + CHAR(10) + '23/10/2024 - Solciitado prorrogaçao por mais 1 mes' + CHAR(13) + CHAR(10) + '30/09/2024 - Cobrado procedimento a ser adotado' + CHAR(13) + CHAR(10) + '19/06/2024 - Juntada efetuada' + CHAR(13) + CHAR(10) + '19/06/2024 - Docs recebidos' + CHAR(13) + CHAR(10) + '10/06/2024 - Numerario enviado, ag retorno' + CHAR(13) + CHAR(10) + '04/06/2024 - Prorrogação por mais 5 meses' + CHAR(13) + CHAR(10) + '03/06/2024 - Cobrado novamente' + CHAR(13) + CHAR(10) + '30/04/2024 - Cobrado procedimento a ser adotado' + CHAR(13) + CHAR(10) + '15/01/2024 - Juntada efetuada' + CHAR(13) + CHAR(10) + '12/01/2024 - Docs recebidos' + CHAR(13) + CHAR(10) + '05/01/2024 - RPR e Numerario enviados, ag retorno' + CHAR(13) + CHAR(10) + '04/01/2024 - Solicitado prorrogação por mais 5 meses' + CHAR(13) + CHAR(10) + '28/12/2023 - Cobrado novamente' + CHAR(13) + CHAR(10) + '21/11/2023 - Cobrado procedimento a ser adotado' + CHAR(13) + CHAR(10) + '17/07/2023 - Juntada efetuada através do DOSSIE' + CHAR(13) + CHAR(10) + '17/07/2023 - Docs recebidos' + CHAR(13) + CHAR(10) + '20/06/2023 - Numerario, TR e RPR enviados, ag retorno' + CHAR(13) + CHAR(10) + '19/06/2023 - Informado que será prorrogado por 6 meses' + CHAR(13) + CHAR(10) + '18/05/2023 - Cobrado procedimento a ser adotado' + CHAR(13) + CHAR(10) + '03/03/2023 - Processo incluido no controle' | X18: WHEN 16 THEN 'SEÇÕES DE LANÇA PARA GUINDASTE CC2800-1, USADAS, TIPO (S7) 2724-22-03/ 2724-22-04, COMPLETAS COM PENDENTES E PINOS PARA MONTAGEM. MARCA: TEREX DEMAG, MODELO: CC 2800-1, NÚMERO DE SERIE 62240, CAPACIDADE DA LANÇA 600 TON, FLEET NUMBER: 1169, ANO DE FABRICAÇÃO 2008, USADO.'
A19: =B19&" - "&COUNTIF($B$3:B19,B19) -> MAMMOET - 11 | B19: MAMMOET | C19: 2117258092 | D19: I-21/1420-MBG | E19: CKE1100G-2 | F19: SUSPENSA | G19: 132105211325331 | H19: =EDATE(I19,-1) -> 45708 | I19: =EDATE(LEFT(L19,10),-1) -> 45736 | J19: CONTRATO DE LOCAÇÃO DATADO EM 30/08/2021 | K19: Parte de Guindaste autopropelido CC2800, sendo: Moitão 200T, cabo de 28MM, 5 roldanas, marca 5321322, modelo HF-280200-00001, numero de serie 63078-2, ano de fabricação 2007 - usado. | L19: 45767 | M19: 44456 | N19: 44459 | O19: MULTIRIO-RJ | P19: 11426377000638 | R19: 202100119574713 | T19: 18/12/2024 - Juntada efetuada 18/12/2024 - Docs recebidos 29/11/2024 - Numerario enviado, ag retorno 28/11/2024 - Solicitado prorrogaçao por mais 4 meses 25/11/2024 - Cobrado procedimento a ser adotado 19/11/2024 - Juntada efetuada 19/11/2024 - Docs recebidos 22/10/2024 - Numerario enviado, ag retorno 21/10/2024 - Solciitado prorrogaçao por mais 1 mes 30/09/2024 - Cobrado procedimento a ser adotado 20/06/2024 - Juntada efetuada 19/06/2024 - Docs recebidos 10/06/2024 - Enviado RPR, ag retorno 04/06/2024 - Solicitado prorrogação por mais 5 meses 03/06/2024 - Cobrado novamente 30/04/2024 - Cobrado procedimento a ser adotado 19/04/2024 - Juntada efetuada 19/04/2024 - Documentação recebida 03/04/2024 - Numerario, RPR e TR enviados, ag retorno 01/04/2024 - Informado que será prorrogado por mais 2 meses 22/03/2024 - Cobrado novamente 23/02/2024 - Cobrado procedimento a ser adotado 19/10/2023 - Juntada efetuada 18/10/2023 - Docs recebidos 02/10/2023 - Enviado numerario, TR e RPR, ag retorno 29/09/2023 - Cobrado novamente, respondido que será prorrogado por mais 6 meses 21/08/2023 - Cobrado procedimento a ser adotado 14/08/2023 - Juntada efetuada pelo DOSSIE 04/08/2023 - Recebido docs 31/07/2023 - Numerario, RPR e TR enviados, agr retorno 26/07/2023 - Informad que será prorrogado por mais 2 meses 26/06/2023 - Cobrado procedimento a ser adotado 09/03/2023 - Juntada efetuada no DOSSIE 06/03/2023 - Docs recebidos 01/02/2023 - Enviado Numerario, RPR e TR, aguardando retorno 26/01/2023 - Informado que a prorrogação será até 08/2023 24/01/2023 - Cobrado procedimento a ser adotado 15/03/2022 - Juntada anexada através do DOSSIE 17/02/2022 - Solicitado prorrogação por 12 meses, TR, RAT e Numerário enviados, aguardando retorno 19/01/2022 - Cobrado procedimento a ser adotado 29/10/2021 - Processo incluido no controle | U19: MARÍTIMO | V19: ="'"&SUBSTITUTE(T19,CHAR(10),"' + CHAR(13) + CHAR(10) + "&CHAR(10)&"'")&"'" -> '18/12/2024 - Juntada efetuada' + CHAR(13) + CHAR(10) + '18/12/2024 - Docs recebidos' + CHAR(13) + CHAR(10) + '29/11/2024 - Numerario enviado, ag retorno' + CHAR(13) + CHAR(10) + '28/11/2024 - Solicitado prorrogaçao por mais 4 meses' + CHAR(13) + CHAR(10) + '25/11/2024 - Cobrado procedimento a ser adotado' + CHAR(13) + CHAR(10) + '19/11/2024 - Juntada efetuada' + CHAR(13) + CHAR(10) + '19/11/2024 - Docs recebidos' + CHAR(13) + CHAR(10) + '22/10/2024 - Numerario enviado, ag retorno' + CHAR(13) + CHAR(10) + '21/10/2024 - Solciitado prorrogaçao por mais 1 mes' + CHAR(13) + CHAR(10) + '30/09/2024 - Cobrado procedimento a ser adotado' + CHAR(13) + CHAR(10) + '20/06/2024 - Juntada efetuada' + CHAR(13) + CHAR(10) + '19/06/2024 - Docs recebidos' + CHAR(13) + CHAR(10) + '10/06/2024 - Enviado RPR, ag retorno' + CHAR(13) + CHAR(10) + '04/06/2024 - Solicitado prorrogação por mais 5 meses' + CHAR(13) + CHAR(10) + '03/06/2024 - Cobrado novamente' + CHAR(13) + CHAR(10) + '30/04/2024 - Cobrado procedimento a ser adotado' + CHAR(13) + CHAR(10) + '19/04/2024 - Juntada efetuada' + CHAR(13) + CHAR(10) + '19/04/2024 - Documentação recebida' + CHAR(13) + CHAR(10) + '03/04/2024 - Numerario, RPR e TR enviados, ag retorno' + CHAR(13) + CHAR(10) + '01/04/2024 - Informado que será prorrogado por mais 2 meses' + CHAR(13) + CHAR(10) + '22/03/2024 - Cobrado novamente' + CHAR(13) + CHAR(10) + '23/02/2024 - Cobrado procedimento a ser adotado' + CHAR(13) + CHAR(10) + '19/10/2023 - Juntada efetuada' + CHAR(13) + CHAR(10) + '18/10/2023 - Docs recebidos' + CHAR(13) + CHAR(10) + '02/10/2023 - Enviado numerario, TR e RPR, ag retorno' + CHAR(13) + CHAR(10) + '29/09/2023 - Cobrado novamente, respondido que será prorrogado por mais 6 meses' + CHAR(13) + CHAR(10) + '21/08/2023 - Cobrado procedimento a ser adotado' + CHAR(13) + CHAR(10) + '14/08/2023 - Juntada efetuada pelo DOSSIE' + CHAR(13) + CHAR(10) + '04/08/2023 - Recebido docs' + CHAR(13) + CHAR(10) + '31/07/2023 - Numerario, RPR e TR enviados, agr retorno' + CHAR(13) + CHAR(10) + '26/07/2023 - Informad que será prorrogado por mais 2 meses' + CHAR(13) + CHAR(10) + '26/06/2023 - Cobrado procedimento a ser adotado' + CHAR(13) + CHAR(10) + '09/03/2023 - Juntada efetuada no DOSSIE' + CHAR(13) + CHAR(10) + '06/03/2023 - Docs recebidos' + CHAR(13) + CHAR(10) + '01/02/2023 - Enviado Numerario, RPR e TR, aguardando retorno' + CHAR(13) + CHAR(10) + '26/01/2023 - Informado que a prorrogação será até 08/2023' + CHAR(13) + CHAR(10) + '24/01/2023 - Cobrado procedimento a ser adotado' + CHAR(13) + CHAR(10) + '15/03/2022 - Juntada anexada através do DOSSIE' + CHAR(13) + CHAR(10) + '17/02/2022 - Solicitado prorrogação por 12 meses, TR, RAT e Numerário enviados, aguardando retorno' + CHAR(13) + CHAR(10) + '19/01/2022 - Cobrado procedimento a ser adotado' + CHAR(13) + CHAR(10) + '29/10/2021 - Processo incluido no controle' | W19: WHEN 17 THEN '18/12/2024 - Juntada efetuada' + CHAR(13) + CHAR(10) + '18/12/2024 - Docs recebidos' + CHAR(13) + CHAR(10) + '29/11/2024 - Numerario enviado, ag retorno' + CHAR(13) + CHAR(10) + '28/11/2024 - Solicitado prorrogaçao por mais 4 meses' + CHAR(13) + CHAR(10) + '25/11/2024 - Cobrado procedimento a ser adotado' + CHAR(13) + CHAR(10) + '19/11/2024 - Juntada efetuada' + CHAR(13) + CHAR(10) + '19/11/2024 - Docs recebidos' + CHAR(13) + CHAR(10) + '22/10/2024 - Numerario enviado, ag retorno' + CHAR(13) + CHAR(10) + '21/10/2024 - Solciitado prorrogaçao por mais 1 mes' + CHAR(13) + CHAR(10) + '30/09/2024 - Cobrado procedimento a ser adotado' + CHAR(13) + CHAR(10) + '20/06/2024 - Juntada efetuada' + CHAR(13) + CHAR(10) + '19/06/2024 - Docs recebidos' + CHAR(13) + CHAR(10) + '10/06/2024 - Enviado RPR, ag retorno' + CHAR(13) + CHAR(10) + '04/06/2024 - Solicitado prorrogação por mais 5 meses' + CHAR(13) + CHAR(10) + '03/06/2024 - Cobrado novamente' + CHAR(13) + CHAR(10) + '30/04/2024 - Cobrado procedimento a ser adotado' + CHAR(13) + CHAR(10) + '19/04/2024 - Juntada efetuada' + CHAR(13) + CHAR(10) + '19/04/2024 - Documentação recebida' + CHAR(13) + CHAR(10) + '03/04/2024 - Numerario, RPR e TR enviados, ag retorno' + CHAR(13) + CHAR(10) + '01/04/2024 - Informado que será prorrogado por mais 2 meses' + CHAR(13) + CHAR(10) + '22/03/2024 - Cobrado novamente' + CHAR(13) + CHAR(10) + '23/02/2024 - Cobrado procedimento a ser adotado' + CHAR(13) + CHAR(10) + '19/10/2023 - Juntada efetuada' + CHAR(13) + CHAR(10) + '18/10/2023 - Docs recebidos' + CHAR(13) + CHAR(10) + '02/10/2023 - Enviado numerario, TR e RPR, ag retorno' + CHAR(13) + CHAR(10) + '29/09/2023 - Cobrado novamente, respondido que será prorrogado por mais 6 meses' + CHAR(13) + CHAR(10) + '21/08/2023 - Cobrado procedimento a ser adotado' + CHAR(13) + CHAR(10) + '14/08/2023 - Juntada efetuada pelo DOSSIE' + CHAR(13) + CHAR(10) + '04/08/2023 - Recebido docs' + CHAR(13) + CHAR(10) + '31/07/2023 - Numerario, RPR e TR enviados, agr retorno' + CHAR(13) + CHAR(10) + '26/07/2023 - Informad que será prorrogado por mais 2 meses' + CHAR(13) + CHAR(10) + '26/06/2023 - Cobrado procedimento a ser adotado' + CHAR(13) + CHAR(10) + '09/03/2023 - Juntada efetuada no DOSSIE' + CHAR(13) + CHAR(10) + '06/03/2023 - Docs recebidos' + CHAR(13) + CHAR(10) + '01/02/2023 - Enviado Numerario, RPR e TR, aguardando retorno' + CHAR(13) + CHAR(10) + '26/01/2023 - Informado que a prorrogação será até 08/2023' + CHAR(13) + CHAR(10) + '24/01/2023 - Cobrado procedimento a ser adotado' + CHAR(13) + CHAR(10) + '15/03/2022 - Juntada anexada através do DOSSIE' + CHAR(13) + CHAR(10) + '17/02/2022 - Solicitado prorrogação por 12 meses, TR, RAT e Numerário enviados, aguardando retorno' + CHAR(13) + CHAR(10) + '19/01/2022 - Cobrado procedimento a ser adotado' + CHAR(13) + CHAR(10) + '29/10/2021 - Processo incluido no controle' | X19: WHEN 17 THEN 'PARTE DE GUINDASTE AUTOPROPELIDO CC2800, SENDO: MOITÃO 200T, CABO DE 28MM, 5 ROLDANAS, MARCA 5321322, MODELO HF-280200-00001, NUMERO DE SERIE 63078-2, ANO DE FABRICAÇÃO 2007 - USADO.'
A20: =B20&" - "&COUNTIF($B$3:B20,B20) -> MAMMOET - 12 | B20: MAMMOET | C20: 1801413543 | D20: I-17/2116-MBG | E20: LINHA DE EIXO + POWER PACK | F20: SUSPENSA | G20: 131705281227807 | H20: =EDATE(I20,-1) -> 45711 | I20: =EDATE(LEFT(L20,10),-1) -> 45739 | J20: CONTRATO DE LOCAÇÃO S/NR | K20: DIVERSOS EQUIPAMENTOS CONFORME DI | L20: 45770 | M20: 43122 | N20: 43150 | O20: ALFÂNDEGA DO PORTO DO RIO DE JANEIRO | P20: 11426377000638 | Q20: 10711.720099/2018-34 | R20: 201800018270352 | S20: 46226 | T20: 23/12/2024 - Juntada efetuada, docs recebidos 29/11/2024 - Enviado Numerario, ag retorno 27/11/2024 - Solicitado prorrogaçao por mais 4 meses 27/11/2024 - Cobrado novamente 28/10/2024 - Cobrado procedimento a ser adotado 25/10/2024 - Despacho 22/08/2024 - Juntada efetuada 12/08/2024 - Docs recebidos 07/08/2024 - Enviado Numerario, ag retorno 05/08/2024 - Solicitado prorrogação por mais 4 meses 25/06/2024 - Cobrado procedimento a ser adotado 21/06/2024 - Juntada efetuada 19/06/2024 - Docs recebidos 17/06/2024 - Numerario enviado, ag retorno 11/06/2024 - Prorrogação por mais 2 meses 03/06/2024 - Cobrado novamente 30/04/2024 - Cobrado procedimento a ser adotado 23/01/2024 - Juntada efetuada 12/01/2024 - Docs recebidos 05/01/2024 - RPR, Numerario e TR enviados, ag retorno 04/01/2023 - Solicitado prorrogação por mais 5 meses 28/12/2023 - Cobrado novamente 01/12/2023 - Cobrado procedimento a ser adotado 31/07/2023 - Apolice juntada 27/07/2023 - Recebido Apolice 21/07/2023 - Juntada efetuada sem Apolice 18/07/2023 - Docs recebidos, exceto Apolice 27/06/2023 - Numerario, TR e RPR enviados 21/06/2023 - Solicitado renovação por 6 meses 01/06/2023 - Cobrado procedimento a ser adotado 09/02/2023 - Despacho de encaminhamento 24/01/2023 - Juntada efetuada DOSSIE e E-CAC, Apolice recebida 23/01/2023 - Docs recebidos, exceto APOLICE, juntada efetuada, aguardando APOLICE 02/01/2023 - Enviado Numerario, RPR e TR equivalente a 6 meses, aguardando retorno 25/11/2022 - Cobrado procedimento a ser adotado 07/11/2022 - Despacho Decisorio 14/10/2022 - Despacho de Encaminhamento 12/07/2022 - Juntada efetuada no e-CAC e no DOSSIE. 08/07/2022 - Cobrado os documentos para seguir com o pedido de prorrogação. 06/06/2022 - Solicitado prorrogação por mais 6 meses, docs enviados, aguardando retorno 24/05/2022 - Cobrado procedimento a ser adotado 18/02/2022 - Juntada efetuada no e-cac e através do DOSSIE da DI 17/02/2022 - Recebido docs 04/02/2022 - Solicitado prorrogação por 5 meses, TR e RAT enviados 27/01/2022 - Cobrado novamente 27/12/2021 - Cobrado procedimento a ser adotado 22/11/2021 - Recebido docs, juntada efeuada através do E-CAC e DOSSIE 17/11/2021 - Cobrado documentos novamente 20/10/2021 - Solicitado renovação por 3 meses, Numerario e TR enviados, aguardando retorno 27/09/2021 - Cobrado procedimento a ser adotado 23/07/2021 - Docs recebidos, aguardando APOLICE, juntada efetuada através do E-CAC e DOSSIE sem APOLICE, recebido APOLICE, juntada efetuada 06/07/2021 - Solicitado prorrogação por 4 meses, Numerário e TR enviados, aguardando docs 25/06/2021 - Cobrado novamente 25/05/2021 - Cobrado procedimento a ser adotado 18/01/2021 - Recebido docs, juntada enviada pelo E-CAC 13/01/2021 - Cobrado docs 23/12/2020 - Solicitada prorrogação por 6 meses, Numerario e TR enviados 24/11/2020 - Cobrado procedimento a ser adotado 16/09/2020 - Recebido documentos, Juntada Enviada pelo E-CAC, aguardando parecer da Receita 14/09/2020 - Cobrado novamente 10/09/2020 - Cobrado novamente 27/08/2020 - Solicitado prorrogação ate 23/01/2021, TR e Numerário enviados 24/08/2020 - Cobrado novamente 20/07/2020 - Cobrado procedimento a ser adotado 15/05/2020 - Juntada enviada 11/05/2020 - Cobrado documentação 18/03/2020 - Cobrado qual procedimennto será adotado 16/01/2020 - Juntada feita pelo E-CAC 07/01/2020 - Cobrado documentação 23/12/2019 - Cobrado novamente 28/11/2019 - Cobrado qual procedimento a ser adotado. 16/07/2019 - Juntada protocolada no e-CAC. 05/07/2019 - Recebido documentação para prosseguir com a prorrogação. 24/06/2019 - Cobrado documentação. 06/06/2019 - Enviado numerário, aguardando deposito e documentos para prosseguir com a prorrogação. 03/06/2019 - Recebido a informação que será prorrogado por 6 meses. 30/05/2018 - Cobrado qual procedimento a ser adotado. 18/01/2019 - Processo enviado para o faturamento. 17/01/2019 - Juntada enviada e aguardando aprovação. 16/01/2019 - Recebida copia autenticada do contrato de serviço. 09/01/2019 - Recebida copia da documentação. 07/01/2019 - Cobrado documentação para prosseguir com a prorrogação. 03/01/2019 - Cobrado documentação para prosseguir com a prorrogação. 02/01/2019 - Cobrado documentação para prosseguir com a prorrogação. 21/12/2018 - Enviado numerário e TR ao cliente. Agdo retorno. 10/12/2018 - O cliente mudou de ideia, o processo será prorrogado por mais 6 meses. 04/12/2018 - Recebida a informação que o material será reexportado. Enviado e-mail para o setor de exportação para providências. 03/12/2018 - Enviado numerario para nacionalização de dois itens. 03/12/2018 - Cobrado qual procedimento será adotado. 22/11/2018 - Cobrado qual procedimento será adotado. 26/09/2018- 2ª Prorrogação enviada ao faturamento 26/09/2018 - Agdo aceite de juntada da 1ª prorrogação e 2ª prorrogação 26/09/2018 - Documentos juntados ao processo. Agdo aceite de juntada 24/09/2018 - Pagamento de darfs e icms 19/09/2018 -Recebemos documentos e numerário 18/09/2018 - Cobrado envio dos documentos e transferencia do numerario 11/09/2018 - Cobrado envio dos documentos e transferencia do numerario 31/08/2018 - Enviado numerario e TR assinado. Agdo documentos e envio dos numerários 27/08/2018 - Informado que será prorrogado por 3 meses; 22/08/2018 - Cobrado procedimento será adotado 17/07/2018 - Prorrogação faturada 11/07/2018- Documentos juntados no processo. Agd aceite de juntada 11/07/2018 - Cobrado vias originais ou autenticadas dos documentos e envio da garantia conforme TR corrigido 10/07/2018 - Cobrado vias originais ou autenticadas dos documentos e envio da garantia conforme TR corrigido 06/07/2018 - Recebido documentos por e-mail 03/07/2018 - Solicitação da seguradora referente aos documentos 03/07/2018 - Dinheiro do numerário em conta 21/06/2018 - Enviado Numerário. Agdo transferência do numerário e Documentos 07/05/2019 - Informado que o procedimento a ser adotado será prorrogação por 3 meses 04/05/2018 - Cobrado procedimento a ser adotado 16/04/2018 - Processo Incluso no Controle * Considerado o prazo do Contrato de Locação, 7 meses a contar da data de assinatura (Cláusula 06 Contrato), até 11/07/2018. * Fiscal Concedeu o regime até 19/09/2018, 7 meses a contar do desembaraço. | U20: MARÍTIMO | V20: ="'"&SUBSTITUTE(T20,CHAR(10),"' + CHAR(13) + CHAR(10) + "&CHAR(10)&"'")&"'" -> '23/12/2024 - Juntada efetuada, docs recebidos' + CHAR(13) + CHAR(10) + '29/11/2024 - Enviado Numerario, ag retorno' + CHAR(13) + CHAR(10) + '27/11/2024 - Solicitado prorrogaçao por mais 4 meses' + CHAR(13) + CHAR(10) + '27/11/2024 - Cobrado novamente' + CHAR(13) + CHAR(10) + '28/10/2024 - Cobrado procedimento a ser adotado' + CHAR(13) + CHAR(10) + '25/10/2024 - Despacho' + CHAR(13) + CHAR(10) + '22/08/2024 - Juntada efetuada' + CHAR(13) + CHAR(10) + '12/08/2024 - Docs recebidos' + CHAR(13) + CHAR(10) + '07/08/2024 - Enviado Numerario, ag retorno' + CHAR(13) + CHAR(10) + '05/08/2024 - Solicitado prorrogação por mais 4 meses' + CHAR(13) + CHAR(10) + '25/06/2024 - Cobrado procedimento a ser adotado' + CHAR(13) + CHAR(10) + '21/06/2024 - Juntada efetuada' + CHAR(13) + CHAR(10) + '19/06/2024 - Docs recebidos' + CHAR(13) + CHAR(10) + '17/06/2024 - Numerario enviado, ag retorno' + CHAR(13) + CHAR(10) + '11/06/2024 - Prorrogação por mais 2 meses' + CHAR(13) + CHAR(10) + '03/06/2024 - Cobrado novamente' + CHAR(13) + CHAR(10) + '30/04/2024 - Cobrado procedimento a ser adotado' + CHAR(13) + CHAR(10) + '23/01/2024 - Juntada efetuada' + CHAR(13) + CHAR(10) + '12/01/2024 - Docs recebidos' + CHAR(13) + CHAR(10) + '05/01/2024 - RPR, Numerario e TR enviados, ag retorno' + CHAR(13) + CHAR(10) + '04/01/2023 - Solicitado prorrogação por mais 5 meses' + CHAR(13) + CHAR(10) + '28/12/2023 - Cobrado novamente' + CHAR(13) + CHAR(10) + '01/12/2023 - Cobrado procedimento a ser adotado' + CHAR(13) + CHAR(10) + '31/07/2023 - Apolice juntada' + CHAR(13) + CHAR(10) + '27/07/2023 - Recebido Apolice' + CHAR(13) + CHAR(10) + '21/07/2023 - Juntada efetuada sem Apolice' + CHAR(13) + CHAR(10) + '18/07/2023 - Docs recebidos, exceto Apolice' + CHAR(13) + CHAR(10) + '27/06/2023 - Numerario, TR e RPR enviados' + CHAR(13) + CHAR(10) + '21/06/2023 - Solicitado renovação por 6 meses' + CHAR(13) + CHAR(10) + '01/06/2023 - Cobrado procedimento a ser adotado' + CHAR(13) + CHAR(10) + '09/02/2023 - Despacho de encaminhamento' + CHAR(13) + CHAR(10) + '24/01/2023 - Juntada efetuada DOSSIE e E-CAC, Apolice recebida' + CHAR(13) + CHAR(10) + '23/01/2023 - Docs recebidos, exceto APOLICE, juntada efetuada, aguardando APOLICE' + CHAR(13) + CHAR(10) + '02/01/2023 - Enviado Numerario, RPR e TR equivalente a 6 meses, aguardando retorno' + CHAR(13) + CHAR(10) + '25/11/2022 - Cobrado procedimento a ser adotado' + CHAR(13) + CHAR(10) + '07/11/2022 - Despacho Decisorio' + CHAR(13) + CHAR(10) + '14/10/2022 - Despacho de Encaminhamento' + CHAR(13) + CHAR(10) + '12/07/2022 - Juntada efetuada no e-CAC e no DOSSIE.' + CHAR(13) + CHAR(10) + '08/07/2022 - Cobrado os documentos para seguir com o pedido de prorrogação.' + CHAR(13) + CHAR(10) + '06/06/2022 - Solicitado prorrogação por mais 6 meses, docs enviados, aguardando retorno' + CHAR(13) + CHAR(10) + '24/05/2022 - Cobrado procedimento a ser adotado' + CHAR(13) + CHAR(10) + '18/02/2022 - Juntada efetuada no e-cac e através do DOSSIE da DI' + CHAR(13) + CHAR(10) + '17/02/2022 - Recebido docs' + CHAR(13) + CHAR(10) + '04/02/2022 - Solicitado prorrogação por 5 meses, TR e RAT enviados' + CHAR(13) + CHAR(10) + '27/01/2022 - Cobrado novamente' + CHAR(13) + CHAR(10) + '27/12/2021 - Cobrado procedimento a ser adotado' + CHAR(13) + CHAR(10) + '22/11/2021 - Recebido docs, juntada efeuada através do E-CAC e DOSSIE' + CHAR(13) + CHAR(10) + '17/11/2021 - Cobrado documentos novamente' + CHAR(13) + CHAR(10) + '20/10/2021 - Solicitado renovação por 3 meses, Numerario e TR enviados, aguardando retorno' + CHAR(13) + CHAR(10) + '27/09/2021 - Cobrado procedimento a ser adotado' + CHAR(13) + CHAR(10) + '23/07/2021 - Docs recebidos, aguardando APOLICE, juntada efetuada através do E-CAC e DOSSIE sem APOLICE, recebido APOLICE, juntada efetuada' + CHAR(13) + CHAR(10) + '06/07/2021 - Solicitado prorrogação por 4 meses, Numerário e TR enviados, aguardando docs' + CHAR(13) + CHAR(10) + '25/06/2021 - Cobrado novamente' + CHAR(13) + CHAR(10) + '25/05/2021 - Cobrado procedimento a ser adotado' + CHAR(13) + CHAR(10) + '18/01/2021 - Recebido docs, juntada enviada pelo E-CAC' + CHAR(13) + CHAR(10) + '13/01/2021 - Cobrado docs' + CHAR(13) + CHAR(10) + '23/12/2020 - Solicitada prorrogação por 6 meses, Numerario e TR enviados' + CHAR(13) + CHAR(10) + '24/11/2020 - Cobrado procedimento a ser adotado' + CHAR(13) + CHAR(10) + '16/09/2020 - Recebido documentos, Juntada Enviada pelo E-CAC, aguardando parecer da Receita' + CHAR(13) + CHAR(10) + '14/09/2020 - Cobrado novamente' + CHAR(13) + CHAR(10) + '10/09/2020 - Cobrado novamente' + CHAR(13) + CHAR(10) + '27/08/2020 - Solicitado prorrogação ate 23/01/2021, TR e Numerário enviados' + CHAR(13) + CHAR(10) + '24/08/2020 - Cobrado novamente' + CHAR(13) + CHAR(10) + '20/07/2020 - Cobrado procedimento a ser adotado' + CHAR(13) + CHAR(10) + '15/05/2020 - Juntada enviada' + CHAR(13) + CHAR(10) + '11/05/2020 - Cobrado documentação' + CHAR(13) + CHAR(10) + '18/03/2020 - Cobrado qual procedimennto será adotado' + CHAR(13) + CHAR(10) + '16/01/2020 - Juntada feita pelo E-CAC' + CHAR(13) + CHAR(10) + '07/01/2020 - Cobrado documentação' + CHAR(13) + CHAR(10) + '23/12/2019 - Cobrado novamente' + CHAR(13) + CHAR(10) + '28/11/2019 - Cobrado qual procedimento a ser adotado. ' + CHAR(13) + CHAR(10) + '16/07/2019 - Juntada protocolada no e-CAC.' + CHAR(13) + CHAR(10) + '05/07/2019 - Recebido documentação para prosseguir com a prorrogação.' + CHAR(13) + CHAR(10) + '24/06/2019 - Cobrado documentação.' + CHAR(13) + CHAR(10) + '06/06/2019 - Enviado numerário, aguardando deposito e documentos para prosseguir com a prorrogação.' + CHAR(13) + CHAR(10) + '03/06/2019 - Recebido a informação que será prorrogado por 6 meses.' + CHAR(13) + CHAR(10) + '30/05/2018 - Cobrado qual procedimento a ser adotado. ' + CHAR(13) + CHAR(10) + '18/01/2019 - Processo enviado para o faturamento.' + CHAR(13) + CHAR(10) + '17/01/2019 - Juntada enviada e aguardando aprovação.' + CHAR(13) + CHAR(10) + '16/01/2019 - Recebida copia autenticada do contrato de serviço.' + CHAR(13) + CHAR(10) + '09/01/2019 - Recebida copia da documentação.' + CHAR(13) + CHAR(10) + '07/01/2019 - Cobrado documentação para prosseguir com a prorrogação. ' + CHAR(13) + CHAR(10) + '03/01/2019 - Cobrado documentação para prosseguir com a prorrogação.' + CHAR(13) + CHAR(10) + '02/01/2019 - Cobrado documentação para prosseguir com a prorrogação.' + CHAR(13) + CHAR(10) + '21/12/2018 - Enviado numerário e TR ao cliente. Agdo retorno.' + CHAR(13) + CHAR(10) + '10/12/2018 - O cliente mudou de ideia, o processo será prorrogado por mais 6 meses.' + CHAR(13) + CHAR(10) + '04/12/2018 - Recebida a informação que o material será reexportado. Enviado e-mail para o setor de exportação para providências. ' + CHAR(13) + CHAR(10) + '03/12/2018 - Enviado numerario para nacionalização de dois itens.' + CHAR(13) + CHAR(10) + '03/12/2018 - Cobrado qual procedimento será adotado.' + CHAR(13) + CHAR(10) + '22/11/2018 - Cobrado qual procedimento será adotado.' + CHAR(13) + CHAR(10) + '26/09/2018- 2ª Prorrogação enviada ao faturamento' + CHAR(13) + CHAR(10) + '26/09/2018 - Agdo aceite de juntada da 1ª prorrogação e 2ª prorrogação ' + CHAR(13) + CHAR(10) + '26/09/2018 - Documentos juntados ao processo. Agdo aceite de juntada' + CHAR(13) + CHAR(10) + '24/09/2018 - Pagamento de darfs e icms' + CHAR(13) + CHAR(10) + '19/09/2018 -Recebemos documentos e numerário' + CHAR(13) + CHAR(10) + '18/09/2018 - Cobrado envio dos documentos e transferencia do numerario' + CHAR(13) + CHAR(10) + '11/09/2018 - Cobrado envio dos documentos e transferencia do numerario' + CHAR(13) + CHAR(10) + '31/08/2018 - Enviado numerario e TR assinado. Agdo documentos e envio dos numerários' + CHAR(13) + CHAR(10) + '27/08/2018 - Informado que será prorrogado por 3 meses;' + CHAR(13) + CHAR(10) + '22/08/2018 - Cobrado procedimento será adotado ' + CHAR(13) + CHAR(10) + '17/07/2018 - Prorrogação faturada' + CHAR(13) + CHAR(10) + '11/07/2018- Documentos juntados no processo. Agd aceite de juntada' + CHAR(13) + CHAR(10) + '11/07/2018 - Cobrado vias originais ou autenticadas dos documentos e envio da garantia conforme TR corrigido' + CHAR(13) + CHAR(10) + '10/07/2018 - Cobrado vias originais ou autenticadas dos documentos e envio da garantia conforme TR corrigido' + CHAR(13) + CHAR(10) + '06/07/2018 - Recebido documentos por e-mail' + CHAR(13) + CHAR(10) + '03/07/2018 - Solicitação da seguradora referente aos documentos ' + CHAR(13) + CHAR(10) + '03/07/2018 - Dinheiro do numerário em conta ' + CHAR(13) + CHAR(10) + '21/06/2018 - Enviado Numerário. Agdo transferência do numerário e Documentos' + CHAR(13) + CHAR(10) + '07/05/2019 - Informado que o procedimento a ser adotado será prorrogação por 3 meses' + CHAR(13) + CHAR(10) + '04/05/2018 - Cobrado procedimento a ser adotado ' + CHAR(13) + CHAR(10) + '16/04/2018 - Processo Incluso no Controle' + CHAR(13) + CHAR(10) + '* Considerado o prazo do Contrato de Locação, 7 meses a contar da data de assinatura (Cláusula 06 Contrato), até 11/07/2018.' + CHAR(13) + CHAR(10) + '* Fiscal Concedeu o regime até 19/09/2018, 7 meses a contar do desembaraço.' | W20: WHEN 18 THEN '23/12/2024 - Juntada efetuada, docs recebidos' + CHAR(13) + CHAR(10) + '29/11/2024 - Enviado Numerario, ag retorno' + CHAR(13) + CHAR(10) + '27/11/2024 - Solicitado prorrogaçao por mais 4 meses' + CHAR(13) + CHAR(10) + '27/11/2024 - Cobrado novamente' + CHAR(13) + CHAR(10) + '28/10/2024 - Cobrado procedimento a ser adotado' + CHAR(13) + CHAR(10) + '25/10/2024 - Despacho' + CHAR(13) + CHAR(10) + '22/08/2024 - Juntada efetuada' + CHAR(13) + CHAR(10) + '12/08/2024 - Docs recebidos' + CHAR(13) + CHAR(10) + '07/08/2024 - Enviado Numerario, ag retorno' + CHAR(13) + CHAR(10) + '05/08/2024 - Solicitado prorrogação por mais 4 meses' + CHAR(13) + CHAR(10) + '25/06/2024 - Cobrado procedimento a ser adotado' + CHAR(13) + CHAR(10) + '21/06/2024 - Juntada efetuada' + CHAR(13) + CHAR(10) + '19/06/2024 - Docs recebidos' + CHAR(13) + CHAR(10) + '17/06/2024 - Numerario enviado, ag retorno' + CHAR(13) + CHAR(10) + '11/06/2024 - Prorrogação por mais 2 meses' + CHAR(13) + CHAR(10) + '03/06/2024 - Cobrado novamente' + CHAR(13) + CHAR(10) + '30/04/2024 - Cobrado procedimento a ser adotado' + CHAR(13) + CHAR(10) + '23/01/2024 - Juntada efetuada' + CHAR(13) + CHAR(10) + '12/01/2024 - Docs recebidos' + CHAR(13) + CHAR(10) + '05/01/2024 - RPR, Numerario e TR enviados, ag retorno' + CHAR(13) + CHAR(10) + '04/01/2023 - Solicitado prorrogação por mais 5 meses' + CHAR(13) + CHAR(10) + '28/12/2023 - Cobrado novamente' + CHAR(13) + CHAR(10) + '01/12/2023 - Cobrado procedimento a ser adotado' + CHAR(13) + CHAR(10) + '31/07/2023 - Apolice juntada' + CHAR(13) + CHAR(10) + '27/07/2023 - Recebido Apolice' + CHAR(13) + CHAR(10) + '21/07/2023 - Juntada efetuada sem Apolice' + CHAR(13) + CHAR(10) + '18/07/2023 - Docs recebidos, exceto Apolice' + CHAR(13) + CHAR(10) + '27/06/2023 - Numerario, TR e RPR enviados' + CHAR(13) + CHAR(10) + '21/06/2023 - Solicitado renovação por 6 meses' + CHAR(13) + CHAR(10) + '01/06/2023 - Cobrado procedimento a ser adotado' + CHAR(13) + CHAR(10) + '09/02/2023 - Despacho de encaminhamento' + CHAR(13) + CHAR(10) + '24/01/2023 - Juntada efetuada DOSSIE e E-CAC, Apolice recebida' + CHAR(13) + CHAR(10) + '23/01/2023 - Docs recebidos, exceto APOLICE, juntada efetuada, aguardando APOLICE' + CHAR(13) + CHAR(10) + '02/01/2023 - Enviado Numerario, RPR e TR equivalente a 6 meses, aguardando retorno' + CHAR(13) + CHAR(10) + '25/11/2022 - Cobrado procedimento a ser adotado' + CHAR(13) + CHAR(10) + '07/11/2022 - Despacho Decisorio' + CHAR(13) + CHAR(10) + '14/10/2022 - Despacho de Encaminhamento' + CHAR(13) + CHAR(10) + '12/07/2022 - Juntada efetuada no e-CAC e no DOSSIE.' + CHAR(13) + CHAR(10) + '08/07/2022 - Cobrado os documentos para seguir com o pedido de prorrogação.' + CHAR(13) + CHAR(10) + '06/06/2022 - Solicitado prorrogação por mais 6 meses, docs enviados, aguardando retorno' + CHAR(13) + CHAR(10) + '24/05/2022 - Cobrado procedimento a ser adotado' + CHAR(13) + CHAR(10) + '18/02/2022 - Juntada efetuada no e-cac e através do DOSSIE da DI' + CHAR(13) + CHAR(10) + '17/02/2022 - Recebido docs' + CHAR(13) + CHAR(10) + '04/02/2022 - Solicitado prorrogação por 5 meses, TR e RAT enviados' + CHAR(13) + CHAR(10) + '27/01/2022 - Cobrado novamente' + CHAR(13) + CHAR(10) + '27/12/2021 - Cobrado procedimento a ser adotado' + CHAR(13) + CHAR(10) + '22/11/2021 - Recebido docs, juntada efeuada através do E-CAC e DOSSIE' + CHAR(13) + CHAR(10) + '17/11/2021 - Cobrado documentos novamente' + CHAR(13) + CHAR(10) + '20/10/2021 - Solicitado renovação por 3 meses, Numerario e TR enviados, aguardando retorno' + CHAR(13) + CHAR(10) + '27/09/2021 - Cobrado procedimento a ser adotado' + CHAR(13) + CHAR(10) + '23/07/2021 - Docs recebidos, aguardando APOLICE, juntada efetuada através do E-CAC e DOSSIE sem APOLICE, recebido APOLICE, juntada efetuada' + CHAR(13) + CHAR(10) + '06/07/2021 - Solicitado prorrogação por 4 meses, Numerário e TR enviados, aguardando docs' + CHAR(13) + CHAR(10) + '25/06/2021 - Cobrado novamente' + CHAR(13) + CHAR(10) + '25/05/2021 - Cobrado procedimento a ser adotado' + CHAR(13) + CHAR(10) + '18/01/2021 - Recebido docs, juntada enviada pelo E-CAC' + CHAR(13) + CHAR(10) + '13/01/2021 - Cobrado docs' + CHAR(13) + CHAR(10) + '23/12/2020 - Solicitada prorrogação por 6 meses, Numerario e TR enviados' + CHAR(13) + CHAR(10) + '24/11/2020 - Cobrado procedimento a ser adotado' + CHAR(13) + CHAR(10) + '16/09/2020 - Recebido documentos, Juntada Enviada pelo E-CAC, aguardando parecer da Receita' + CHAR(13) + CHAR(10) + '14/09/2020 - Cobrado novamente' + CHAR(13) + CHAR(10) + '10/09/2020 - Cobrado novamente' + CHAR(13) + CHAR(10) + '27/08/2020 - Solicitado prorrogação ate 23/01/2021, TR e Numerário enviados' + CHAR(13) + CHAR(10) + '24/08/2020 - Cobrado novamente' + CHAR(13) + CHAR(10) + '20/07/2020 - Cobrado procedimento a ser adotado' + CHAR(13) + CHAR(10) + '15/05/2020 - Juntada enviada' + CHAR(13) + CHAR(10) + '11/05/2020 - Cobrado documentação' + CHAR(13) + CHAR(10) + '18/03/2020 - Cobrado qual procedimennto será adotado' + CHAR(13) + CHAR(10) + '16/01/2020 - Juntada feita pelo E-CAC' + CHAR(13) + CHAR(10) + '07/01/2020 - Cobrado documentação' + CHAR(13) + CHAR(10) + '23/12/2019 - Cobrado novamente' + CHAR(13) + CHAR(10) + '28/11/2019 - Cobrado qual procedimento a ser adotado. ' + CHAR(13) + CHAR(10) + '16/07/2019 - Juntada protocolada no e-CAC.' + CHAR(13) + CHAR(10) + '05/07/2019 - Recebido documentação para prosseguir com a prorrogação.' + CHAR(13) + CHAR(10) + '24/06/2019 - Cobrado documentação.' + CHAR(13) + CHAR(10) + '06/06/2019 - Enviado numerário, aguardando deposito e documentos para prosseguir com a prorrogação.' + CHAR(13) + CHAR(10) + '03/06/2019 - Recebido a informação que será prorrogado por 6 meses.' + CHAR(13) + CHAR(10) + '30/05/2018 - Cobrado qual procedimento a ser adotado. ' + CHAR(13) + CHAR(10) + '18/01/2019 - Processo enviado para o faturamento.' + CHAR(13) + CHAR(10) + '17/01/2019 - Juntada enviada e aguardando aprovação.' + CHAR(13) + CHAR(10) + '16/01/2019 - Recebida copia autenticada do contrato de serviço.' + CHAR(13) + CHAR(10) + '09/01/2019 - Recebida copia da documentação.' + CHAR(13) + CHAR(10) + '07/01/2019 - Cobrado documentação para prosseguir com a prorrogação. ' + CHAR(13) + CHAR(10) + '03/01/2019 - Cobrado documentação para prosseguir com a prorrogação.' + CHAR(13) + CHAR(10) + '02/01/2019 - Cobrado documentação para prosseguir com a prorrogação.' + CHAR(13) + CHAR(10) + '21/12/2018 - Enviado numerário e TR ao cliente. Agdo retorno.' + CHAR(13) + CHAR(10) + '10/12/2018 - O cliente mudou de ideia, o processo será prorrogado por mais 6 meses.' + CHAR(13) + CHAR(10) + '04/12/2018 - Recebida a informação que o material será reexportado. Enviado e-mail para o setor de exportação para providências. ' + CHAR(13) + CHAR(10) + '03/12/2018 - Enviado numerario para nacionalização de dois itens.' + CHAR(13) + CHAR(10) + '03/12/2018 - Cobrado qual procedimento será adotado.' + CHAR(13) + CHAR(10) + '22/11/2018 - Cobrado qual procedimento será adotado.' + CHAR(13) + CHAR(10) + '26/09/2018- 2ª Prorrogação enviada ao faturamento' + CHAR(13) + CHAR(10) + '26/09/2018 - Agdo aceite de juntada da 1ª prorrogação e 2ª prorrogação ' + CHAR(13) + CHAR(10) + '26/09/2018 - Documentos juntados ao processo. Agdo aceite de juntada' + CHAR(13) + CHAR(10) + '24/09/2018 - Pagamento de darfs e icms' + CHAR(13) + CHAR(10) + '19/09/2018 -Recebemos documentos e numerário' + CHAR(13) + CHAR(10) + '18/09/2018 - Cobrado envio dos documentos e transferencia do numerario' + CHAR(13) + CHAR(10) + '11/09/2018 - Cobrado envio dos documentos e transferencia do numerario' + CHAR(13) + CHAR(10) + '31/08/2018 - Enviado numerario e TR assinado. Agdo documentos e envio dos numerários' + CHAR(13) + CHAR(10) + '27/08/2018 - Informado que será prorrogado por 3 meses;' + CHAR(13) + CHAR(10) + '22/08/2018 - Cobrado procedimento será adotado ' + CHAR(13) + CHAR(10) + '17/07/2018 - Prorrogação faturada' + CHAR(13) + CHAR(10) + '11/07/2018- Documentos juntados no processo. Agd aceite de juntada' + CHAR(13) + CHAR(10) + '11/07/2018 - Cobrado vias originais ou autenticadas dos documentos e envio da garantia conforme TR corrigido' + CHAR(13) + CHAR(10) + '10/07/2018 - Cobrado vias originais ou autenticadas dos documentos e envio da garantia conforme TR corrigido' + CHAR(13) + CHAR(10) + '06/07/2018 - Recebido documentos por e-mail' + CHAR(13) + CHAR(10) + '03/07/2018 - Solicitação da seguradora referente aos documentos ' + CHAR(13) + CHAR(10) + '03/07/2018 - Dinheiro do numerário em conta ' + CHAR(13) + CHAR(10) + '21/06/2018 - Enviado Numerário. Agdo transferência do numerário e Documentos' + CHAR(13) + CHAR(10) + '07/05/2019 - Informado que o procedimento a ser adotado será prorrogação por 3 meses' + CHAR(13) + CHAR(10) + '04/05/2018 - Cobrado procedimento a ser adotado ' + CHAR(13) + CHAR(10) + '16/04/2018 - Processo Incluso no Controle' + CHAR(13) + CHAR(10) + '* Considerado o prazo do Contrato de Locação, 7 meses a contar da data de assinatura (Cláusula 06 Contrato), até 11/07/2018.' + CHAR(13) + CHAR(10) + '* Fiscal Concedeu o regime até 19/09/2018, 7 meses a contar do desembaraço.' | X20: WHEN 18 THEN 'DIVERSOS EQUIPAMENTOS CONFORME DI'
A21: =B21&" - "&COUNTIF($B$3:B21,B21) -> MAMMOET - 13 | B21: MAMMOET | C21: 1905629534 | D21: I-19/0083-MBG | E21: GUINDASTE CC 2800-1 | F21: SUSPENSA | G21: 131905052962183 | H21: =EDATE(I21,-1) -> 45711 | I21: =EDATE(LEFT(L21,10),-1) -> 45739 | J21: CONTRATO DE LOCAÇÃO S/NR DATADO DE 15/02/2019 | K21: Guindaste autopropelido sobre esteiras, marca Terex-Demag, modelo CC2800-I, numero de serie 62277, ano de fabricação 2008, usado, numero da frota 1331, omputadorizado, acionado por motor diesel, capacidade de 600 toneladas, Superlift, contra-pesos,com todos acessórios para seu funcionamento, desmontado parcialmente para manuseio e transporte. | L21: 45770 | M21: 43552 | N21: 43564 | O21: CAMPOS DOS GOITACAZES | P21: 11426377000638 | Q21: 10120.004639/0319-51 | R21: 201900038644169 | S21: 46226 | T21: 23/12/2024 - Juntada efetuada 23/12/2024 - Docs recebidos 25/11/2024 - Cobrado procedimento a ser adotado 22/11/2024 - Juntada efetuada 22/11/2024 - Docs recebidos 14/11/2024 - Numerario enviado ag retorno 12/11/2024 - Soclitiado prorrogaçao por mais 1 mes 30/09/2024 - Cobrado procedimento a ser adotado 23/06/2024 - Juntada efetuada 21/06/2024 - Docs recebidos 14/06/2024 - Enviado numerario, ag retorno 11/06/2024 - Solicitado prorrogação por mais 5 meses 03/06/2024 - Cobrado novamente 30/04/2024 - Cobrado procedimento a ser adotado 23/11/2023 - Juntada efetuada 22/11/2023 - Docs recebidos 27/10/2023 - Numerario e RPR foi enviado, ag retorno 26/10/2023 - Cobrado novamente, informado que será prorrogado por mais 7 meses 29/09/2023 - Cobrado procedimento a ser adotado 19/09/2023 - Juntada efetuada pelo DOSSIE 18/09/2023 - Recebido docs 05/09/2023 - Enviado Numerario e RPR, ag retorno 30/08/2023 - SOlicitado prorrogação por mais 2 meses 27/07/2023 - Cobrado procedimento a ser adotado 24/07/2023 - Apolice recebida e juntada 21/07/2023 - Juntada efetuada sem apolice 18/07/2023 - Docs recebidos, exceto Apolice 27/06/2023 - Numerario, TR e RPR enviados, ag retorno 21/06/2023 - Solicitado prorrogação por 2 meses 01/06/2023 - Cobrado procedimento a ser adotado 24/01/2023 - Juntada efetuada DOSSIE e E-CAC, Apolice recebida 23/01/2023 - Docs recebidos, exceto APOLICE, juntada efetuada, aguardando APOLICE 10/01/2023 - Informado que será prorrogado por 6 meses, numerario, RPR e TR enviados, aguardando retorno 25/11/2022 - Cobrado procedimento a ser adotado 20/01/2022 - Juntada efetuada no E-CAC e DOSSIE 03/01/2022 - Informado que será prorrogado por 12 meses 28/12/2021 - Cobrado novamente 23/11/2021 - Cobrado procedimento a ser adotado 23/07/2021 - Docs recebidos, aguardando APOLICE, juntada efetuada através do E-CAC e DOSSIE sem APOLICE, APOLICE recebida, doc juntado 06/07/2021 - Solicitado prorrogação por 6 meses, TR e Numerario enviados 25/06/2021 - Cobrado novamente 25/05/2021 - Cobrado procedimento a ser adotado 04/05/2021 - Esteiras do guindaste com defeito e foram reexportadas, DI 21/0585528-7 para novas esteiras, acopladas ao guindaste 08/02/2021 - Despacho Decisorio 21/01/2021 - Docs recebidos, juntada feita no E-CAC 13/01/2021 - Cobrado docs 23/12/2020 - Informado que será prorrogado por 6 meses, TR e Numerario enviados 23/11/2020 - Cobrado procedimento a ser adotado 15/09/2020 - Despacho Decisorio 09/09/2020 - E-CAC com erro (antivirus analisando constantemente), documentos feitos pelo SVA, e protocolo fisicamente junto a RECEITA 27/08/2020 - Solicitado prorrogação ate 23/01/2021, TR e Numerário enviados 17/08/2020 - Cobrado novamente 10/07/2020 - Cobrado qual procedimento deverá ser adotado 18/06/2020 - Despacho Decisorio 08/06/2020 - Juntada enviada pelo E-CAC 28/05/2020 - TR e Numerario enviados, aguardando documentos 27/05/2020 - Cobrado novamente, será prorrogado por mais 3 meses 09/04/2020 - Cobrado procedimento a ser adotado 29/11/2019 - Juntada protocolada no e-CAC. 25/11/2019 - Recebido a documentação para inicio da prorrogação. 14/11/2019 - Cobrado qual procedimento será adotado. 31/10/2019 - Enviado o numerário e aguardando documentação para inicio da prorrogação. 29/10/2019 - Recebido a informação que será prorrogado por 6 meses. 09/10/2019 - Juntada enviada no e-CAC. 08/10/2019 - Recebido os documentos para inicio da prorrogação. 07/10/2019 - Cobrado documentação para inicio da prorrogação. 02/10/2019 - Cobrado documentação para inicio da prorrogação. 19/09/2019 - Enviando TR e numerario. 13/09/2019 - Inormado que será prorrogado por dois meses. 29/08/2019 - Cobrado qual procedimento será adotado. 24/06/2019 - Processo Incluso no controle | U21: MARÍTIMO | V21: ="'"&SUBSTITUTE(T21,CHAR(10),"' + CHAR(13) + CHAR(10) + "&CHAR(10)&"'")&"'" -> '23/12/2024 - Juntada efetuada' + CHAR(13) + CHAR(10) + '23/12/2024 - Docs recebidos' + CHAR(13) + CHAR(10) + '25/11/2024 - Cobrado procedimento a ser adotado' + CHAR(13) + CHAR(10) + '22/11/2024 - Juntada efetuada' + CHAR(13) + CHAR(10) + '22/11/2024 - Docs recebidos' + CHAR(13) + CHAR(10) + '14/11/2024 - Numerario enviado ag retorno' + CHAR(13) + CHAR(10) + '12/11/2024 - Soclitiado prorrogaçao por mais 1 mes' + CHAR(13) + CHAR(10) + '30/09/2024 - Cobrado procedimento a ser adotado' + CHAR(13) + CHAR(10) + '23/06/2024 - Juntada efetuada' + CHAR(13) + CHAR(10) + '21/06/2024 - Docs recebidos' + CHAR(13) + CHAR(10) + '14/06/2024 - Enviado numerario, ag retorno' + CHAR(13) + CHAR(10) + '11/06/2024 - Solicitado prorrogação por mais 5 meses' + CHAR(13) + CHAR(10) + '03/06/2024 - Cobrado novamente' + CHAR(13) + CHAR(10) + '30/04/2024 - Cobrado procedimento a ser adotado' + CHAR(13) + CHAR(10) + '23/11/2023 - Juntada efetuada' + CHAR(13) + CHAR(10) + '22/11/2023 - Docs recebidos' + CHAR(13) + CHAR(10) + '27/10/2023 - Numerario e RPR foi enviado, ag retorno' + CHAR(13) + CHAR(10) + '26/10/2023 - Cobrado novamente, informado que será prorrogado por mais 7 meses' + CHAR(13) + CHAR(10) + '29/09/2023 - Cobrado procedimento a ser adotado' + CHAR(13) + CHAR(10) + '19/09/2023 - Juntada efetuada pelo DOSSIE' + CHAR(13) + CHAR(10) + '18/09/2023 - Recebido docs' + CHAR(13) + CHAR(10) + '05/09/2023 - Enviado Numerario e RPR, ag retorno' + CHAR(13) + CHAR(10) + '30/08/2023 - SOlicitado prorrogação por mais 2 meses' + CHAR(13) + CHAR(10) + '27/07/2023 - Cobrado procedimento a ser adotado' + CHAR(13) + CHAR(10) + '24/07/2023 - Apolice recebida e juntada' + CHAR(13) + CHAR(10) + '21/07/2023 - Juntada efetuada sem apolice' + CHAR(13) + CHAR(10) + '18/07/2023 - Docs recebidos, exceto Apolice' + CHAR(13) + CHAR(10) + '27/06/2023 - Numerario, TR e RPR enviados, ag retorno' + CHAR(13) + CHAR(10) + '21/06/2023 - Solicitado prorrogação por 2 meses' + CHAR(13) + CHAR(10) + '01/06/2023 - Cobrado procedimento a ser adotado' + CHAR(13) + CHAR(10) + '24/01/2023 - Juntada efetuada DOSSIE e E-CAC, Apolice recebida' + CHAR(13) + CHAR(10) + '23/01/2023 - Docs recebidos, exceto APOLICE, juntada efetuada, aguardando APOLICE' + CHAR(13) + CHAR(10) + '10/01/2023 - Informado que será prorrogado por 6 meses, numerario, RPR e TR enviados, aguardando retorno' + CHAR(13) + CHAR(10) + '25/11/2022 - Cobrado procedimento a ser adotado' + CHAR(13) + CHAR(10) + '20/01/2022 - Juntada efetuada no E-CAC e DOSSIE' + CHAR(13) + CHAR(10) + '03/01/2022 - Informado que será prorrogado por 12 meses' + CHAR(13) + CHAR(10) + '28/12/2021 - Cobrado novamente' + CHAR(13) + CHAR(10) + '23/11/2021 - Cobrado procedimento a ser adotado' + CHAR(13) + CHAR(10) + '23/07/2021 - Docs recebidos, aguardando APOLICE, juntada efetuada através do E-CAC e DOSSIE sem APOLICE, APOLICE recebida, doc juntado' + CHAR(13) + CHAR(10) + '06/07/2021 - Solicitado prorrogação por 6 meses, TR e Numerario enviados' + CHAR(13) + CHAR(10) + '25/06/2021 - Cobrado novamente' + CHAR(13) + CHAR(10) + '25/05/2021 - Cobrado procedimento a ser adotado' + CHAR(13) + CHAR(10) + '04/05/2021 - Esteiras do guindaste com defeito e foram reexportadas, DI 21/0585528-7 para novas esteiras, acopladas ao guindaste' + CHAR(13) + CHAR(10) + '08/02/2021 - Despacho Decisorio' + CHAR(13) + CHAR(10) + '21/01/2021 - Docs recebidos, juntada feita no E-CAC' + CHAR(13) + CHAR(10) + '13/01/2021 - Cobrado docs' + CHAR(13) + CHAR(10) + '23/12/2020 - Informado que será prorrogado por 6 meses, TR e Numerario enviados' + CHAR(13) + CHAR(10) + '23/11/2020 - Cobrado procedimento a ser adotado' + CHAR(13) + CHAR(10) + '15/09/2020 - Despacho Decisorio' + CHAR(13) + CHAR(10) + '09/09/2020 - E-CAC com erro (antivirus analisando constantemente), documentos feitos pelo SVA, e protocolo fisicamente junto a RECEITA' + CHAR(13) + CHAR(10) + '27/08/2020 - Solicitado prorrogação ate 23/01/2021, TR e Numerário enviados' + CHAR(13) + CHAR(10) + '17/08/2020 - Cobrado novamente' + CHAR(13) + CHAR(10) + '10/07/2020 - Cobrado qual procedimento deverá ser adotado' + CHAR(13) + CHAR(10) + '18/06/2020 - Despacho Decisorio' + CHAR(13) + CHAR(10) + '08/06/2020 - Juntada enviada pelo E-CAC' + CHAR(13) + CHAR(10) + '28/05/2020 - TR e Numerario enviados, aguardando documentos' + CHAR(13) + CHAR(10) + '27/05/2020 - Cobrado novamente, será prorrogado por mais 3 meses' + CHAR(13) + CHAR(10) + '09/04/2020 - Cobrado procedimento a ser adotado' + CHAR(13) + CHAR(10) + '29/11/2019 - Juntada protocolada no e-CAC.' + CHAR(13) + CHAR(10) + '25/11/2019 - Recebido a documentação para inicio da prorrogação.' + CHAR(13) + CHAR(10) + '14/11/2019 - Cobrado qual procedimento será adotado.' + CHAR(13) + CHAR(10) + '31/10/2019 - Enviado o numerário e aguardando documentação para inicio da prorrogação.' + CHAR(13) + CHAR(10) + '29/10/2019 - Recebido a informação que será prorrogado por 6 meses.' + CHAR(13) + CHAR(10) + '09/10/2019 - Juntada enviada no e-CAC.' + CHAR(13) + CHAR(10) + '08/10/2019 - Recebido os documentos para inicio da prorrogação.' + CHAR(13) + CHAR(10) + '07/10/2019 - Cobrado documentação para inicio da prorrogação.' + CHAR(13) + CHAR(10) + '02/10/2019 - Cobrado documentação para inicio da prorrogação.' + CHAR(13) + CHAR(10) + '19/09/2019 - Enviando TR e numerario.' + CHAR(13) + CHAR(10) + '13/09/2019 - Inormado que será prorrogado por dois meses.' + CHAR(13) + CHAR(10) + '29/08/2019 - Cobrado qual procedimento será adotado.' + CHAR(13) + CHAR(10) + '24/06/2019 - Processo Incluso no controle' | W21: WHEN 19 THEN '23/12/2024 - Juntada efetuada' + CHAR(13) + CHAR(10) + '23/12/2024 - Docs recebidos' + CHAR(13) + CHAR(10) + '25/11/2024 - Cobrado procedimento a ser adotado' + CHAR(13) + CHAR(10) + '22/11/2024 - Juntada efetuada' + CHAR(13) + CHAR(10) + '22/11/2024 - Docs recebidos' + CHAR(13) + CHAR(10) + '14/11/2024 - Numerario enviado ag retorno' + CHAR(13) + CHAR(10) + '12/11/2024 - Soclitiado prorrogaçao por mais 1 mes' + CHAR(13) + CHAR(10) + '30/09/2024 - Cobrado procedimento a ser adotado' + CHAR(13) + CHAR(10) + '23/06/2024 - Juntada efetuada' + CHAR(13) + CHAR(10) + '21/06/2024 - Docs recebidos' + CHAR(13) + CHAR(10) + '14/06/2024 - Enviado numerario, ag retorno' + CHAR(13) + CHAR(10) + '11/06/2024 - Solicitado prorrogação por mais 5 meses' + CHAR(13) + CHAR(10) + '03/06/2024 - Cobrado novamente' + CHAR(13) + CHAR(10) + '30/04/2024 - Cobrado procedimento a ser adotado' + CHAR(13) + CHAR(10) + '23/11/2023 - Juntada efetuada' + CHAR(13) + CHAR(10) + '22/11/2023 - Docs recebidos' + CHAR(13) + CHAR(10) + '27/10/2023 - Numerario e RPR foi enviado, ag retorno' + CHAR(13) + CHAR(10) + '26/10/2023 - Cobrado novamente, informado que será prorrogado por mais 7 meses' + CHAR(13) + CHAR(10) + '29/09/2023 - Cobrado procedimento a ser adotado' + CHAR(13) + CHAR(10) + '19/09/2023 - Juntada efetuada pelo DOSSIE' + CHAR(13) + CHAR(10) + '18/09/2023 - Recebido docs' + CHAR(13) + CHAR(10) + '05/09/2023 - Enviado Numerario e RPR, ag retorno' + CHAR(13) + CHAR(10) + '30/08/2023 - SOlicitado prorrogação por mais 2 meses' + CHAR(13) + CHAR(10) + '27/07/2023 - Cobrado procedimento a ser adotado' + CHAR(13) + CHAR(10) + '24/07/2023 - Apolice recebida e juntada' + CHAR(13) + CHAR(10) + '21/07/2023 - Juntada efetuada sem apolice' + CHAR(13) + CHAR(10) + '18/07/2023 - Docs recebidos, exceto Apolice' + CHAR(13) + CHAR(10) + '27/06/2023 - Numerario, TR e RPR enviados, ag retorno' + CHAR(13) + CHAR(10) + '21/06/2023 - Solicitado prorrogação por 2 meses' + CHAR(13) + CHAR(10) + '01/06/2023 - Cobrado procedimento a ser adotado' + CHAR(13) + CHAR(10) + '24/01/2023 - Juntada efetuada DOSSIE e E-CAC, Apolice recebida' + CHAR(13) + CHAR(10) + '23/01/2023 - Docs recebidos, exceto APOLICE, juntada efetuada, aguardando APOLICE' + CHAR(13) + CHAR(10) + '10/01/2023 - Informado que será prorrogado por 6 meses, numerario, RPR e TR enviados, aguardando retorno' + CHAR(13) + CHAR(10) + '25/11/2022 - Cobrado procedimento a ser adotado' + CHAR(13) + CHAR(10) + '20/01/2022 - Juntada efetuada no E-CAC e DOSSIE' + CHAR(13) + CHAR(10) + '03/01/2022 - Informado que será prorrogado por 12 meses' + CHAR(13) + CHAR(10) + '28/12/2021 - Cobrado novamente' + CHAR(13) + CHAR(10) + '23/11/2021 - Cobrado procedimento a ser adotado' + CHAR(13) + CHAR(10) + '23/07/2021 - Docs recebidos, aguardando APOLICE, juntada efetuada através do E-CAC e DOSSIE sem APOLICE, APOLICE recebida, doc juntado' + CHAR(13) + CHAR(10) + '06/07/2021 - Solicitado prorrogação por 6 meses, TR e Numerario enviados' + CHAR(13) + CHAR(10) + '25/06/2021 - Cobrado novamente' + CHAR(13) + CHAR(10) + '25/05/2021 - Cobrado procedimento a ser adotado' + CHAR(13) + CHAR(10) + '04/05/2021 - Esteiras do guindaste com defeito e foram reexportadas, DI 21/0585528-7 para novas esteiras, acopladas ao guindaste' + CHAR(13) + CHAR(10) + '08/02/2021 - Despacho Decisorio' + CHAR(13) + CHAR(10) + '21/01/2021 - Docs recebidos, juntada feita no E-CAC' + CHAR(13) + CHAR(10) + '13/01/2021 - Cobrado docs' + CHAR(13) + CHAR(10) + '23/12/2020 - Informado que será prorrogado por 6 meses, TR e Numerario enviados' + CHAR(13) + CHAR(10) + '23/11/2020 - Cobrado procedimento a ser adotado' + CHAR(13) + CHAR(10) + '15/09/2020 - Despacho Decisorio' + CHAR(13) + CHAR(10) + '09/09/2020 - E-CAC com erro (antivirus analisando constantemente), documentos feitos pelo SVA, e protocolo fisicamente junto a RECEITA' + CHAR(13) + CHAR(10) + '27/08/2020 - Solicitado prorrogação ate 23/01/2021, TR e Numerário enviados' + CHAR(13) + CHAR(10) + '17/08/2020 - Cobrado novamente' + CHAR(13) + CHAR(10) + '10/07/2020 - Cobrado qual procedimento deverá ser adotado' + CHAR(13) + CHAR(10) + '18/06/2020 - Despacho Decisorio' + CHAR(13) + CHAR(10) + '08/06/2020 - Juntada enviada pelo E-CAC' + CHAR(13) + CHAR(10) + '28/05/2020 - TR e Numerario enviados, aguardando documentos' + CHAR(13) + CHAR(10) + '27/05/2020 - Cobrado novamente, será prorrogado por mais 3 meses' + CHAR(13) + CHAR(10) + '09/04/2020 - Cobrado procedimento a ser adotado' + CHAR(13) + CHAR(10) + '29/11/2019 - Juntada protocolada no e-CAC.' + CHAR(13) + CHAR(10) + '25/11/2019 - Recebido a documentação para inicio da prorrogação.' + CHAR(13) + CHAR(10) + '14/11/2019 - Cobrado qual procedimento será adotado.' + CHAR(13) + CHAR(10) + '31/10/2019 - Enviado o numerário e aguardando documentação para inicio da prorrogação.' + CHAR(13) + CHAR(10) + '29/10/2019 - Recebido a informação que será prorrogado por 6 meses.' + CHAR(13) + CHAR(10) + '09/10/2019 - Juntada enviada no e-CAC.' + CHAR(13) + CHAR(10) + '08/10/2019 - Recebido os documentos para inicio da prorrogação.' + CHAR(13) + CHAR(10) + '07/10/2019 - Cobrado documentação para inicio da prorrogação.' + CHAR(13) + CHAR(10) + '02/10/2019 - Cobrado documentação para inicio da prorrogação.' + CHAR(13) + CHAR(10) + '19/09/2019 - Enviando TR e numerario.' + CHAR(13) + CHAR(10) + '13/09/2019 - Inormado que será prorrogado por dois meses.' + CHAR(13) + CHAR(10) + '29/08/2019 - Cobrado qual procedimento será adotado.' + CHAR(13) + CHAR(10) + '24/06/2019 - Processo Incluso no controle' | X21: WHEN 19 THEN 'GUINDASTE AUTOPROPELIDO SOBRE ESTEIRAS, MARCA TEREX-DEMAG, MODELO CC2800-I, NUMERO DE SERIE 62277, ANO DE FABRICAÇÃO 2008, USADO, NUMERO DA FROTA 1331, OMPUTADORIZADO, ACIONADO POR MOTOR DIESEL, CAPACIDADE DE 600 TONELADAS, SUPERLIFT, CONTRA-PESOS,COM TODOS ACESSÓRIOS PARA SEU FUNCIONAMENTO, DESMONTADO PARCIALMENTE PARA MANUSEIO E TRANSPORTE.'
A22: =B22&" - "&COUNTIF($B$3:B22,B22) -> MAMMOET - 14 | B22: MAMMOET | C22: 1906086887 | D22: I-19/0142-MBG | E22: CONTAINER OFICINA | F22: PAGA | G22: 131905052962345 | H22: =EDATE(I22,-1) -> 45711 | I22: =EDATE(LEFT(L22,10),-1) -> 45739 | J22: CONTRATO DE LOCAÇÃO S/NR DATADO DE 15/02/2019 | K22: DIVERSOS EQUIPAMENTOS CONFROME DI | L22: 45770 | M22: 43559 | N22: 43564 | O22: CAMPOS DOS GOITACAZES | P22: 11426377000638 | Q22: 10120.004638/0319-14 | R22: 201900038679949 | T22: 19/12/2024 - Juntada efetuada 17/12/2024 - Docs recebidos 25/11/2024 - Cobrado procedimento a ser adotado 22/11/2024 - Juntada efetuada 22/11/2024 - Docs recebidos 14/11/2024 - Numerario enviado, ag retorno 12/11/2024 - SOlicitado renovaçao por mais 1 mes 30/09/2024 - Cobrado procedimento a ser adotado 21/06/2024 - Juntada efetuada 19/06/2024 - Docs recebidos 14/06/2024 - Numerario enviado, ag retorno 11/06/2024 - Solicitado prorrogação por mais 5 meses 03/06/2024 - Cobrado novamente 30/04/2024 - Cobrado procedimento a ser adotado 15/01/2024 - Juntada efetuada 12/01/2024 - Docs recebidos 05/01/2024 - RPR e Numerario enviados, ag retorno 04/01/2024 - Solicitado prorrogação por mais 5 meses 28/12/2023 - Cobrado novamente 01/12/2023 - Cobrado procedimento a ser adotado 21/07/2023 - Juntada efetuada pelo DOSSIE 18/07/2023 - Docs recebidos 26/06/2023 - Solicitado renovação por 6 meses, numerario enviado, ag retorno 01/06/2023 - Cobrado procedimento a ser adotado 19/01/2023 - Juntada efetuada no E-CAC e PORTAL UNICO 11/01/2023 - Recebidos docs 02/01/2023 - Enviado numerario equivalente a 6 meses, aguardando retorno 25/11/2022 - Cobrado procedimento a ser adotado 20/01/2022 - Juntada efetuada através do E-CAC e DOSSIE 03/01/2022 - Informado que será prorrogado por 12 meses 28/12/2021 - Cobrado novamente 23/11/2021 - Cobrado procedimento a ser adotado 21/07/2021 - Recebido docs, juntada efetuada pelo e E-CAC e DOSSIE 06/07/2021 - Solicitado prorrogação por 6 meses, TR e Numerario enviados 25/06/2021 - Cobrado novamente 25/05/2021 - Cobrado procedimento a ser adotado 23/04/2021 - Docs recebidos, juntada efetuada pelo E-CAC e DOSSIE 16/04/2021 - Cobrado novamente 30/03/2021 - Solcitado Prorrogação por 3 meses, Numerario enviado, ag docs 25/03/2021 - Cobrado novamente 22/02/2021 - Cobrado procedimento a ser adotado 04/02/2021 - Despacho Decisorio 21/01/2021 - Docs recebidos, juntada efetuada no E-CAC 13/01/2021 - Cobrado docs 30/12/2020 - Solicitado prorrogação por mais 3 meses, Numerario enviado 29/12/2020 - Cobrado novamente 23/11/2020 - Cobrado procedimento a ser adotado 30/09/2020 - Despacho Decisorio 09/09/2020 - Juntada enviada pelo E-CAC 27/08/2020 - Solicitado prorrogação ate 23/01/2021, TR e Numerário enviados 17/08/2020 - Cobrado novamente 10/07/2020 - Cobrado qual procedimento deverá ser adotado 16/06/2020 - Despacho Decisorio 08/06/2020 - Juntada enviada pelo E-CAC 28/05/2020 - TR e numerario enviados, aguardando documentos 27/05/2020 - Cobrado novamente, informado que será prorrogado por mais 3 meses 09/04/2020 - Cobrado procedimento a ser adotado 29/11/2019 - Juntada enviada no e-CAC. 25/11/2019 -Recebido os documentos para inicio da prorrogação. 14/11/2019 - Cobrado documentos para inicio da prorrogação. 31/10/2019 - Enviado o numerário e aguardando documentação para inicio da prorrogação. 29/10/2019 - Recebido a informação que será prorrogado por 6 meses. 09/10/2019 - Juntada enviada no e-CAC. 08/10/2019 - Recebido os documentos para inicio da prorrogação. 07/10/2019 - Cobrado documentação para inicio da prorrogação. 02/10/2019 - Cobrado documentação para inicio da prorrogação. 19/09/2019 - Enviando TR e numerario. 13/09/2019 - Inormado que será prorrogado por dois meses. 29/08/2019 - Cobrado qual procedimento será adotado. 16/05/2019 - Processo Incluso no controle | U22: MARÍTIMO | V22: ="'"&SUBSTITUTE(T22,CHAR(10),"' + CHAR(13) + CHAR(10) + "&CHAR(10)&"'")&"'" -> '19/12/2024 - Juntada efetuada' + CHAR(13) + CHAR(10) + '17/12/2024 - Docs recebidos' + CHAR(13) + CHAR(10) + '25/11/2024 - Cobrado procedimento a ser adotado' + CHAR(13) + CHAR(10) + '22/11/2024 - Juntada efetuada' + CHAR(13) + CHAR(10) + '22/11/2024 - Docs recebidos' + CHAR(13) + CHAR(10) + '14/11/2024 - Numerario enviado, ag retorno' + CHAR(13) + CHAR(10) + '12/11/2024 - SOlicitado renovaçao por mais 1 mes' + CHAR(13) + CHAR(10) + '30/09/2024 - Cobrado procedimento a ser adotado' + CHAR(13) + CHAR(10) + '21/06/2024 - Juntada efetuada' + CHAR(13) + CHAR(10) + '19/06/2024 - Docs recebidos' + CHAR(13) + CHAR(10) + '14/06/2024 - Numerario enviado, ag retorno' + CHAR(13) + CHAR(10) + '11/06/2024 - Solicitado prorrogação por mais 5 meses' + CHAR(13) + CHAR(10) + '03/06/2024 - Cobrado novamente' + CHAR(13) + CHAR(10) + '30/04/2024 - Cobrado procedimento a ser adotado' + CHAR(13) + CHAR(10) + '15/01/2024 - Juntada efetuada' + CHAR(13) + CHAR(10) + '12/01/2024 - Docs recebidos' + CHAR(13) + CHAR(10) + '05/01/2024 - RPR e Numerario enviados, ag retorno' + CHAR(13) + CHAR(10) + '04/01/2024 - Solicitado prorrogação por mais 5 meses' + CHAR(13) + CHAR(10) + '28/12/2023 - Cobrado novamente' + CHAR(13) + CHAR(10) + '01/12/2023 - Cobrado procedimento a ser adotado' + CHAR(13) + CHAR(10) + '21/07/2023 - Juntada efetuada pelo DOSSIE' + CHAR(13) + CHAR(10) + '18/07/2023 - Docs recebidos' + CHAR(13) + CHAR(10) + '26/06/2023 - Solicitado renovação por 6 meses, numerario enviado, ag retorno' + CHAR(13) + CHAR(10) + '01/06/2023 - Cobrado procedimento a ser adotado' + CHAR(13) + CHAR(10) + '19/01/2023 - Juntada efetuada no E-CAC e PORTAL UNICO' + CHAR(13) + CHAR(10) + '11/01/2023 - Recebidos docs' + CHAR(13) + CHAR(10) + '02/01/2023 - Enviado numerario equivalente a 6 meses, aguardando retorno' + CHAR(13) + CHAR(10) + '25/11/2022 - Cobrado procedimento a ser adotado' + CHAR(13) + CHAR(10) + '20/01/2022 - Juntada efetuada através do E-CAC e DOSSIE' + CHAR(13) + CHAR(10) + '03/01/2022 - Informado que será prorrogado por 12 meses' + CHAR(13) + CHAR(10) + '28/12/2021 - Cobrado novamente' + CHAR(13) + CHAR(10) + '23/11/2021 - Cobrado procedimento a ser adotado' + CHAR(13) + CHAR(10) + '21/07/2021 - Recebido docs, juntada efetuada pelo e E-CAC e DOSSIE' + CHAR(13) + CHAR(10) + '06/07/2021 - Solicitado prorrogação por 6 meses, TR e Numerario enviados' + CHAR(13) + CHAR(10) + '25/06/2021 - Cobrado novamente' + CHAR(13) + CHAR(10) + '25/05/2021 - Cobrado procedimento a ser adotado' + CHAR(13) + CHAR(10) + '23/04/2021 - Docs recebidos, juntada efetuada pelo E-CAC e DOSSIE' + CHAR(13) + CHAR(10) + '16/04/2021 - Cobrado novamente' + CHAR(13) + CHAR(10) + '30/03/2021 - Solcitado Prorrogação por 3 meses, Numerario enviado, ag docs' + CHAR(13) + CHAR(10) + '25/03/2021 - Cobrado novamente' + CHAR(13) + CHAR(10) + '22/02/2021 - Cobrado procedimento a ser adotado' + CHAR(13) + CHAR(10) + '04/02/2021 - Despacho Decisorio' + CHAR(13) + CHAR(10) + '21/01/2021 - Docs recebidos, juntada efetuada no E-CAC' + CHAR(13) + CHAR(10) + '13/01/2021 - Cobrado docs' + CHAR(13) + CHAR(10) + '30/12/2020 - Solicitado prorrogação por mais 3 meses, Numerario enviado' + CHAR(13) + CHAR(10) + '29/12/2020 - Cobrado novamente' + CHAR(13) + CHAR(10) + '23/11/2020 - Cobrado procedimento a ser adotado' + CHAR(13) + CHAR(10) + '30/09/2020 - Despacho Decisorio' + CHAR(13) + CHAR(10) + '09/09/2020 - Juntada enviada pelo E-CAC' + CHAR(13) + CHAR(10) + '27/08/2020 - Solicitado prorrogação ate 23/01/2021, TR e Numerário enviados' + CHAR(13) + CHAR(10) + '17/08/2020 - Cobrado novamente' + CHAR(13) + CHAR(10) + '10/07/2020 - Cobrado qual procedimento deverá ser adotado' + CHAR(13) + CHAR(10) + '16/06/2020 - Despacho Decisorio' + CHAR(13) + CHAR(10) + '08/06/2020 - Juntada enviada pelo E-CAC' + CHAR(13) + CHAR(10) + '28/05/2020 - TR e numerario enviados, aguardando documentos' + CHAR(13) + CHAR(10) + '27/05/2020 - Cobrado novamente, informado que será prorrogado por mais 3 meses' + CHAR(13) + CHAR(10) + '09/04/2020 - Cobrado procedimento a ser adotado' + CHAR(13) + CHAR(10) + '29/11/2019 - Juntada enviada no e-CAC.' + CHAR(13) + CHAR(10) + '25/11/2019 -Recebido os documentos para inicio da prorrogação.' + CHAR(13) + CHAR(10) + '14/11/2019 - Cobrado documentos para inicio da prorrogação.' + CHAR(13) + CHAR(10) + '31/10/2019 - Enviado o numerário e aguardando documentação para inicio da prorrogação.' + CHAR(13) + CHAR(10) + '29/10/2019 - Recebido a informação que será prorrogado por 6 meses.' + CHAR(13) + CHAR(10) + '09/10/2019 - Juntada enviada no e-CAC.' + CHAR(13) + CHAR(10) + '08/10/2019 - Recebido os documentos para inicio da prorrogação.' + CHAR(13) + CHAR(10) + '07/10/2019 - Cobrado documentação para inicio da prorrogação.' + CHAR(13) + CHAR(10) + '02/10/2019 - Cobrado documentação para inicio da prorrogação.' + CHAR(13) + CHAR(10) + '19/09/2019 - Enviando TR e numerario.' + CHAR(13) + CHAR(10) + '13/09/2019 - Inormado que será prorrogado por dois meses.' + CHAR(13) + CHAR(10) + '29/08/2019 - Cobrado qual procedimento será adotado.' + CHAR(13) + CHAR(10) + '16/05/2019 - Processo Incluso no controle' | W22: WHEN 20 THEN '19/12/2024 - Juntada efetuada' + CHAR(13) + CHAR(10) + '17/12/2024 - Docs recebidos' + CHAR(13) + CHAR(10) + '25/11/2024 - Cobrado procedimento a ser adotado' + CHAR(13) + CHAR(10) + '22/11/2024 - Juntada efetuada' + CHAR(13) + CHAR(10) + '22/11/2024 - Docs recebidos' + CHAR(13) + CHAR(10) + '14/11/2024 - Numerario enviado, ag retorno' + CHAR(13) + CHAR(10) + '12/11/2024 - SOlicitado renovaçao por mais 1 mes' + CHAR(13) + CHAR(10) + '30/09/2024 - Cobrado procedimento a ser adotado' + CHAR(13) + CHAR(10) + '21/06/2024 - Juntada efetuada' + CHAR(13) + CHAR(10) + '19/06/2024 - Docs recebidos' + CHAR(13) + CHAR(10) + '14/06/2024 - Numerario enviado, ag retorno' + CHAR(13) + CHAR(10) + '11/06/2024 - Solicitado prorrogação por mais 5 meses' + CHAR(13) + CHAR(10) + '03/06/2024 - Cobrado novamente' + CHAR(13) + CHAR(10) + '30/04/2024 - Cobrado procedimento a ser adotado' + CHAR(13) + CHAR(10) + '15/01/2024 - Juntada efetuada' + CHAR(13) + CHAR(10) + '12/01/2024 - Docs recebidos' + CHAR(13) + CHAR(10) + '05/01/2024 - RPR e Numerario enviados, ag retorno' + CHAR(13) + CHAR(10) + '04/01/2024 - Solicitado prorrogação por mais 5 meses' + CHAR(13) + CHAR(10) + '28/12/2023 - Cobrado novamente' + CHAR(13) + CHAR(10) + '01/12/2023 - Cobrado procedimento a ser adotado' + CHAR(13) + CHAR(10) + '21/07/2023 - Juntada efetuada pelo DOSSIE' + CHAR(13) + CHAR(10) + '18/07/2023 - Docs recebidos' + CHAR(13) + CHAR(10) + '26/06/2023 - Solicitado renovação por 6 meses, numerario enviado, ag retorno' + CHAR(13) + CHAR(10) + '01/06/2023 - Cobrado procedimento a ser adotado' + CHAR(13) + CHAR(10) + '19/01/2023 - Juntada efetuada no E-CAC e PORTAL UNICO' + CHAR(13) + CHAR(10) + '11/01/2023 - Recebidos docs' + CHAR(13) + CHAR(10) + '02/01/2023 - Enviado numerario equivalente a 6 meses, aguardando retorno' + CHAR(13) + CHAR(10) + '25/11/2022 - Cobrado procedimento a ser adotado' + CHAR(13) + CHAR(10) + '20/01/2022 - Juntada efetuada através do E-CAC e DOSSIE' + CHAR(13) + CHAR(10) + '03/01/2022 - Informado que será prorrogado por 12 meses' + CHAR(13) + CHAR(10) + '28/12/2021 - Cobrado novamente' + CHAR(13) + CHAR(10) + '23/11/2021 - Cobrado procedimento a ser adotado' + CHAR(13) + CHAR(10) + '21/07/2021 - Recebido docs, juntada efetuada pelo e E-CAC e DOSSIE' + CHAR(13) + CHAR(10) + '06/07/2021 - Solicitado prorrogação por 6 meses, TR e Numerario enviados' + CHAR(13) + CHAR(10) + '25/06/2021 - Cobrado novamente' + CHAR(13) + CHAR(10) + '25/05/2021 - Cobrado procedimento a ser adotado' + CHAR(13) + CHAR(10) + '23/04/2021 - Docs recebidos, juntada efetuada pelo E-CAC e DOSSIE' + CHAR(13) + CHAR(10) + '16/04/2021 - Cobrado novamente' + CHAR(13) + CHAR(10) + '30/03/2021 - Solcitado Prorrogação por 3 meses, Numerario enviado, ag docs' + CHAR(13) + CHAR(10) + '25/03/2021 - Cobrado novamente' + CHAR(13) + CHAR(10) + '22/02/2021 - Cobrado procedimento a ser adotado' + CHAR(13) + CHAR(10) + '04/02/2021 - Despacho Decisorio' + CHAR(13) + CHAR(10) + '21/01/2021 - Docs recebidos, juntada efetuada no E-CAC' + CHAR(13) + CHAR(10) + '13/01/2021 - Cobrado docs' + CHAR(13) + CHAR(10) + '30/12/2020 - Solicitado prorrogação por mais 3 meses, Numerario enviado' + CHAR(13) + CHAR(10) + '29/12/2020 - Cobrado novamente' + CHAR(13) + CHAR(10) + '23/11/2020 - Cobrado procedimento a ser adotado' + CHAR(13) + CHAR(10) + '30/09/2020 - Despacho Decisorio' + CHAR(13) + CHAR(10) + '09/09/2020 - Juntada enviada pelo E-CAC' + CHAR(13) + CHAR(10) + '27/08/2020 - Solicitado prorrogação ate 23/01/2021, TR e Numerário enviados' + CHAR(13) + CHAR(10) + '17/08/2020 - Cobrado novamente' + CHAR(13) + CHAR(10) + '10/07/2020 - Cobrado qual procedimento deverá ser adotado' + CHAR(13) + CHAR(10) + '16/06/2020 - Despacho Decisorio' + CHAR(13) + CHAR(10) + '08/06/2020 - Juntada enviada pelo E-CAC' + CHAR(13) + CHAR(10) + '28/05/2020 - TR e numerario enviados, aguardando documentos' + CHAR(13) + CHAR(10) + '27/05/2020 - Cobrado novamente, informado que será prorrogado por mais 3 meses' + CHAR(13) + CHAR(10) + '09/04/2020 - Cobrado procedimento a ser adotado' + CHAR(13) + CHAR(10) + '29/11/2019 - Juntada enviada no e-CAC.' + CHAR(13) + CHAR(10) + '25/11/2019 -Recebido os documentos para inicio da prorrogação.' + CHAR(13) + CHAR(10) + '14/11/2019 - Cobrado documentos para inicio da prorrogação.' + CHAR(13) + CHAR(10) + '31/10/2019 - Enviado o numerário e aguardando documentação para inicio da prorrogação.' + CHAR(13) + CHAR(10) + '29/10/2019 - Recebido a informação que será prorrogado por 6 meses.' + CHAR(13) + CHAR(10) + '09/10/2019 - Juntada enviada no e-CAC.' + CHAR(13) + CHAR(10) + '08/10/2019 - Recebido os documentos para inicio da prorrogação.' + CHAR(13) + CHAR(10) + '07/10/2019 - Cobrado documentação para inicio da prorrogação.' + CHAR(13) + CHAR(10) + '02/10/2019 - Cobrado documentação para inicio da prorrogação.' + CHAR(13) + CHAR(10) + '19/09/2019 - Enviando TR e numerario.' + CHAR(13) + CHAR(10) + '13/09/2019 - Inormado que será prorrogado por dois meses.' + CHAR(13) + CHAR(10) + '29/08/2019 - Cobrado qual procedimento será adotado.' + CHAR(13) + CHAR(10) + '16/05/2019 - Processo Incluso no controle' | X22: WHEN 20 THEN 'DIVERSOS EQUIPAMENTOS CONFROME DI'
A23: =B23&" - "&COUNTIF($B$3:B23,B23) -> MAMMOET - 15 | B23: MAMMOET | C23: 2117294706 | D23: I-21/1419-MBG | E23: CC2800-1 | F23: SUSPENSA | G23: 132105211325412 | H23: =EDATE(I23,-1) -> 45711 | I23: =EDATE(LEFT(L23,10),-1) -> 45739 | J23: CONTRATO DE LOCAÇÃO DATADO DE 15/02/2018 | K23: Seção de lança de 12 metros usada para guindaste Terex-Demag CC 2800 - 1 com todas as peças e acessórios para montagem e operação, marca: Terex Demag, tipo: 12 Meter Main Boom Insert 2724-20-01, numero de série 62277, fleet number 1331, ano de fabricação 2008 - usado. | L23: 45770 | M23: 44449 | N23: 44459 | O23: MULTIRIO-RJ | P23: 11426377000638 | R23: 202100119592274 | T23: 19/12/2024 - Juntada efetuada 18/12/2024 - Docs recebidos 25/11/2024 - Cobrado procedimento a ser adotado 25/11/2024 - Juntada efetuada 22/11/2024 - Docs recebidos 14/11/2024 - Numerario enviado, ag retorno 11/11/2024 - Solicitado prorrogaçao por mais 1 mes 30/09/2024 - Cobrado procedimento a ser adotado 21/06/2024 - Juntada efetuada 19/06/2024 - Docs recebidos 14/06/2024 - Numerario enviado, ag retorno 11/06/2024 - Soclitiado prorrogação por mais 5 meses 03/06/2024 - Cobrado novamente 30/04/2024 - Cobrado procedimento a ser adotado 22/03/2024 - Juntada efetuada 14/03/2024 - Docs recedibos 11/03/2024 - Informado que será prorrogado por mais 3 meses, numerario, RPR e TR enviados, ag retorno 01/03/2024 - Cobrado novamente 25/01/2024 - Cobrado procedimento a ser adotado 20/10/2023 - Juntada efetuada 18/10/2023 - Docs recebidos 06/10/2023 - TR, RPR e Numerario enviado, ag retorno 03/10/2023 - Informado que será prorrogado por mais 5 meses 29/09/2023 - Cobrado novamente 30/08/2023 - Cobrado procedimento a ser adotado 21/07/2023 - Juntada efetuada através do DOSSIE 19/07/2023 - Docs recebidos 27/06/2023 - Numerario, TR e RPR enviados, ag retorno 22/06/2023 - Solicitado prorrogação por 3 meses 01/06/2023 - Cobrado procedimento a ser adotado 19/01/2023 - Juntada efetuada através do DOSSIÊ 12/01/2023 - Docs recebidos 02/01/2023 - Enviado Numerario, RPR e TR equivalente a 6 meses, aguardando retorno 25/11/2022 - Cobrado procedimento a ser adotado 21/01/2022 - Juntada anexada ao DOSSIE 03/01/2022 - Informado que será renovado por 12 meses 28/12/2021 - Cobrado novamente 23/11/2021 - Cobrado procedimento a ser adotado 29/10/2021 - Processo incluido no controle | U23: MARÍTIMO | V23: ="'"&SUBSTITUTE(T23,CHAR(10),"' + CHAR(13) + CHAR(10) + "&CHAR(10)&"'")&"'" -> '19/12/2024 - Juntada efetuada' + CHAR(13) + CHAR(10) + '18/12/2024 - Docs recebidos' + CHAR(13) + CHAR(10) + '25/11/2024 - Cobrado procedimento a ser adotado' + CHAR(13) + CHAR(10) + '25/11/2024 - Juntada efetuada' + CHAR(13) + CHAR(10) + '22/11/2024 - Docs recebidos' + CHAR(13) + CHAR(10) + '14/11/2024 - Numerario enviado, ag retorno' + CHAR(13) + CHAR(10) + '11/11/2024 - Solicitado prorrogaçao por mais 1 mes' + CHAR(13) + CHAR(10) + '30/09/2024 - Cobrado procedimento a ser adotado' + CHAR(13) + CHAR(10) + '21/06/2024 - Juntada efetuada' + CHAR(13) + CHAR(10) + '19/06/2024 - Docs recebidos' + CHAR(13) + CHAR(10) + '14/06/2024 - Numerario enviado, ag retorno' + CHAR(13) + CHAR(10) + '11/06/2024 - Soclitiado prorrogação por mais 5 meses' + CHAR(13) + CHAR(10) + '03/06/2024 - Cobrado novamente' + CHAR(13) + CHAR(10) + '30/04/2024 - Cobrado procedimento a ser adotado' + CHAR(13) + CHAR(10) + '22/03/2024 - Juntada efetuada' + CHAR(13) + CHAR(10) + '14/03/2024 - Docs recedibos' + CHAR(13) + CHAR(10) + '11/03/2024 - Informado que será prorrogado por mais 3 meses, numerario, RPR e TR enviados, ag retorno' + CHAR(13) + CHAR(10) + '01/03/2024 - Cobrado novamente' + CHAR(13) + CHAR(10) + '25/01/2024 - Cobrado procedimento a ser adotado' + CHAR(13) + CHAR(10) + '20/10/2023 - Juntada efetuada' + CHAR(13) + CHAR(10) + '18/10/2023 - Docs recebidos' + CHAR(13) + CHAR(10) + '06/10/2023 - TR, RPR e Numerario enviado, ag retorno' + CHAR(13) + CHAR(10) + '03/10/2023 - Informado que será prorrogado por mais 5 meses' + CHAR(13) + CHAR(10) + '29/09/2023 - Cobrado novamente' + CHAR(13) + CHAR(10) + '30/08/2023 - Cobrado procedimento a ser adotado' + CHAR(13) + CHAR(10) + '21/07/2023 - Juntada efetuada através do DOSSIE' + CHAR(13) + CHAR(10) + '19/07/2023 - Docs recebidos' + CHAR(13) + CHAR(10) + '27/06/2023 - Numerario, TR e RPR enviados, ag retorno' + CHAR(13) + CHAR(10) + '22/06/2023 - Solicitado prorrogação por 3 meses' + CHAR(13) + CHAR(10) + '01/06/2023 - Cobrado procedimento a ser adotado' + CHAR(13) + CHAR(10) + '19/01/2023 - Juntada efetuada através do DOSSIÊ' + CHAR(13) + CHAR(10) + '12/01/2023 - Docs recebidos' + CHAR(13) + CHAR(10) + '02/01/2023 - Enviado Numerario, RPR e TR equivalente a 6 meses, aguardando retorno' + CHAR(13) + CHAR(10) + '25/11/2022 - Cobrado procedimento a ser adotado' + CHAR(13) + CHAR(10) + '21/01/2022 - Juntada anexada ao DOSSIE' + CHAR(13) + CHAR(10) + '03/01/2022 - Informado que será renovado por 12 meses' + CHAR(13) + CHAR(10) + '28/12/2021 - Cobrado novamente' + CHAR(13) + CHAR(10) + '23/11/2021 - Cobrado procedimento a ser adotado' + CHAR(13) + CHAR(10) + '29/10/2021 - Processo incluido no controle' | W23: WHEN 21 THEN '19/12/2024 - Juntada efetuada' + CHAR(13) + CHAR(10) + '18/12/2024 - Docs recebidos' + CHAR(13) + CHAR(10) + '25/11/2024 - Cobrado procedimento a ser adotado' + CHAR(13) + CHAR(10) + '25/11/2024 - Juntada efetuada' + CHAR(13) + CHAR(10) + '22/11/2024 - Docs recebidos' + CHAR(13) + CHAR(10) + '14/11/2024 - Numerario enviado, ag retorno' + CHAR(13) + CHAR(10) + '11/11/2024 - Solicitado prorrogaçao por mais 1 mes' + CHAR(13) + CHAR(10) + '30/09/2024 - Cobrado procedimento a ser adotado' + CHAR(13) + CHAR(10) + '21/06/2024 - Juntada efetuada' + CHAR(13) + CHAR(10) + '19/06/2024 - Docs recebidos' + CHAR(13) + CHAR(10) + '14/06/2024 - Numerario enviado, ag retorno' + CHAR(13) + CHAR(10) + '11/06/2024 - Soclitiado prorrogação por mais 5 meses' + CHAR(13) + CHAR(10) + '03/06/2024 - Cobrado novamente' + CHAR(13) + CHAR(10) + '30/04/2024 - Cobrado procedimento a ser adotado' + CHAR(13) + CHAR(10) + '22/03/2024 - Juntada efetuada' + CHAR(13) + CHAR(10) + '14/03/2024 - Docs recedibos' + CHAR(13) + CHAR(10) + '11/03/2024 - Informado que será prorrogado por mais 3 meses, numerario, RPR e TR enviados, ag retorno' + CHAR(13) + CHAR(10) + '01/03/2024 - Cobrado novamente' + CHAR(13) + CHAR(10) + '25/01/2024 - Cobrado procedimento a ser adotado' + CHAR(13) + CHAR(10) + '20/10/2023 - Juntada efetuada' + CHAR(13) + CHAR(10) + '18/10/2023 - Docs recebidos' + CHAR(13) + CHAR(10) + '06/10/2023 - TR, RPR e Numerario enviado, ag retorno' + CHAR(13) + CHAR(10) + '03/10/2023 - Informado que será prorrogado por mais 5 meses' + CHAR(13) + CHAR(10) + '29/09/2023 - Cobrado novamente' + CHAR(13) + CHAR(10) + '30/08/2023 - Cobrado procedimento a ser adotado' + CHAR(13) + CHAR(10) + '21/07/2023 - Juntada efetuada através do DOSSIE' + CHAR(13) + CHAR(10) + '19/07/2023 - Docs recebidos' + CHAR(13) + CHAR(10) + '27/06/2023 - Numerario, TR e RPR enviados, ag retorno' + CHAR(13) + CHAR(10) + '22/06/2023 - Solicitado prorrogação por 3 meses' + CHAR(13) + CHAR(10) + '01/06/2023 - Cobrado procedimento a ser adotado' + CHAR(13) + CHAR(10) + '19/01/2023 - Juntada efetuada através do DOSSIÊ' + CHAR(13) + CHAR(10) + '12/01/2023 - Docs recebidos' + CHAR(13) + CHAR(10) + '02/01/2023 - Enviado Numerario, RPR e TR equivalente a 6 meses, aguardando retorno' + CHAR(13) + CHAR(10) + '25/11/2022 - Cobrado procedimento a ser adotado' + CHAR(13) + CHAR(10) + '21/01/2022 - Juntada anexada ao DOSSIE' + CHAR(13) + CHAR(10) + '03/01/2022 - Informado que será renovado por 12 meses' + CHAR(13) + CHAR(10) + '28/12/2021 - Cobrado novamente' + CHAR(13) + CHAR(10) + '23/11/2021 - Cobrado procedimento a ser adotado' + CHAR(13) + CHAR(10) + '29/10/2021 - Processo incluido no controle' | X23: WHEN 21 THEN 'SEÇÃO DE LANÇA DE 12 METROS USADA PARA GUINDASTE TEREX-DEMAG CC 2800 - 1 COM TODAS AS PEÇAS E ACESSÓRIOS PARA MONTAGEM E OPERAÇÃO, MARCA: TEREX DEMAG, TIPO: 12 METER MAIN BOOM INSERT 2724-20-01, NUMERO DE SÉRIE 62277, FLEET NUMBER 1331, ANO DE FABRICAÇÃO 2008 - USADO.'
A24: =B24&" - "&COUNTIF($B$3:B24,B24) -> MAMMOET - 16 | B24: MAMMOET | C24: 2406046760 | D24: I-24/0252-MBG | E24: JIB | F24: SUSPENSA | G24: 72405055138258 | H24: =EDATE(I24,-1) -> 45713 | I24: =EDATE(LEFT(L24,10),-1) -> 45741 | J24: CONTRATO DE COMODATO DE 27/02/2024 | K24: Lança auxiliar mecânica para aumentar o comprimento, altura e raio do guindaste, usado, capacidade: 90 tons, Marca: Grove, Modelo: RT 890E, ano de fabricação 2012, número de equipamento/série: 232649. | L24: 45772 | M24: 45371 | N24: 45376 | O24: SUATA SERV. LOG-SUAPE | P24: 11426377000123 | R24: 202400230765378 | T24: 23/12/2024 - Juntada efetuada, docs recebidos 29/11/2024 - Enviado numerario, ag retorno 27/11/2024 - Solicitado prorrogaçao por mais 4 meses 27/11/2024 - Cobrado procedimento a ser adotado 25/11/2024 - Juntada efetuada 22/11/2024 - Docs recebidos 14/11/2024 - Numerario enviado, ag retorno 12/11/2024 - Solicitado prorrogaçao por mais 1 mes 30/09/2024 - Cobrado procedimento a ser adotado 25/06/2024 - Juntada efetuada 25/06/2024 - Docs recebidos 17/06/2024 - Numerario enviado, ag retorno 11/06/2024 - Prorrogaçao por mais 5 meses 03/06/2024 - Cobrado novamente 30/04/2024 - Cobrado procedimento a ser adotado 08/04/2024 - Processo incluído no controle | U24: MARÍTIMO | V24: ="'"&SUBSTITUTE(T24,CHAR(10),"' + CHAR(13) + CHAR(10) + "&CHAR(10)&"'")&"'" -> '23/12/2024 - Juntada efetuada, docs recebidos' + CHAR(13) + CHAR(10) + '29/11/2024 - Enviado numerario, ag retorno' + CHAR(13) + CHAR(10) + '27/11/2024 - Solicitado prorrogaçao por mais 4 meses' + CHAR(13) + CHAR(10) + '27/11/2024 - Cobrado procedimento a ser adotado' + CHAR(13) + CHAR(10) + '25/11/2024 - Juntada efetuada' + CHAR(13) + CHAR(10) + '22/11/2024 - Docs recebidos' + CHAR(13) + CHAR(10) + '14/11/2024 - Numerario enviado, ag retorno' + CHAR(13) + CHAR(10) + '12/11/2024 - Solicitado prorrogaçao por mais 1 mes' + CHAR(13) + CHAR(10) + '30/09/2024 - Cobrado procedimento a ser adotado' + CHAR(13) + CHAR(10) + '25/06/2024 - Juntada efetuada' + CHAR(13) + CHAR(10) + '25/06/2024 - Docs recebidos' + CHAR(13) + CHAR(10) + '17/06/2024 - Numerario enviado, ag retorno' + CHAR(13) + CHAR(10) + '11/06/2024 - Prorrogaçao por mais 5 meses' + CHAR(13) + CHAR(10) + '03/06/2024 - Cobrado novamente' + CHAR(13) + CHAR(10) + '30/04/2024 - Cobrado procedimento a ser adotado' + CHAR(13) + CHAR(10) + '08/04/2024 - Processo incluído no controle' | W24: WHEN 22 THEN '23/12/2024 - Juntada efetuada, docs recebidos' + CHAR(13) + CHAR(10) + '29/11/2024 - Enviado numerario, ag retorno' + CHAR(13) + CHAR(10) + '27/11/2024 - Solicitado prorrogaçao por mais 4 meses' + CHAR(13) + CHAR(10) + '27/11/2024 - Cobrado procedimento a ser adotado' + CHAR(13) + CHAR(10) + '25/11/2024 - Juntada efetuada' + CHAR(13) + CHAR(10) + '22/11/2024 - Docs recebidos' + CHAR(13) + CHAR(10) + '14/11/2024 - Numerario enviado, ag retorno' + CHAR(13) + CHAR(10) + '12/11/2024 - Solicitado prorrogaçao por mais 1 mes' + CHAR(13) + CHAR(10) + '30/09/2024 - Cobrado procedimento a ser adotado' + CHAR(13) + CHAR(10) + '25/06/2024 - Juntada efetuada' + CHAR(13) + CHAR(10) + '25/06/2024 - Docs recebidos' + CHAR(13) + CHAR(10) + '17/06/2024 - Numerario enviado, ag retorno' + CHAR(13) + CHAR(10) + '11/06/2024 - Prorrogaçao por mais 5 meses' + CHAR(13) + CHAR(10) + '03/06/2024 - Cobrado novamente' + CHAR(13) + CHAR(10) + '30/04/2024 - Cobrado procedimento a ser adotado' + CHAR(13) + CHAR(10) + '08/04/2024 - Processo incluído no controle' | X24: WHEN 22 THEN 'LANÇA AUXILIAR MECÂNICA PARA AUMENTAR O COMPRIMENTO, ALTURA E RAIO DO GUINDASTE, USADO, CAPACIDADE: 90 TONS, MARCA: GROVE, MODELO: RT 890E, ANO DE FABRICAÇÃO 2012, NÚMERO DE EQUIPAMENTO/SÉRIE: 232649.'
A25: =B25&" - "&COUNTIF($B$3:B25,B25) -> MAMMOET - 17 | B25: MAMMOET | C25: 2210462397 | D25: I-22/0623-MBG | E25: CKE1100G2 - KOBELCO | F25: SUSPENSA | G25: 102205119780521 | H25: =EDATE(I25,-1) -> 45716 | I25: =EDATE(LEFT(L25,10),-1) -> 45744 | J25: S/NR. | K25: Guindaste autopropelido sobre esteiras, marca Kobelco, modelo CKE1100 G-2 , número de serie GK06-05004, ano de fabricação 2016 - usado, número da frota 2678, computadorizado, acionado por motor diesel, capacidade de 110 toneladas, contra-pesos, com todos acessórios para seu funcionamento até 28 metros de lança, desmontado parcialmente para manuseio e transporte. | L25: 45775 | M25: 44714 | N25: 44740 | O25: PORTO DE SALVADOR - INTERMARITIMA TERMINAIS LTDA. | P25: 11426377000123 | R25: 202200151499195 | S25: 46540 | T25: 26/12/2024 - Juntada efetuada 23/12/2024 - Docs recebidos 28/10/2024 - Cobrado procedimento a ser adotado 27/09/2024 - Juntada efetuada 27/09/2024 - Docs recebidos 09/09/2024 - Cobrado novamente 05/08/2024 - Cobrado procedimento a ser adotado 28/06/2024 - Juntada efetuada 27/06/2024 - Docs recebidos 14/06/2024 - Numerario enviado, ag retorno 13/06/2024 - Solicitado prorrogação por mais 3 meses 03/06/2024 - Cobrado novamente 30/04/2024 - Cobrado procedimento a ser adotado 27/12/2023 - Juntada efetuada. 30/11/2023 - Numerario e RPR enviados, ag retorno 22/11/2023 - Informado que será prorrogado por mais 6 meses 30/10/2023 - Cobrado procedimento a ser adotado 27/06/2023 - Juntada efetuada através do DOSSIE 27/06/2023 - Doctos recebidos 01/06/2023 - Solicitado prorrogação por 6 meses, TR, RAT e Numerario enviados, ag retorno 26/04/2023 - Cobrado procedimento a ser adotado 28/07/2022 - Processo incluido no controle | U25: MARÍTIMO | V25: ="'"&SUBSTITUTE(T25,CHAR(10),"' + CHAR(13) + CHAR(10) + "&CHAR(10)&"'")&"'" -> '26/12/2024 - Juntada efetuada' + CHAR(13) + CHAR(10) + '23/12/2024 - Docs recebidos' + CHAR(13) + CHAR(10) + '28/10/2024 - Cobrado procedimento a ser adotado' + CHAR(13) + CHAR(10) + '27/09/2024 - Juntada efetuada' + CHAR(13) + CHAR(10) + '27/09/2024 - Docs recebidos' + CHAR(13) + CHAR(10) + '09/09/2024 - Cobrado novamente' + CHAR(13) + CHAR(10) + '05/08/2024 - Cobrado procedimento a ser adotado' + CHAR(13) + CHAR(10) + '28/06/2024 - Juntada efetuada' + CHAR(13) + CHAR(10) + '27/06/2024 - Docs recebidos' + CHAR(13) + CHAR(10) + '14/06/2024 - Numerario enviado, ag retorno' + CHAR(13) + CHAR(10) + '13/06/2024 - Solicitado prorrogação por mais 3 meses' + CHAR(13) + CHAR(10) + '03/06/2024 - Cobrado novamente' + CHAR(13) + CHAR(10) + '30/04/2024 - Cobrado procedimento a ser adotado' + CHAR(13) + CHAR(10) + '27/12/2023 - Juntada efetuada.' + CHAR(13) + CHAR(10) + '30/11/2023 - Numerario e RPR enviados, ag retorno' + CHAR(13) + CHAR(10) + '22/11/2023 - Informado que será prorrogado por mais 6 meses' + CHAR(13) + CHAR(10) + '30/10/2023 - Cobrado procedimento a ser adotado' + CHAR(13) + CHAR(10) + '27/06/2023 - Juntada efetuada através do DOSSIE' + CHAR(13) + CHAR(10) + '27/06/2023 - Doctos recebidos' + CHAR(13) + CHAR(10) + '01/06/2023 - Solicitado prorrogação por 6 meses, TR, RAT e Numerario enviados, ag retorno' + CHAR(13) + CHAR(10) + '26/04/2023 - Cobrado procedimento a ser adotado' + CHAR(13) + CHAR(10) + '28/07/2022 - Processo incluido no controle' | W25: WHEN 23 THEN '26/12/2024 - Juntada efetuada' + CHAR(13) + CHAR(10) + '23/12/2024 - Docs recebidos' + CHAR(13) + CHAR(10) + '28/10/2024 - Cobrado procedimento a ser adotado' + CHAR(13) + CHAR(10) + '27/09/2024 - Juntada efetuada' + CHAR(13) + CHAR(10) + '27/09/2024 - Docs recebidos' + CHAR(13) + CHAR(10) + '09/09/2024 - Cobrado novamente' + CHAR(13) + CHAR(10) + '05/08/2024 - Cobrado procedimento a ser adotado' + CHAR(13) + CHAR(10) + '28/06/2024 - Juntada efetuada' + CHAR(13) + CHAR(10) + '27/06/2024 - Docs recebidos' + CHAR(13) + CHAR(10) + '14/06/2024 - Numerario enviado, ag retorno' + CHAR(13) + CHAR(10) + '13/06/2024 - Solicitado prorrogação por mais 3 meses' + CHAR(13) + CHAR(10) + '03/06/2024 - Cobrado novamente' + CHAR(13) + CHAR(10) + '30/04/2024 - Cobrado procedimento a ser adotado' + CHAR(13) + CHAR(10) + '27/12/2023 - Juntada efetuada.' + CHAR(13) + CHAR(10) + '30/11/2023 - Numerario e RPR enviados, ag retorno' + CHAR(13) + CHAR(10) + '22/11/2023 - Informado que será prorrogado por mais 6 meses' + CHAR(13) + CHAR(10) + '30/10/2023 - Cobrado procedimento a ser adotado' + CHAR(13) + CHAR(10) + '27/06/2023 - Juntada efetuada através do DOSSIE' + CHAR(13) + CHAR(10) + '27/06/2023 - Doctos recebidos' + CHAR(13) + CHAR(10) + '01/06/2023 - Solicitado prorrogação por 6 meses, TR, RAT e Numerario enviados, ag retorno' + CHAR(13) + CHAR(10) + '26/04/2023 - Cobrado procedimento a ser adotado' + CHAR(13) + CHAR(10) + '28/07/2022 - Processo incluido no controle' | X25: WHEN 23 THEN 'GUINDASTE AUTOPROPELIDO SOBRE ESTEIRAS, MARCA KOBELCO, MODELO CKE1100 G-2 , NÚMERO DE SERIE GK06-05004, ANO DE FABRICAÇÃO 2016 - USADO, NÚMERO DA FROTA 2678, COMPUTADORIZADO, ACIONADO POR MOTOR DIESEL, CAPACIDADE DE 110 TONELADAS, CONTRA-PESOS, COM TODOS ACESSÓRIOS PARA SEU FUNCIONAMENTO ATÉ 28 METROS DE LANÇA, DESMONTADO PARCIALMENTE PARA MANUSEIO E TRANSPORTE.'
A26: =B26&" - "&COUNTIF($B$3:B26,B26) -> MAMMOET - 18 | B26: MAMMOET | C26: 2210427150 | D26: I-22/0631-MBG | E26: LR1300 | F26: SUSPENSA | G26: 102205119780440 | H26: =EDATE(I26,-1) -> 45716 | I26: =EDATE(LEFT(L26,10),-1) -> 45744 | J26: S/NR. | K26: GUINDASTE AUTOPROPULSADO SOB ESTEIRAS, MARCA LIEBHERR, MODELO LR1300-W, SERIE 138128, ANO 2010 - USADO, NUMERO DE FROTA 1844, COM CAPACIDADE TOTAL DE ELEVAÇÃO MÁXIMA DE 300 TONELADAS, INTEIRAMENTE DESMONTADO PARA MANUSEIO E TRANSPORTE, COM TODOS OS SEUS ACESSÓRIOS PARA SEU FUNCIONAMENTO ATÉ 65 METROS DE LANÇA, COMPOSTODE: CORPO PRINCIPAL, ESTEIRAS, CONTRAPESOS, LANÇA PRINCIPAL , DISPOSITIVOS E FERRAMENTAS DE MONTAGEM E IÇAMENTO E DEMAIS ACESSÓRIOS NECESSÁRIOS A OPERAÇÃO DO EQUIPAMENTO | L26: 45775 | M26: 44714 | N26: 44740 | O26: PORTO DE SALVADOR - INTERMARITIMA TERMINAIS LTDA. | P26: 11426377000123 | R26: 202200151629293 | S26: 46540 | T26: 26/12/2024 - Juntada efetuada 23/12/2024 - Docs recebidos 28/10/2024 - Cobrado procedimento a ser adotado 27/09/2024 - Juntada efetuada 27/09/2024 - Docs recebidos 09/09/2024 - Cobrado novamente 05/08/2024 - Cobrado procedimento a ser adotado 28/06/2024 - Juntada efetuada 27/06/2024 - Docs recebidos 17/06/2024 - Numerario enviado, ag retorno 13/06/2024 - Prorrogação por mais 3 meses 30/04/2024 - Cobrado procedimento a ser adotado 26/12/2023 - Juntada efetuada. 30/11/2023 - Numerario e RPR enviados, ag retorno 22/11/2023 - Solicitado prorrogação por mais 6 meses 30/10/2023 - Cobrado procedimento a ser adotado 27/06/2023 - Juntada efetuada através do DOSSIE 26/06/2023 - Documentação recebida 01/06/2023 - Solicitado prorrogação por 6 meses, Numerario, TR e RAT enviados, aguardando retorno 26/04/2023 - Cobrado procediment a ser adotado 28/07/2022 - Processo incluido no controle | U26: MARÍTIMO | V26: ="'"&SUBSTITUTE(T26,CHAR(10),"' + CHAR(13) + CHAR(10) + "&CHAR(10)&"'")&"'" -> '26/12/2024 - Juntada efetuada' + CHAR(13) + CHAR(10) + '23/12/2024 - Docs recebidos' + CHAR(13) + CHAR(10) + '28/10/2024 - Cobrado procedimento a ser adotado' + CHAR(13) + CHAR(10) + '27/09/2024 - Juntada efetuada' + CHAR(13) + CHAR(10) + '27/09/2024 - Docs recebidos' + CHAR(13) + CHAR(10) + '09/09/2024 - Cobrado novamente' + CHAR(13) + CHAR(10) + '05/08/2024 - Cobrado procedimento a ser adotado' + CHAR(13) + CHAR(10) + '28/06/2024 - Juntada efetuada' + CHAR(13) + CHAR(10) + '27/06/2024 - Docs recebidos' + CHAR(13) + CHAR(10) + '17/06/2024 - Numerario enviado, ag retorno' + CHAR(13) + CHAR(10) + '13/06/2024 - Prorrogação por mais 3 meses' + CHAR(13) + CHAR(10) + '30/04/2024 - Cobrado procedimento a ser adotado' + CHAR(13) + CHAR(10) + '26/12/2023 - Juntada efetuada.' + CHAR(13) + CHAR(10) + '30/11/2023 - Numerario e RPR enviados, ag retorno' + CHAR(13) + CHAR(10) + '22/11/2023 - Solicitado prorrogação por mais 6 meses' + CHAR(13) + CHAR(10) + '30/10/2023 - Cobrado procedimento a ser adotado' + CHAR(13) + CHAR(10) + '27/06/2023 - Juntada efetuada através do DOSSIE' + CHAR(13) + CHAR(10) + '26/06/2023 - Documentação recebida' + CHAR(13) + CHAR(10) + '01/06/2023 - Solicitado prorrogação por 6 meses, Numerario, TR e RAT enviados, aguardando retorno' + CHAR(13) + CHAR(10) + '26/04/2023 - Cobrado procediment a ser adotado' + CHAR(13) + CHAR(10) + '28/07/2022 - Processo incluido no controle' | W26: WHEN 24 THEN '26/12/2024 - Juntada efetuada' + CHAR(13) + CHAR(10) + '23/12/2024 - Docs recebidos' + CHAR(13) + CHAR(10) + '28/10/2024 - Cobrado procedimento a ser adotado' + CHAR(13) + CHAR(10) + '27/09/2024 - Juntada efetuada' + CHAR(13) + CHAR(10) + '27/09/2024 - Docs recebidos' + CHAR(13) + CHAR(10) + '09/09/2024 - Cobrado novamente' + CHAR(13) + CHAR(10) + '05/08/2024 - Cobrado procedimento a ser adotado' + CHAR(13) + CHAR(10) + '28/06/2024 - Juntada efetuada' + CHAR(13) + CHAR(10) + '27/06/2024 - Docs recebidos' + CHAR(13) + CHAR(10) + '17/06/2024 - Numerario enviado, ag retorno' + CHAR(13) + CHAR(10) + '13/06/2024 - Prorrogação por mais 3 meses' + CHAR(13) + CHAR(10) + '30/04/2024 - Cobrado procedimento a ser adotado' + CHAR(13) + CHAR(10) + '26/12/2023 - Juntada efetuada.' + CHAR(13) + CHAR(10) + '30/11/2023 - Numerario e RPR enviados, ag retorno' + CHAR(13) + CHAR(10) + '22/11/2023 - Solicitado prorrogação por mais 6 meses' + CHAR(13) + CHAR(10) + '30/10/2023 - Cobrado procedimento a ser adotado' + CHAR(13) + CHAR(10) + '27/06/2023 - Juntada efetuada através do DOSSIE' + CHAR(13) + CHAR(10) + '26/06/2023 - Documentação recebida' + CHAR(13) + CHAR(10) + '01/06/2023 - Solicitado prorrogação por 6 meses, Numerario, TR e RAT enviados, aguardando retorno' + CHAR(13) + CHAR(10) + '26/04/2023 - Cobrado procediment a ser adotado' + CHAR(13) + CHAR(10) + '28/07/2022 - Processo incluido no controle' | X26: WHEN 24 THEN 'GUINDASTE AUTOPROPULSADO SOB ESTEIRAS, MARCA LIEBHERR, MODELO LR1300-W, SERIE 138128, ANO 2010 - USADO, NUMERO DE FROTA 1844, COM CAPACIDADE TOTAL DE ELEVAÇÃO MÁXIMA DE 300 TONELADAS, INTEIRAMENTE DESMONTADO PARA MANUSEIO E TRANSPORTE, COM TODOS OS SEUS ACESSÓRIOS PARA SEU FUNCIONAMENTO ATÉ 65 METROS DE LANÇA, COMPOSTODE: CORPO PRINCIPAL, ESTEIRAS, CONTRAPESOS, LANÇA PRINCIPAL , DISPOSITIVOS E FERRAMENTAS DE MONTAGEM E IÇAMENTO E DEMAIS ACESSÓRIOS NECESSÁRIOS A OPERAÇÃO DO EQUIPAMENTO'
A27: =B27&" - "&COUNTIF($B$3:B27,B27) -> MAMMOET - 19 | B27: MAMMOET | C27: 2210450267 | D27: I-22/0621-MBG | E27: CK1100 (KOBELCO) | F27: SUSPENSA | G27: 102205119780602 | H27: =EDATE(I27,-1) -> 45716 | I27: =EDATE(LEFT(L27,10),-1) -> 45744 | J27: S/NR. | K27: Guindaste autopropelido sobre esteiras, marca Kobelco, modelo CK1100 , número de serie GH04-03371, ano de fabricação 2014 - usado, número da frota 2611, computadorizado, acionado por motor diesel, capacidade de 110 toneladas, contra-pesos, com todos acessórios para seu funcionamento até 28 metros de lança, desmontado parcialmente para manuseio e transporte. | L27: 45775 | M27: 44714 | N27: 44740 | O27: PORTO DE SALVADOR - INTERMARITIMA TERMINAIS LTDA. | P27: 11426377000123 | R27: 202200151434298 | S27: 46540 | T27: 26/12/2024 - Juntada efetuada 23/12/2024 - Docs recebidos 28/10/2024 - Cobrado procedimento a ser adotado 27/09/2024 - Juntada efetuada 27/09/2024 - Docs recebidos 09/09/2024 - Cobrado novamente 05/08/2024 - Cobrado procedimento a ser adotado 28/06/2024 - Juntada efetuada 27/06/2024 - Docs recebidos 14/06/2024 - Numerario enviado, ag retorno 13/06/2024 - Solicitado prorrogação por mais 3 meses 30/04/2024 - Cobrado procedimento a ser adotado 26/12/2023 - Juntada efetuada. 22/11/2023 - Informado que será prorrogado por mais 6 meses, Numerario e RPR enviados, ag retorno 30/10/2023 - Cobrado procedimento a ser adotado 28/06/2023 - Juntada efetuada através do DOSSIE 28/06/2023 - Recebido documentos 27/06/2023 - Cobrado retorno 01/06/2023 - Solicitado prorrogação por 6 meses, Numerario, TR e RAT enviados, aguardando retorno 26/04/2023 - Cobrado procedimento a ser adotado 28/07/2022 - Processo incluido no controle | U27: MARÍTIMO | V27: ="'"&SUBSTITUTE(T27,CHAR(10),"' + CHAR(13) + CHAR(10) + "&CHAR(10)&"'")&"'" -> '26/12/2024 - Juntada efetuada' + CHAR(13) + CHAR(10) + '23/12/2024 - Docs recebidos' + CHAR(13) + CHAR(10) + '28/10/2024 - Cobrado procedimento a ser adotado' + CHAR(13) + CHAR(10) + '27/09/2024 - Juntada efetuada' + CHAR(13) + CHAR(10) + '27/09/2024 - Docs recebidos' + CHAR(13) + CHAR(10) + '09/09/2024 - Cobrado novamente' + CHAR(13) + CHAR(10) + '05/08/2024 - Cobrado procedimento a ser adotado' + CHAR(13) + CHAR(10) + '28/06/2024 - Juntada efetuada' + CHAR(13) + CHAR(10) + '27/06/2024 - Docs recebidos' + CHAR(13) + CHAR(10) + '14/06/2024 - Numerario enviado, ag retorno' + CHAR(13) + CHAR(10) + '13/06/2024 - Solicitado prorrogação por mais 3 meses' + CHAR(13) + CHAR(10) + '30/04/2024 - Cobrado procedimento a ser adotado' + CHAR(13) + CHAR(10) + '26/12/2023 - Juntada efetuada.' + CHAR(13) + CHAR(10) + '22/11/2023 - Informado que será prorrogado por mais 6 meses, Numerario e RPR enviados, ag retorno' + CHAR(13) + CHAR(10) + '30/10/2023 - Cobrado procedimento a ser adotado' + CHAR(13) + CHAR(10) + '28/06/2023 - Juntada efetuada através do DOSSIE' + CHAR(13) + CHAR(10) + '28/06/2023 - Recebido documentos' + CHAR(13) + CHAR(10) + '27/06/2023 - Cobrado retorno' + CHAR(13) + CHAR(10) + '01/06/2023 - Solicitado prorrogação por 6 meses, Numerario, TR e RAT enviados, aguardando retorno' + CHAR(13) + CHAR(10) + '26/04/2023 - Cobrado procedimento a ser adotado' + CHAR(13) + CHAR(10) + '28/07/2022 - Processo incluido no controle' | W27: WHEN 25 THEN '26/12/2024 - Juntada efetuada' + CHAR(13) + CHAR(10) + '23/12/2024 - Docs recebidos' + CHAR(13) + CHAR(10) + '28/10/2024 - Cobrado procedimento a ser adotado' + CHAR(13) + CHAR(10) + '27/09/2024 - Juntada efetuada' + CHAR(13) + CHAR(10) + '27/09/2024 - Docs recebidos' + CHAR(13) + CHAR(10) + '09/09/2024 - Cobrado novamente' + CHAR(13) + CHAR(10) + '05/08/2024 - Cobrado procedimento a ser adotado' + CHAR(13) + CHAR(10) + '28/06/2024 - Juntada efetuada' + CHAR(13) + CHAR(10) + '27/06/2024 - Docs recebidos' + CHAR(13) + CHAR(10) + '14/06/2024 - Numerario enviado, ag retorno' + CHAR(13) + CHAR(10) + '13/06/2024 - Solicitado prorrogação por mais 3 meses' + CHAR(13) + CHAR(10) + '30/04/2024 - Cobrado procedimento a ser adotado' + CHAR(13) + CHAR(10) + '26/12/2023 - Juntada efetuada.' + CHAR(13) + CHAR(10) + '22/11/2023 - Informado que será prorrogado por mais 6 meses, Numerario e RPR enviados, ag retorno' + CHAR(13) + CHAR(10) + '30/10/2023 - Cobrado procedimento a ser adotado' + CHAR(13) + CHAR(10) + '28/06/2023 - Juntada efetuada através do DOSSIE' + CHAR(13) + CHAR(10) + '28/06/2023 - Recebido documentos' + CHAR(13) + CHAR(10) + '27/06/2023 - Cobrado retorno' + CHAR(13) + CHAR(10) + '01/06/2023 - Solicitado prorrogação por 6 meses, Numerario, TR e RAT enviados, aguardando retorno' + CHAR(13) + CHAR(10) + '26/04/2023 - Cobrado procedimento a ser adotado' + CHAR(13) + CHAR(10) + '28/07/2022 - Processo incluido no controle' | X27: WHEN 25 THEN 'GUINDASTE AUTOPROPELIDO SOBRE ESTEIRAS, MARCA KOBELCO, MODELO CK1100 , NÚMERO DE SERIE GH04-03371, ANO DE FABRICAÇÃO 2014 - USADO, NÚMERO DA FROTA 2611, COMPUTADORIZADO, ACIONADO POR MOTOR DIESEL, CAPACIDADE DE 110 TONELADAS, CONTRA-PESOS, COM TODOS ACESSÓRIOS PARA SEU FUNCIONAMENTO ATÉ 28 METROS DE LANÇA, DESMONTADO PARCIALMENTE PARA MANUSEIO E TRANSPORTE.'
A28: =B28&" - "&COUNTIF($B$3:B28,B28) -> MAMMOET - 20 | B28: MAMMOET | C28: 2210475103 | D28: I-22/0630-MBG | E28: RT890E | F28: SUSPENSA | G28: 102205119780793 | H28: =EDATE(I28,-1) -> 45716 | I28: =EDATE(LEFT(L28,10),-1) -> 45745 | J28: S/NR. | K28: Caminhão Guindaste sobre Pneu com lança telescópica até 50 metros, capacidade máxima de elevação 90 toneladas, com 2 eixos totais sendo 2 eixos direcionáveis, pronto para manuseio e operação. Marca Grove, modelo RT890E, usado, ano de fabricação 2012, numero de série 232649, frota 2144. | L28: 45776 | M28: 44714 | N28: 44741 | O28: PORTO DE SALVADOR - INTERMARITIMA TERMINAIS LTDA. | P28: 11426377000123 | R28: 202200151564345 | S28: 46540 | T28: 26/12/2024 - Juntada efetuada 23/12/2024 - Docs recebidos 08/11/2024 - Cobrado procedimento a ser adotado 28/09/2024 - Juntada efetuada 27/09/2024 - Docs recebidos 09/09/2024 - Cobrado novamente 05/08/2024 - Cobrado procedimento a ser adotado 28/06/2024 - Juntada efetuada 27/06/2024 - Docs recebidos 14/06/2024 - Numerario enviado, ag retorno 13/06/2024 - Solicitado prorrogação por mais 3 meses 30/04/2024 - Cobrado procedimento a ser adotado 28/12/2023 - Juntada efetuada 22/12/2023 - Recebido docs 30/11/2023 - Numerario e RPR enviados, ag retorno[ 22/11/2023 - Solicitado prorrogaçção por mais 6 meses 30/10/2023 - Cobrado procedimento a ser adotado 03/07/2023 - Juntada efetuada através do DOSSIE, Apolice recebida em 30/06 a noite 28/06/2023 - Docs recebidos, exceto APOLICE. Anexado ao DOSSIE o que foi recebido 27/06/2023 - Cobrado retorno 01/06/2023 - Solicitado prorrogação por 6 meses, Numerario, TR e RAT enviados, aguardando retorno 26/04/2023 - Cobrado procedimento a ser adotado 28/07/2022 - Processo incluido no controle | U28: MARÍTIMO | V28: ="'"&SUBSTITUTE(T28,CHAR(10),"' + CHAR(13) + CHAR(10) + "&CHAR(10)&"'")&"'" -> '26/12/2024 - Juntada efetuada' + CHAR(13) + CHAR(10) + '23/12/2024 - Docs recebidos' + CHAR(13) + CHAR(10) + '08/11/2024 - Cobrado procedimento a ser adotado' + CHAR(13) + CHAR(10) + '28/09/2024 - Juntada efetuada' + CHAR(13) + CHAR(10) + '27/09/2024 - Docs recebidos' + CHAR(13) + CHAR(10) + '09/09/2024 - Cobrado novamente' + CHAR(13) + CHAR(10) + '05/08/2024 - Cobrado procedimento a ser adotado' + CHAR(13) + CHAR(10) + '28/06/2024 - Juntada efetuada' + CHAR(13) + CHAR(10) + '27/06/2024 - Docs recebidos' + CHAR(13) + CHAR(10) + '14/06/2024 - Numerario enviado, ag retorno' + CHAR(13) + CHAR(10) + '13/06/2024 - Solicitado prorrogação por mais 3 meses' + CHAR(13) + CHAR(10) + '30/04/2024 - Cobrado procedimento a ser adotado' + CHAR(13) + CHAR(10) + '28/12/2023 - Juntada efetuada' + CHAR(13) + CHAR(10) + '22/12/2023 - Recebido docs' + CHAR(13) + CHAR(10) + '30/11/2023 - Numerario e RPR enviados, ag retorno[' + CHAR(13) + CHAR(10) + '22/11/2023 - Solicitado prorrogaçção por mais 6 meses' + CHAR(13) + CHAR(10) + '30/10/2023 - Cobrado procedimento a ser adotado' + CHAR(13) + CHAR(10) + '03/07/2023 - Juntada efetuada através do DOSSIE, Apolice recebida em 30/06 a noite' + CHAR(13) + CHAR(10) + '28/06/2023 - Docs recebidos, exceto APOLICE. Anexado ao DOSSIE o que foi recebido' + CHAR(13) + CHAR(10) + '27/06/2023 - Cobrado retorno' + CHAR(13) + CHAR(10) + '01/06/2023 - Solicitado prorrogação por 6 meses, Numerario, TR e RAT enviados, aguardando retorno' + CHAR(13) + CHAR(10) + '26/04/2023 - Cobrado procedimento a ser adotado' + CHAR(13) + CHAR(10) + '28/07/2022 - Processo incluido no controle' | W28: WHEN 26 THEN '26/12/2024 - Juntada efetuada' + CHAR(13) + CHAR(10) + '23/12/2024 - Docs recebidos' + CHAR(13) + CHAR(10) + '08/11/2024 - Cobrado procedimento a ser adotado' + CHAR(13) + CHAR(10) + '28/09/2024 - Juntada efetuada' + CHAR(13) + CHAR(10) + '27/09/2024 - Docs recebidos' + CHAR(13) + CHAR(10) + '09/09/2024 - Cobrado novamente' + CHAR(13) + CHAR(10) + '05/08/2024 - Cobrado procedimento a ser adotado' + CHAR(13) + CHAR(10) + '28/06/2024 - Juntada efetuada' + CHAR(13) + CHAR(10) + '27/06/2024 - Docs recebidos' + CHAR(13) + CHAR(10) + '14/06/2024 - Numerario enviado, ag retorno' + CHAR(13) + CHAR(10) + '13/06/2024 - Solicitado prorrogação por mais 3 meses' + CHAR(13) + CHAR(10) + '30/04/2024 - Cobrado procedimento a ser adotado' + CHAR(13) + CHAR(10) + '28/12/2023 - Juntada efetuada' + CHAR(13) + CHAR(10) + '22/12/2023 - Recebido docs' + CHAR(13) + CHAR(10) + '30/11/2023 - Numerario e RPR enviados, ag retorno[' + CHAR(13) + CHAR(10) + '22/11/2023 - Solicitado prorrogaçção por mais 6 meses' + CHAR(13) + CHAR(10) + '30/10/2023 - Cobrado procedimento a ser adotado' + CHAR(13) + CHAR(10) + '03/07/2023 - Juntada efetuada através do DOSSIE, Apolice recebida em 30/06 a noite' + CHAR(13) + CHAR(10) + '28/06/2023 - Docs recebidos, exceto APOLICE. Anexado ao DOSSIE o que foi recebido' + CHAR(13) + CHAR(10) + '27/06/2023 - Cobrado retorno' + CHAR(13) + CHAR(10) + '01/06/2023 - Solicitado prorrogação por 6 meses, Numerario, TR e RAT enviados, aguardando retorno' + CHAR(13) + CHAR(10) + '26/04/2023 - Cobrado procedimento a ser adotado' + CHAR(13) + CHAR(10) + '28/07/2022 - Processo incluido no controle' | X28: WHEN 26 THEN 'CAMINHÃO GUINDASTE SOBRE PNEU COM LANÇA TELESCÓPICA ATÉ 50 METROS, CAPACIDADE MÁXIMA DE ELEVAÇÃO 90 TONELADAS, COM 2 EIXOS TOTAIS SENDO 2 EIXOS DIRECIONÁVEIS, PRONTO PARA MANUSEIO E OPERAÇÃO. MARCA GROVE, MODELO RT890E, USADO, ANO DE FABRICAÇÃO 2012, NUMERO DE SÉRIE 232649, FROTA 2144.'
A29: =B29&" - "&COUNTIF($B$3:B29,B29) -> MARLIM AZUL - 1 | B29: MARLIM AZUL | C29: 240006359556 | D29: E-24/0119-MRL | H29: =EDATE(I29,-1) -> 45717 | I29: =EDATE(LEFT(L29,10),-1) -> 45748 | J29: LAUDO DE IDNETIFICAÇÃO DE MERCADORIAS | K29: DIVERSOS EQUIPAMENTOS CONFORME DUE | L29: 45778 | M29: 45399 | N29: 45413 | O29: AEROPORTO INTERNACIONAL DE SAO PAULO/GUARULHOS | P29: 29884534000290 | R29: 202400233843302 | T29: 15/05/2024 - Processo incluído no controle | U29: AÉREO | V29: ="'"&SUBSTITUTE(T29,CHAR(10),"' + CHAR(13) + CHAR(10) + "&CHAR(10)&"'")&"'" -> '15/05/2024 - Processo incluído no controle' | W29: WHEN 27 THEN '15/05/2024 - Processo incluído no controle' | X29: WHEN 27 THEN 'DIVERSOS EQUIPAMENTOS CONFORME DUE'
A30: =B30&" - "&COUNTIF($B$3:B30,B30) -> MAMMOET - 21 | B30: MAMMOET | C30: 2104031884 | D30: I-21/0242-MBG | E30: MID POINTS | H30: =EDATE(I30,-1) -> 45720 | I30: =EDATE(LEFT(L30,10),-1) -> 45751 | J30: CONTRATO DE LOCAÇÃO S/NR DATADO DE 30/07/2020 | K30: Conjunto tensor para lança de 108 metros, tipo SSL/LSL, marca Terex, sem numero de serie , ano de fabricação 2008 | L30: 45781 | M30: 44256 | N30: 44263 | O30: EADI EMBRAGEM-SP | P30: 11426377000123 | Q30: 13032.193464/2021-68 | R30: 202100101144776 | T30: 10/12/2024 - Despacho 04/12/2024 - Juntada efetuda 25/11/2024 - Solicitado prorrogaçao por mais 6 meses, ag retorno 18/11/2024 - Despacho 13/11/2024 - Intimaçao 06/11/2024 - Cobrado procedimento a ser adotado 01/11/2024 - Juntada efetuada 30/10/2024 - Docs recebidos 18/10/2024 - Numerario enviado, ag retorno 17/10/2024 - Solicitado renovaçao por mais 1 mes 14/10/2024 - Cobrado novamente 09/09/2024 - Cobrado procedimento a ser adotado 04/07/2024 - Juntada efetuada 02/07/2024 - Docs recebidos 25/06/2024 - Solicitado prorrogaçao por mais 4 meses, numerario enviado, ag retorno 10/06/2024 - Cobrado procedimento 05/06/2024 - Juntada efetuada 29/05/2024 - Docs recebidos 24/05/2024 - Enviado Numerario e RPR, ag retorno 21/05/2024 - Solicitadoprorrogação por mais 1 mes 08/05/2024 - Cobrado novamente 05/04/2024 - Cobrado procedimento a ser adotado 04/01/2024 - Juntada efetuada 03/01/2024 - Docs recebidos 08/11/2023 - Cobrado procedimento a ser adotado 14/07/2023 - Despacho decisorio 03/07/2023 - Juntada efetuada através do DOSSIÊ 28/06/2023 - Docs recebidos 20/06/2023 - Numerario e TR enviado, ag retorno 19/06/2023 - Informado que será prorrogado por 6 meses 09/05/2023 - Cobrado procedimento a ser adotado 21/03/2023 - Despacho Decisorio 01/03/2023 - Juntada efetuada atravé do DOSSIE 28/02/2023 - Cobrado retorno, recebido documentação 08/02/2023 - Solicitado prorrogação, enviado numerário, aguardando retorno 10/01/2023 - Cobrado procedimento a ser adotado 22/03/2022 - Despacho Decisorio 16/02/2022 - Juntada anexada através do DOSSIE 08/02/2022 - Solicitado prorrogação por 12 meses, solicitação de numerário enviada, ag retorno 05/01/2022 - Cobrado procedimento a ser adotado 14/09/2021 - Despacho Decisorio 30/08/2021 - Docs recebidos, docs anexados ao DOSSIE 06/08/2021 - Solicitado renovação por 6 meses, enviado numerário, ag docs 13/07/2021 Cobrado procedimento a ser adotado 11/05/2021 - Processo incluído no controle | U30: AÉREO | V30: ="'"&SUBSTITUTE(T30,CHAR(10),"' + CHAR(13) + CHAR(10) + "&CHAR(10)&"'")&"'" -> '10/12/2024 - Despacho' + CHAR(13) + CHAR(10) + '04/12/2024 - Juntada efetuda' + CHAR(13) + CHAR(10) + '25/11/2024 - Solicitado prorrogaçao por mais 6 meses, ag retorno' + CHAR(13) + CHAR(10) + '18/11/2024 - Despacho' + CHAR(13) + CHAR(10) + '13/11/2024 - Intimaçao' + CHAR(13) + CHAR(10) + '06/11/2024 - Cobrado procedimento a ser adotado' + CHAR(13) + CHAR(10) + '01/11/2024 - Juntada efetuada' + CHAR(13) + CHAR(10) + '30/10/2024 - Docs recebidos' + CHAR(13) + CHAR(10) + '18/10/2024 - Numerario enviado, ag retorno' + CHAR(13) + CHAR(10) + '17/10/2024 - Solicitado renovaçao por mais 1 mes' + CHAR(13) + CHAR(10) + '14/10/2024 - Cobrado novamente' + CHAR(13) + CHAR(10) + '09/09/2024 - Cobrado procedimento a ser adotado' + CHAR(13) + CHAR(10) + '04/07/2024 - Juntada efetuada' + CHAR(13) + CHAR(10) + '02/07/2024 - Docs recebidos' + CHAR(13) + CHAR(10) + '25/06/2024 - Solicitado prorrogaçao por mais 4 meses, numerario enviado, ag retorno' + CHAR(13) + CHAR(10) + '10/06/2024 - Cobrado procedimento' + CHAR(13) + CHAR(10) + '05/06/2024 - Juntada efetuada' + CHAR(13) + CHAR(10) + '29/05/2024 - Docs recebidos' + CHAR(13) + CHAR(10) + '24/05/2024 - Enviado Numerario e RPR, ag retorno' + CHAR(13) + CHAR(10) + '21/05/2024 - Solicitadoprorrogação por mais 1 mes' + CHAR(13) + CHAR(10) + '08/05/2024 - Cobrado novamente' + CHAR(13) + CHAR(10) + '05/04/2024 - Cobrado procedimento a ser adotado' + CHAR(13) + CHAR(10) + '04/01/2024 - Juntada efetuada' + CHAR(13) + CHAR(10) + '03/01/2024 - Docs recebidos' + CHAR(13) + CHAR(10) + '08/11/2023 - Cobrado procedimento a ser adotado' + CHAR(13) + CHAR(10) + '14/07/2023 - Despacho decisorio' + CHAR(13) + CHAR(10) + '03/07/2023 - Juntada efetuada através do DOSSIÊ' + CHAR(13) + CHAR(10) + '28/06/2023 - Docs recebidos' + CHAR(13) + CHAR(10) + '20/06/2023 - Numerario e TR enviado, ag retorno' + CHAR(13) + CHAR(10) + '19/06/2023 - Informado que será prorrogado por 6 meses' + CHAR(13) + CHAR(10) + '09/05/2023 - Cobrado procedimento a ser adotado' + CHAR(13) + CHAR(10) + '21/03/2023 - Despacho Decisorio' + CHAR(13) + CHAR(10) + '01/03/2023 - Juntada efetuada atravé do DOSSIE' + CHAR(13) + CHAR(10) + '28/02/2023 - Cobrado retorno, recebido documentação' + CHAR(13) + CHAR(10) + '08/02/2023 - Solicitado prorrogação, enviado numerário, aguardando retorno' + CHAR(13) + CHAR(10) + '10/01/2023 - Cobrado procedimento a ser adotado' + CHAR(13) + CHAR(10) + '22/03/2022 - Despacho Decisorio' + CHAR(13) + CHAR(10) + '16/02/2022 - Juntada anexada através do DOSSIE' + CHAR(13) + CHAR(10) + '08/02/2022 - Solicitado prorrogação por 12 meses, solicitação de numerário enviada, ag retorno' + CHAR(13) + CHAR(10) + '05/01/2022 - Cobrado procedimento a ser adotado' + CHAR(13) + CHAR(10) + '14/09/2021 - Despacho Decisorio' + CHAR(13) + CHAR(10) + '30/08/2021 - Docs recebidos, docs anexados ao DOSSIE' + CHAR(13) + CHAR(10) + '06/08/2021 - Solicitado renovação por 6 meses, enviado numerário, ag docs' + CHAR(13) + CHAR(10) + '13/07/2021 Cobrado procedimento a ser adotado' + CHAR(13) + CHAR(10) + '11/05/2021 - Processo incluído no controle' | W30: WHEN 28 THEN '10/12/2024 - Despacho' + CHAR(13) + CHAR(10) + '04/12/2024 - Juntada efetuda' + CHAR(13) + CHAR(10) + '25/11/2024 - Solicitado prorrogaçao por mais 6 meses, ag retorno' + CHAR(13) + CHAR(10) + '18/11/2024 - Despacho' + CHAR(13) + CHAR(10) + '13/11/2024 - Intimaçao' + CHAR(13) + CHAR(10) + '06/11/2024 - Cobrado procedimento a ser adotado' + CHAR(13) + CHAR(10) + '01/11/2024 - Juntada efetuada' + CHAR(13) + CHAR(10) + '30/10/2024 - Docs recebidos' + CHAR(13) + CHAR(10) + '18/10/2024 - Numerario enviado, ag retorno' + CHAR(13) + CHAR(10) + '17/10/2024 - Solicitado renovaçao por mais 1 mes' + CHAR(13) + CHAR(10) + '14/10/2024 - Cobrado novamente' + CHAR(13) + CHAR(10) + '09/09/2024 - Cobrado procedimento a ser adotado' + CHAR(13) + CHAR(10) + '04/07/2024 - Juntada efetuada' + CHAR(13) + CHAR(10) + '02/07/2024 - Docs recebidos' + CHAR(13) + CHAR(10) + '25/06/2024 - Solicitado prorrogaçao por mais 4 meses, numerario enviado, ag retorno' + CHAR(13) + CHAR(10) + '10/06/2024 - Cobrado procedimento' + CHAR(13) + CHAR(10) + '05/06/2024 - Juntada efetuada' + CHAR(13) + CHAR(10) + '29/05/2024 - Docs recebidos' + CHAR(13) + CHAR(10) + '24/05/2024 - Enviado Numerario e RPR, ag retorno' + CHAR(13) + CHAR(10) + '21/05/2024 - Solicitadoprorrogação por mais 1 mes' + CHAR(13) + CHAR(10) + '08/05/2024 - Cobrado novamente' + CHAR(13) + CHAR(10) + '05/04/2024 - Cobrado procedimento a ser adotado' + CHAR(13) + CHAR(10) + '04/01/2024 - Juntada efetuada' + CHAR(13) + CHAR(10) + '03/01/2024 - Docs recebidos' + CHAR(13) + CHAR(10) + '08/11/2023 - Cobrado procedimento a ser adotado' + CHAR(13) + CHAR(10) + '14/07/2023 - Despacho decisorio' + CHAR(13) + CHAR(10) + '03/07/2023 - Juntada efetuada através do DOSSIÊ' + CHAR(13) + CHAR(10) + '28/06/2023 - Docs recebidos' + CHAR(13) + CHAR(10) + '20/06/2023 - Numerario e TR enviado, ag retorno' + CHAR(13) + CHAR(10) + '19/06/2023 - Informado que será prorrogado por 6 meses' + CHAR(13) + CHAR(10) + '09/05/2023 - Cobrado procedimento a ser adotado' + CHAR(13) + CHAR(10) + '21/03/2023 - Despacho Decisorio' + CHAR(13) + CHAR(10) + '01/03/2023 - Juntada efetuada atravé do DOSSIE' + CHAR(13) + CHAR(10) + '28/02/2023 - Cobrado retorno, recebido documentação' + CHAR(13) + CHAR(10) + '08/02/2023 - Solicitado prorrogação, enviado numerário, aguardando retorno' + CHAR(13) + CHAR(10) + '10/01/2023 - Cobrado procedimento a ser adotado' + CHAR(13) + CHAR(10) + '22/03/2022 - Despacho Decisorio' + CHAR(13) + CHAR(10) + '16/02/2022 - Juntada anexada através do DOSSIE' + CHAR(13) + CHAR(10) + '08/02/2022 - Solicitado prorrogação por 12 meses, solicitação de numerário enviada, ag retorno' + CHAR(13) + CHAR(10) + '05/01/2022 - Cobrado procedimento a ser adotado' + CHAR(13) + CHAR(10) + '14/09/2021 - Despacho Decisorio' + CHAR(13) + CHAR(10) + '30/08/2021 - Docs recebidos, docs anexados ao DOSSIE' + CHAR(13) + CHAR(10) + '06/08/2021 - Solicitado renovação por 6 meses, enviado numerário, ag docs' + CHAR(13) + CHAR(10) + '13/07/2021 Cobrado procedimento a ser adotado' + CHAR(13) + CHAR(10) + '11/05/2021 - Processo incluído no controle' | X30: WHEN 28 THEN 'CONJUNTO TENSOR PARA LANÇA DE 108 METROS, TIPO SSL/LSL, MARCA TEREX, SEM NUMERO DE SERIE , ANO DE FABRICAÇÃO 2008'
